Workbook
Name Año1: INICIO!$B$28
Name Año2: INICIO!$C$28
Name Año3: INICIO!$D$28
Name Año4: INICIO!$E$28
Name Año5: INICIO!$F$28
Name Producto1: INICIO!$B$40
Name Producto10: INICIO!$B$49
Name Producto11: INICIO!$B$50
Name Producto12: INICIO!$B$51
Name Producto13: INICIO!$B$52
Name Producto14: INICIO!$B$53
Name Producto15: INICIO!$B$54
Name Producto2: INICIO!$B$41
Name Producto3: INICIO!$B$42
Name Producto4: INICIO!$B$43
Name Producto5: INICIO!$B$44
Name Producto6: INICIO!$B$45
Name Producto7: INICIO!$B$46
Name Producto8: INICIO!$B$47
Name Producto9: INICIO!$B$48

Sheet INICIO
A9: Información General
A10: NOMBRE DE LA EMPRESA | B10: TIZA
A11: TIPO DE SOCIEDAD | B11: S.A.S
A12: AÑO DE INICIO DE OPERACIONES | B12: 2027
A13: PAÍS DONDE ESTAN LOS CLIENTES | B13: COLOMBIA
A14: MONEDA DE REFERENCIA | B14: COP
A17: Información general sobre los estudiantes a cargo del proyecto y socios adicionales
A18: NOMBRE DEL SOCIO | B18: TIPO DE SOCIO | C18: PARTICIPACIÓN
A19: Danna Sanchez | B19: ESTUDIANTE | C19: 0.25
A20: Sergio Nieto | B20: ESTUDIANTE | C20: 0.25
A21: Daniel Martin | B21: ESTUDIANTE | C21: 0.25
A22: Christian Morales | B22: ESTUDIANTE | C22: 0.25
A23: INVERSOR 5
A24: INVERSOR 6
A26: Variables Macroeconómicas y otros datos de interés
A27: VARIABLES | B27: AÑO
B28: =B12 -> 2027 | C28: =B28+1 -> 2028 | D28: =C28+1 -> 2029 | E28: =D28+1 -> 2030 | F28: =E28+1 -> 2031
A29: Tasa de cambio proyectada (COP/USD) | B29: 4150 | C29: 4280 | D29: 4410 | E29: 4410 | F29: 4410
A30: Inflación Anual Esperada | B30: 0.05 | C30: 0.042 | D30: 0.038 | E30: 0.035 | F30: 0.033
A31: Tasa de Crecimiento de la Industria (proyectada) | B31: =(12%*50%)+(4%*50%) -> 0.08 | C31: =(12%*50%)+(4%*50%) -> 0.08 | D31: =(12%*50%)+(4%*50%) -> 0.08 | E31: =(12%*50%)+(4%*50%) -> 0.08 | F31: =(12%*50%)+(4%*50%) -> 0.08
A32: Salario Mínimo Mensual Legal Vigente proyectado | B32: 1856000 | C32: 1949000 | D32: 2036000 | E32: 2118000 | F32: 2203000
A33: Auxilio de Transporte Legal Proyectado | B33: 268000 | C33: 282000 | D33: 294000 | E33: 306000 | F33: 318000
A34: Tasa del Impuesto de Renta Esperada | B34: 0.35 | C34: 0.35 | D34: 0.35 | E34: 0.35 | F34: 0.35
A39: PORTAFOLIO DE PRODUCTOS Y/O SERVICIOS | B39: NOMBRE DEL PRODUCTO O SERVICIO
A40: PRODUCTO O SERVICIO 1 | B40: Suscripcion Freemium
A41: PRODUCTO O SERVICIO 2 | B41: Suscripcion Premium
A42: PRODUCTO O SERVICIO 3
A43: PRODUCTO O SERVICIO 4
A44: PRODUCTO O SERVICIO 5
A45: PRODUCTO O SERVICIO 6
A46: PRODUCTO O SERVICIO 7
A47: PRODUCTO O SERVICIO 8
A48: PRODUCTO O SERVICIO 9
A49: PRODUCTO O SERVICIO 10
A50: PRODUCTO O SERVICIO 11
A51: PRODUCTO O SERVICIO 12
A52: PRODUCTO O SERVICIO 13
A53: PRODUCTO O SERVICIO 14
A54: PRODUCTO O SERVICIO 15
A56: GASTOS PREOPERATIVOS | B56: AÑO
B57: =Año1-1 -> 2026 | C57: =Año1 -> 2027 | D57: =C57+1 -> 2028 | E57: =D57+1 -> 2029 | F57: =E57+1 -> 2030 | G57: =F57+1 -> 2031
A58: Registro en Camara de Comercio | B58: 232000
A59: Diseño de marca y branding | B59: 500000
A60: Hosting y dominio (configuración inicial) | B60: 350000
A61: Licencias herramientas de desarrollo | B61: 800000
A62: Certificado SSL y seguridad | B62: 200000
A63: Prototipado y pruebas de usabilidad | B63: 300000
A65: TOTAL GASTOS PRE-OPERATIVOS | B65: =SUM(B58:B64) -> 2382000 | C65: =SUM(C58:C64) -> 0 | D65: =SUM(D58:D64) -> 0 | E65: =SUM(E58:E64) -> 0 | F65: =SUM(F58:F64) -> 0 | G65: =SUM(G58:G64) -> 0
A67: Riesgos Laborales
A68: Tipo de Riesgo | B68: Valor
A69: I | B69: 0.00522
A70: II | B70: 0.01044
A71: III | B71: 0.02436
A72: IV | B72: 0.0435
A73: V | B73: 0.0696
A77: Plantilla Realizada por María Teresa Macías Joven
A78: Universidad de La Sabana
A79: Versión 2025
A80: ®Todos los derechos reservados
A81: Si desea utilizar esta plantilla por fuera del programa Expo-Empresarial, clase de proyecto empresarial de la Universidad de La Sabana, asegúrese de poseer los derechos de uso por parte de la autora de la plantilla, con una autorización clara, expresa y por escrito.

Sheet INGRESOS
B1: =CONCATENATE(INICIO!$B$10," ",INICIO!$B$11) -> TIZA S.A.S
B5: PRESUPUESTO DE VENTAS
A9: PLAZO DE COBRO | B9: =Año1 -> 2027 | N9: =Año2 -> 2028 | Z9: =Año3 -> 2029 | AL9: =Año4 -> 2030 | AX9: =Año5 -> 2031
B10: Mes 1 | C10: Mes 2 | D10: Mes 3 | E10: Mes 4 | F10: Mes 5 | G10: Mes 6 | H10: Mes 7 | I10: Mes 8 | J10: Mes 9 | K10: Mes 10 | L10: Mes 11 | M10: Mes 12 | N10: Mes 13 | O10: Mes 14 | P10: Mes 15 | Q10: Mes 16 | R10: Mes 17 | S10: Mes 18 | T10: Mes 19 | U10: Mes 20 | V10: Mes 21 | W10: Mes 22 | X10: Mes 23 | Y10: Mes 24 | Z10: Mes 25 | AA10: Mes 26 | AB10: Mes 27 | AC10: Mes 28 | AD10: Mes 29 | AE10: Mes 30 | AF10: Mes 31 | AG10: Mes 32 | AH10: Mes 33 | AI10: Mes 34 | AJ10: Mes 35 | AK10: Mes 36 | AL10: Mes 37 | AM10: Mes 38 | AN10: Mes 39 | AO10: Mes 40 | AP10: Mes 41 | AQ10: Mes 42 | AR10: Mes 43 | AS10: Mes 44 | AT10: Mes 45 | AU10: Mes 46 | AV10: Mes 47 | AW10: Mes 48 | AX10: Mes 49 | AY10: Mes 50 | AZ10: Mes 51 | BA10: Mes 52 | BB10: Mes 53 | BC10: Mes 54 | BD10: Mes 55 | BE10: Mes 56 | BF10: Mes 57 | BG10: Mes 58 | BH10: Mes 59 | BI10: Mes 60
A11: Plazo que otorgará a los clientes para que le paguen (en días) | B11: 0 | C11: 0 | D11: 0 | E11: 0 | F11: 0 | G11: 0 | H11: 0 | I11: 0 | J11: 0 | K11: 0 | L11: 0 | M11: 0 | N11: 0 | O11: 0 | P11: 0 | Q11: 0 | R11: 0 | S11: 0 | T11: 0 | U11: 0 | V11: 0 | W11: 0 | X11: 0 | Y11: 0 | Z11: 0 | AA11: 0 | AB11: 0 | AC11: 0 | AD11: 0 | AE11: 0 | AF11: 0 | AG11: 0 | AH11: 0 | AI11: 0 | AJ11: 0 | AK11: 0 | AL11: 0 | AM11: 0 | AN11: 0 | AO11: 0 | AP11: 0 | AQ11: 0 | AR11: 0 | AS11: 0 | AT11: 0 | AU11: 0 | AV11: 0 | AW11: 0 | AX11: 0 | AY11: 0 | AZ11: 0 | BA11: 0 | BB11: 0 | BC11: 0 | BD11: 0 | BE11: 0 | BF11: 0 | BG11: 0 | BH11: 0 | BI11: 0
A13: TOTAL INGRESOS | B13: =Año1 -> 2027 | N13: =Año2 -> 2028 | Z13: =Año3 -> 2029 | AL13: =Año4 -> 2030 | AX13: =Año5 -> 2031
B14: =B10 -> Mes 1 | C14: =C10 -> Mes 2 | D14: =D10 -> Mes 3 | E14: =E10 -> Mes 4 | F14: =F10 -> Mes 5 | G14: =G10 -> Mes 6 | H14: =H10 -> Mes 7 | I14: =I10 -> Mes 8 | ... BI14: =BI10 -> Mes 60
A15: =CONCATENATE("Total ingresos por ventas del producto o servicio"," ",Producto1) -> Total ingresos por ventas del producto o servicio Suscripcion Freemium | B15: 0 | C15: 0 | D15: 0 | E15: 0 | F15: 0 | G15: 0 | H15: 0 | I15: 0 | J15: 0 | K15: 0 | L15: 0 | M15: 0 | N15: 0 | O15: 0 | P15: 0 | Q15: 0 | R15: 0 | S15: 0 | T15: 0 | U15: 0 | V15: 0 | W15: 0 | X15: 0 | Y15: 0 | Z15: 0 | AA15: 0 | AB15: 0 | AC15: 0 | AD15: 0 | AE15: 0 | AF15: 0 | AG15: 0 | AH15: 0 | AI15: 0 | AJ15: 0 | AK15: 0 | AL15: 0 | AM15: 0 | AN15: 0 | AO15: 0 | AP15: 0 | AQ15: 0 | AR15: 0 | AS15: 0 | AT15: 0 | AU15: 0 | AV15: 0 | AW15: 0 | AX15: 0
A16: =CONCATENATE("Total ingresos por ventas del producto o servicio"," ",Producto2) -> Total ingresos por ventas del producto o servicio Suscripcion Premium | B16: 400000 | C16: 600000 | D16: 880000 | E16: 1200000 | F16: 1520000 | G16: 1800000 | H16: 2200000 | I16: 2600000 | J16: 3000000 | K16: 3400000 | L16: 3800000 | M16: 4400000 | N16: 5000000 | O16: 5800000 | P16: 6600000 | Q16: 7400000 | R16: 8400000 | S16: 9400000 | T16: 10400000 | U16: 11600000 | V16: 12800000 | W16: 14000000 | X16: 15200000 | Y16: 16800000 | Z16: 18400000 | AA16: 20000000 | AB16: 21800000 | AC16: 23600000 | AD16: 25600000 | AE16: 27600000 | AF16: 29800000 | AG16: 32000000 | AH16: 34400000 | AI16: 36800000 | AJ16: 39200000 | AK16: 42000000 | AL16: 44800000 | AM16: 47600000 | AN16: 50400000 | AO16: 53600000 | AP16: 56800000 | AQ16: 60000000 | AR16: 63200000 | AS16: 66400000 | AT16: 69600000 | AU16: 73200000 | AV16: 76800000 | AW16: 80800000 | AX16: 84800000
A17: =CONCATENATE("Total ingresos por ventas del producto o servicio"," ",Producto3) -> Total ingresos por ventas del producto o servicio
A18: =CONCATENATE("Total ingresos por ventas del producto o servicio"," ",Producto4) -> Total ingresos por ventas del producto o servicio
A19: =CONCATENATE("Total ingresos por ventas del producto o servicio"," ",Producto5) -> Total ingresos por ventas del producto o servicio
A20: =CONCATENATE("Total ingresos por ventas del producto o servicio"," ",Producto6) -> Total ingresos por ventas del producto o servicio
A21: =CONCATENATE("Total ingresos por ventas del producto o servicio"," ",Producto7) -> Total ingresos por ventas del producto o servicio
A22: =CONCATENATE("Total ingresos por ventas del producto o servicio"," ",Producto8) -> Total ingresos por ventas del producto o servicio
A23: =CONCATENATE("Total ingresos por ventas del producto o servicio"," ",Producto9) -> Total ingresos por ventas del producto o servicio
A24: =CONCATENATE("Total ingresos por ventas del producto o servicio"," ",Producto10) -> Total ingresos por ventas del producto o servicio
A25: =CONCATENATE("Total ingresos por ventas del producto o servicio"," ",Producto11) -> Total ingresos por ventas del producto o servicio
A26: =CONCATENATE("Total ingresos por ventas del producto o servicio"," ",Producto12) -> Total ingresos por ventas del producto o servicio
A27: =CONCATENATE("Total ingresos por ventas del producto o servicio"," ",Producto13) -> Total ingresos por ventas del producto o servicio
A28: =CONCATENATE("Total ingresos por ventas del producto o servicio"," ",Producto14) -> Total ingresos por ventas del producto o servicio
A29: =CONCATENATE("Total ingresos por ventas del producto o servicio"," ",Producto15) -> Total ingresos por ventas del producto o servicio
A30: TOTAL INGRESOS POR VENTAS | B30: =SUM(B15:B29) -> 400000 | C30: =SUM(C15:C29) -> 600000 | D30: =SUM(D15:D29) -> 880000 | E30: =SUM(E15:E29) -> 1200000 | F30: =SUM(F15:F29) -> 1520000 | G30: =SUM(G15:G29) -> 1800000 | H30: =SUM(H15:H29) -> 2200000 | I30: =SUM(I15:I29) -> 2600000 | ... BI30: =SUM(BI15:BI29) -> 0
A33: Plantilla Realizada por María Teresa Macías Joven
A34: Universidad de La Sabana
A35: Versión 2021
A36: ®Todos los derechos reservados
A37: Si desea utilizar esta plantilla por fuera del programa Expo-Empresarial, clase de proyecto empresarial de la Universidad de La Sabana, asegúrese de poseer los derechos de uso por parte de la autora de la plantilla, con una autorización clara, expresa y por escrito.

Sheet COSTOS
B1: =CONCATENATE(INICIO!$B$10," ",INICIO!$B$11) -> TIZA S.A.S
B5: PRESUPUESTO DE COSTOS
A8: PRONÓSTICO DE COSTOS RELACIONADOS A LA PRODUCCIÓN DEL PRODUCTO O SERVICIO | B8: =Año1 -> 2027 | N8: =Año2 -> 2028 | Z8: =Año3 -> 2029 | AL8: =Año4 -> 2030 | AX8: =Año5 -> 2031
B9: Mes 1 | C9: Mes 2 | D9: Mes 3 | E9: Mes 4 | F9: Mes 5 | G9: Mes 6 | H9: Mes 7 | I9: Mes 8 | J9: Mes 9 | K9: Mes 10 | L9: Mes 11 | M9: Mes 12 | N9: Mes 13 | O9: Mes 14 | P9: Mes 15 | Q9: Mes 16 | R9: Mes 17 | S9: Mes 18 | T9: Mes 19 | U9: Mes 20 | V9: Mes 21 | W9: Mes 22 | X9: Mes 23 | Y9: Mes 24 | Z9: Mes 25 | AA9: Mes 26 | AB9: Mes 27 | AC9: Mes 28 | AD9: Mes 29 | AE9: Mes 30 | AF9: Mes 31 | AG9: Mes 32 | AH9: Mes 33 | AI9: Mes 34 | AJ9: Mes 35 | AK9: Mes 36 | AL9: Mes 37 | AM9: Mes 38 | AN9: Mes 39 | AO9: Mes 40 | AP9: Mes 41 | AQ9: Mes 42 | AR9: Mes 43 | AS9: Mes 44 | AT9: Mes 45 | AU9: Mes 46 | AV9: Mes 47 | AW9: Mes 48 | AX9: Mes 49 | AY9: Mes 50 | AZ9: Mes 51 | BA9: Mes 52 | BB9: Mes 53 | BC9: Mes 54 | BD9: Mes 55 | BE9: Mes 56 | BF9: Mes 57 | BG9: Mes 58 | BH9: Mes 59 | BI9: Mes 60
A10: Suscripcion Geminy - API Key | B10: 48140 | C10: 51460 | D10: 56108 | E10: 61420 | F10: 66732 | G10: 71380 | H10: 78020 | I10: 84660 | J10: 91300 | K10: 97940 | L10: 104580 | M10: 114540 | N10: 128400 | O10: 142096 | P10: 155792 | Q10: 169488 | R10: 186608 | S10: 203728 | T10: 220848 | U10: 241392 | V10: 261936 | W10: 282480 | X10: 303024 | Y10: 330416 | Z10: 368676 | AA10: 396900 | AB10: 428652 | AC10: 460404 | AD10: 495684 | AE10: 530964 | AF10: 569772 | AG10: 608580 | AH10: 650916 | AI10: 693252 | AJ10: 735588 | AK10: 784980 | AL10: 834372 | AM10: 883764 | AN10: 933156 | AO10: 989604 | AP10: 1046052 | AQ10: 1102500 | AR10: 1158948 | AS10: 1215396 | AT10: 1271844 | AU10: 1335348 | AV10: 1398852 | AW10: 1469412 | AX10: 1539972
A11: Dominio Web | B11: 5187 | C11: 5187 | D11: 5187 | E11: 5187 | F11: 5187 | G11: 5187 | H11: 5187 | I11: 5187 | J11: 5187 | K11: 5187 | L11: 5187 | M11: 5187 | N11: 5350 | O11: 5350 | P11: 5350 | Q11: 5350 | R11: 5350 | S11: 5350 | T11: 5350 | U11: 5350 | V11: 5350 | W11: 5350 | X11: 5350 | Y11: 5350 | Z11: 5512 | AA11: 5512 | AB11: 5512 | AC11: 5512 | AD11: 5512 | AE11: 5512 | AF11: 5512 | AG11: 5512 | AH11: 5512 | AI11: 5512 | AJ11: 5512 | AK11: 5512 | AL11: 5512 | AM11: 5512 | AN11: 5512 | AO11: 5512 | AP11: 5512 | AQ11: 5512 | AR11: 5512 | AS11: 5512 | AT11: 5512 | AU11: 5512 | AV11: 5512 | AW11: 5512 | AX11: 5512
A12: Suscripcion Supabase | B12: 0 | C12: 0 | D12: 0 | E12: 0 | F12: 0 | G12: 0 | H12: 103750 | I12: 103750 | J12: 103750 | K12: 103750 | L12: 103750 | M12: 103750 | N12: 107000 | O12: 107000 | P12: 107000 | Q12: 107000 | R12: 107000 | S12: 107000 | T12: 107000 | U12: 107000 | V12: 107000 | W12: 107000 | X12: 107000 | Y12: 107000 | Z12: 220500 | AA12: 220500 | AB12: 220500 | AC12: 220500 | AD12: 220500 | AE12: 220500 | AF12: 220500 | AG12: 220500 | AH12: 220500 | AI12: 220500 | AJ12: 220500 | AK12: 220500 | AL12: 220500 | AM12: 220500 | AN12: 220500 | AO12: 220500 | AP12: 220500 | AQ12: 220500 | AR12: 220500 | AS12: 220500 | AT12: 220500 | AU12: 220500 | AV12: 220500 | AW12: 220500 | AX12: 220500
A13: Internet (uso de internet en operaciones) | B13: 68000 | C13: 68000 | D13: 68000 | E13: 68000 | F13: 68000 | G13: 68000 | H13: 68000 | I13: 68000 | J13: 68000 | K13: 68000 | L13: 68000 | M13: 68000 | N13: 71200 | O13: 71200 | P13: 71200 | Q13: 71200 | R13: 71200 | S13: 71200 | T13: 71200 | U13: 71200 | V13: 71200 | W13: 71200 | X13: 71200 | Y13: 71200 | Z13: 74400 | AA13: 74400 | AB13: 74400 | AC13: 74400 | AD13: 74400 | AE13: 74400 | AF13: 74400 | AG13: 74400 | AH13: 74400 | AI13: 74400 | AJ13: 74400 | AK13: 74400 | AL13: 77600 | AM13: 77600 | AN13: 77600 | AO13: 77600 | AP13: 77600 | AQ13: 77600 | AR13: 77600 | AS13: 77600 | AT13: 77600 | AU13: 77600 | AV13: 77600 | AW13: 77600 | AX13: 80800
A14: Enel | B14: 48000 | C14: 48000 | D14: 48000 | E14: 48000 | F14: 48000 | G14: 48000 | H14: 48000 | I14: 48000 | J14: 48000 | K14: 48000 | L14: 48000 | M14: 48000 | N14: 50400 | O14: 50400 | P14: 50400 | Q14: 50400 | R14: 50400 | S14: 50400 | T14: 50400 | U14: 50400 | V14: 50400 | W14: 50400 | X14: 50400 | Y14: 50400 | Z14: 52800 | AA14: 52800 | AB14: 52800 | AC14: 52800 | AD14: 52800 | AE14: 52800 | AF14: 52800 | AG14: 52800 | AH14: 52800 | AI14: 52800 | AJ14: 52800 | AK14: 52800 | AL14: 55200 | AM14: 55200 | AN14: 55200 | AO14: 55200 | AP14: 55200 | AQ14: 55200 | AR14: 55200 | AS14: 55200 | AT14: 55200 | AU14: 55200 | AV14: 55200 | AW14: 55200 | AX14: 57600
A25: TOTAL PRONOSTICO DE COSTOS | B25: =SUM(B10:B24) -> 169327 | C25: =SUM(C10:C24) -> 172647 | D25: =SUM(D10:D24) -> 177295 | E25: =SUM(E10:E24) -> 182607 | F25: =SUM(F10:F24) -> 187919 | G25: =SUM(G10:G24) -> 192567 | H25: =SUM(H10:H24) -> 302957 | I25: =SUM(I10:I24) -> 309597 | ... BI25: =SUM(BI10:BI24) -> 0
A28: PRONOSTICO NOMINA OPERATIVA | B28: =Año1 -> 2027 | N28: =Año2 -> 2028 | Z28: =Año3 -> 2029 | AL28: =Año4 -> 2030 | AX28: =Año5 -> 2031
B29: =B9 -> Mes 1 | C29: =C9 -> Mes 2 | D29: =D9 -> Mes 3 | E29: =E9 -> Mes 4 | F29: =F9 -> Mes 5 | G29: =G9 -> Mes 6 | H29: =H9 -> Mes 7 | I29: =I9 -> Mes 8 | ... BI29: =BI9 -> Mes 60
A30: Cargo | B30: Salario mensual | C30: Salario mensual | D30: Salario mensual | E30: Salario mensual | F30: Salario mensual | G30: Salario mensual | H30: Salario mensual | I30: Salario mensual | J30: Salario mensual | K30: Salario mensual | L30: Salario mensual | M30: Salario mensual | N30: Salario mensual | O30: Salario mensual | P30: Salario mensual | Q30: Salario mensual | R30: Salario mensual | S30: Salario mensual | T30: Salario mensual | U30: Salario mensual | V30: Salario mensual | W30: Salario mensual | X30: Salario mensual | Y30: Salario mensual | Z30: Salario mensual | AA30: Salario mensual | AB30: Salario mensual | AC30: Salario mensual | AD30: Salario mensual | AE30: Salario mensual | AF30: Salario mensual | AG30: Salario mensual | AH30: Salario mensual | AI30: Salario mensual | AJ30: Salario mensual | AK30: Salario mensual | AL30: Salario mensual | AM30: Salario mensual | AN30: Salario mensual | AO30: Salario mensual | AP30: Salario mensual | AQ30: Salario mensual | AR30: Salario mensual | AS30: Salario mensual | AT30: Salario mensual | AU30: Salario mensual | AV30: Salario mensual | AW30: Salario mensual | AX30: Salario mensual | AY30: Salario mensual | AZ30: Salario mensual | BA30: Salario mensual | BB30: Salario mensual | BC30: Salario mensual | BD30: Salario mensual | BE30: Salario mensual | BF30: Salario mensual | BG30: Salario mensual | BH30: Salario mensual | BI30: Salario mensual
A31: Desarrollador Junior 1 | B31: 3500000 | C31: 3500000 | D31: 3500000 | E31: 3500000 | F31: 3500000 | G31: 3500000 | H31: 3500000 | I31: 3500000 | J31: 3500000 | K31: 3500000 | L31: 3500000 | M31: 3500000 | N31: 3700000 | O31: 3700000 | P31: 3700000 | Q31: 3700000 | R31: 3700000 | S31: 3700000 | T31: 3700000 | U31: 3700000 | V31: 3700000 | W31: 3700000 | X31: 3700000 | Y31: 3700000 | Z31: 3900000 | AA31: 3900000 | AB31: 3900000 | AC31: 3900000 | AD31: 3900000 | AE31: 3900000 | AF31: 3900000 | AG31: 3900000 | AH31: 3900000 | AI31: 3900000 | AJ31: 3900000 | AK31: 3900000 | AL31: 4100000 | AM31: 4100000 | AN31: 4100000 | AO31: 4100000 | AP31: 4100000 | AQ31: 4100000 | AR31: 4100000 | AS31: 4100000 | AT31: 4100000 | AU31: 4100000 | AV31: 4100000 | AW31: 4100000 | AX31: 4100000
A32: Desarrollador Junior 2 | B32: 0 | C32: 0 | D32: 0 | E32: 0 | F32: 0 | G32: 0 | H32: 0 | I32: 0 | J32: 0 | K32: 0 | L32: 0 | M32: 0 | N32: 3700000 | O32: 3700000 | P32: 3700000 | Q32: 3700000 | R32: 3700000 | S32: 3700000 | T32: 3700000 | U32: 3700000 | V32: 3700000 | W32: 3700000 | X32: 3700000 | Y32: 3700000 | Z32: 3900000 | AA32: 3900000 | AB32: 3900000 | AC32: 3900000 | AD32: 3900000 | AE32: 3900000 | AF32: 3900000 | AG32: 3900000 | AH32: 3900000 | AI32: 3900000 | AJ32: 3900000 | AK32: 3900000 | AL32: 4100000 | AM32: 4100000 | AN32: 4100000 | AO32: 4100000 | AP32: 4100000 | AQ32: 4100000 | AR32: 4100000 | AS32: 4100000 | AT32: 4100000 | AU32: 4100000 | AV32: 4100000 | AW32: 4100000 | AX32: 4100000
A33: Desarrollador Mid | B33: 0 | C33: 0 | D33: 0 | E33: 0 | F33: 0 | G33: 0 | H33: 0 | I33: 0 | J33: 0 | K33: 0 | L33: 0 | M33: 0 | N33: 0 | O33: 0 | P33: 0 | Q33: 0 | R33: 0 | S33: 0 | T33: 0 | U33: 0 | V33: 0 | W33: 0 | X33: 0 | Y33: 0 | Z33: 5500000 | AA33: 5500000 | AB33: 5500000 | AC33: 5500000 | AD33: 5500000 | AE33: 5500000 | AF33: 5500000 | AG33: 5500000 | AH33: 5500000 | AI33: 5500000 | AJ33: 5500000 | AK33: 5500000 | AL33: 5800000 | AM33: 5800000 | AN33: 5800000 | AO33: 5800000 | AP33: 5800000 | AQ33: 5800000 | AR33: 5800000 | AS33: 5800000 | AT33: 5800000 | AU33: 5800000 | AV33: 5800000 | AW33: 5800000 | AX33: 5800000
A34: Desarrollador Senior | B34: 0 | C34: 0 | D34: 0 | E34: 0 | F34: 0 | G34: 0 | H34: 0 | I34: 0 | J34: 0 | K34: 0 | L34: 0 | M34: 0 | N34: 0 | O34: 0 | P34: 0 | Q34: 0 | R34: 0 | S34: 0 | T34: 0 | U34: 0 | V34: 0 | W34: 0 | X34: 0 | Y34: 0 | Z34: 0 | AA34: 0 | AB34: 0 | AC34: 0 | AD34: 0 | AE34: 0 | AF34: 0 | AG34: 0 | AH34: 0 | AI34: 0 | AJ34: 0 | AK34: 0 | AL34: 7500000 | AM34: 7500000 | AN34: 7500000 | AO34: 7500000 | AP34: 7500000 | AQ34: 7500000 | AR34: 7500000 | AS34: 7500000 | AT34: 7500000 | AU34: 7500000 | AV34: 7500000 | AW34: 7500000 | AX34: 7500000
A47: TOTAL NÓMINA OPERATIVA | B47: =SUM(B31:B46) -> 3500000 | C47: =SUM(C31:C46) -> 3500000 | D47: =SUM(D31:D46) -> 3500000 | E47: =SUM(E31:E46) -> 3500000 | F47: =SUM(F31:F46) -> 3500000 | G47: =SUM(G31:G46) -> 3500000 | H47: =SUM(H31:H46) -> 3500000 | I47: =SUM(I31:I46) -> 3500000 | ... BI47: =SUM(BI31:BI46) -> 0
A48: Auxilios de Transporte | B48: =IF(B31=0,0,IF(B31<INICIO!$B$32*2,INICIO!$B$33,0))+IF(B32=0,0,IF(B32<INICIO!$B$32*2,INICIO!$B$33,0))+IF(B33=0,0,IF(B33<INICIO!$B$32*2,INICIO!$B$33,0))+IF(B34=0,0,IF(B34<INICIO!$B$32*2,INICIO!$B$33,0))+IF(B35=0,0,IF(B35<INICIO!$B$32*2,INICIO!$B$33,0))+IF(B36=0,0,IF(B36<INICIO!$B$32*2,INICIO!$B$33,0))+IF(B37=0,0,IF(B37<INICIO!$B$32*2,INICIO!$B$33,0))+IF(B38=0,0,IF(B38<INICIO!$B$32*2,INICIO!$B$33,0))+IF(B39=0,0,IF(B39<INICIO!$B$32*2,INICIO!$B$33,0))+IF(B40=0,0,IF(B40<INICIO!$B$32*2,INICIO!$B$33,0))+IF(B41=0,0,IF(B41<INICIO!$B$32*2,INICIO!$B$33,0))+IF(B42=0,0,IF(B42<INICIO!$B$32*2,INICIO!$B$33,0))+IF(B43=0,0,IF(B43<INICIO!$B$32*2,INICIO!$B$33,0))+IF(B44=0,0,IF(B44<INICIO!$B$32*2,INICIO!$B$33,0))+IF(B45=0,0,IF(B45<INICIO!$B$32*2,INICIO!$B$33,0))+IF(B46=0,0,IF(B46<INICIO!$B$32*2,INICIO!$B$33,0)) -> 268000 | C48: =IF(C31=0,0,IF(C31<INICIO!$B$32*2,INICIO!$B$33,0))+IF(C32=0,0,IF(C32<INICIO!$B$32*2,INICIO!$B$33,0))+IF(C33=0,0,IF(C33<INICIO!$B$32*2,INICIO!$B$33,0))+IF(C34=0,0,IF(C34<INICIO!$B$32*2,INICIO!$B$33,0))+IF(C35=0,0,IF(C35<INICIO!$B$32*2,INICIO!$B$33,0))+IF(C36=0,0,IF(C36<INICIO!$B$32*2,INICIO!$B$33,0))+IF(C37=0,0,IF(C37<INICIO!$B$32*2,INICIO!$B$33,0))+IF(C38=0,0,IF(C38<INICIO!$B$32*2,INICIO!$B$33,0))+IF(C39=0,0,IF(C39<INICIO!$B$32*2,INICIO!$B$33,0))+IF(C40=0,0,IF(C40<INICIO!$B$32*2,INICIO!$B$33,0))+IF(C41=0,0,IF(C41<INICIO!$B$32*2,INICIO!$B$33,0))+IF(C42=0,0,IF(C42<INICIO!$B$32*2,INICIO!$B$33,0))+IF(C43=0,0,IF(C43<INICIO!$B$32*2,INICIO!$B$33,0))+IF(C44=0,0,IF(C44<INICIO!$B$32*2,INICIO!$B$33,0))+IF(C45=0,0,IF(C45<INICIO!$B$32*2,INICIO!$B$33,0))+IF(C46=0,0,IF(C46<INICIO!$B$32*2,INICIO!$B$33,0)) -> 268000 | D48: =IF(D31=0,0,IF(D31<INICIO!$B$32*2,INICIO!$B$33,0))+IF(D32=0,0,IF(D32<INICIO!$B$32*2,INICIO!$B$33,0))+IF(D33=0,0,IF(D33<INICIO!$B$32*2,INICIO!$B$33,0))+IF(D34=0,0,IF(D34<INICIO!$B$32*2,INICIO!$B$33,0))+IF(D35=0,0,IF(D35<INICIO!$B$32*2,INICIO!$B$33,0))+IF(D36=0,0,IF(D36<INICIO!$B$32*2,INICIO!$B$33,0))+IF(D37=0,0,IF(D37<INICIO!$B$32*2,INICIO!$B$33,0))+IF(D38=0,0,IF(D38<INICIO!$B$32*2,INICIO!$B$33,0))+IF(D39=0,0,IF(D39<INICIO!$B$32*2,INICIO!$B$33,0))+IF(D40=0,0,IF(D40<INICIO!$B$32*2,INICIO!$B$33,0))+IF(D41=0,0,IF(D41<INICIO!$B$32*2,INICIO!$B$33,0))+IF(D42=0,0,IF(D42<INICIO!$B$32*2,INICIO!$B$33,0))+IF(D43=0,0,IF(D43<INICIO!$B$32*2,INICIO!$B$33,0))+IF(D44=0,0,IF(D44<INICIO!$B$32*2,INICIO!$B$33,0))+IF(D45=0,0,IF(D45<INICIO!$B$32*2,INICIO!$B$33,0))+IF(D46=0,0,IF(D46<INICIO!$B$32*2,INICIO!$B$33,0)) -> 268000 | E48: =IF(E31=0,0,IF(E31<INICIO!$B$32*2,INICIO!$B$33,0))+IF(E32=0,0,IF(E32<INICIO!$B$32*2,INICIO!$B$33,0))+IF(E33=0,0,IF(E33<INICIO!$B$32*2,INICIO!$B$33,0))+IF(E34=0,0,IF(E34<INICIO!$B$32*2,INICIO!$B$33,0))+IF(E35=0,0,IF(E35<INICIO!$B$32*2,INICIO!$B$33,0))+IF(E36=0,0,IF(E36<INICIO!$B$32*2,INICIO!$B$33,0))+IF(E37=0,0,IF(E37<INICIO!$B$32*2,INICIO!$B$33,0))+IF(E38=0,0,IF(E38<INICIO!$B$32*2,INICIO!$B$33,0))+IF(E39=0,0,IF(E39<INICIO!$B$32*2,INICIO!$B$33,0))+IF(E40=0,0,IF(E40<INICIO!$B$32*2,INICIO!$B$33,0))+IF(E41=0,0,IF(E41<INICIO!$B$32*2,INICIO!$B$33,0))+IF(E42=0,0,IF(E42<INICIO!$B$32*2,INICIO!$B$33,0))+IF(E43=0,0,IF(E43<INICIO!$B$32*2,INICIO!$B$33,0))+IF(E44=0,0,IF(E44<INICIO!$B$32*2,INICIO!$B$33,0))+IF(E45=0,0,IF(E45<INICIO!$B$32*2,INICIO!$B$33,0))+IF(E46=0,0,IF(E46<INICIO!$B$32*2,INICIO!$B$33,0)) -> 268000 | F48: =IF(F31=0,0,IF(F31<INICIO!$B$32*2,INICIO!$B$33,0))+IF(F32=0,0,IF(F32<INICIO!$B$32*2,INICIO!$B$33,0))+IF(F33=0,0,IF(F33<INICIO!$B$32*2,INICIO!$B$33,0))+IF(F34=0,0,IF(F34<INICIO!$B$32*2,INICIO!$B$33,0))+IF(F35=0,0,IF(F35<INICIO!$B$32*2,INICIO!$B$33,0))+IF(F36=0,0,IF(F36<INICIO!$B$32*2,INICIO!$B$33,0))+IF(F37=0,0,IF(F37<INICIO!$B$32*2,INICIO!$B$33,0))+IF(F38=0,0,IF(F38<INICIO!$B$32*2,INICIO!$B$33,0))+IF(F39=0,0,IF(F39<INICIO!$B$32*2,INICIO!$B$33,0))+IF(F40=0,0,IF(F40<INICIO!$B$32*2,INICIO!$B$33,0))+IF(F41=0,0,IF(F41<INICIO!$B$32*2,INICIO!$B$33,0))+IF(F42=0,0,IF(F42<INICIO!$B$32*2,INICIO!$B$33,0))+IF(F43=0,0,IF(F43<INICIO!$B$32*2,INICIO!$B$33,0))+IF(F44=0,0,IF(F44<INICIO!$B$32*2,INICIO!$B$33,0))+IF(F45=0,0,IF(F45<INICIO!$B$32*2,INICIO!$B$33,0))+IF(F46=0,0,IF(F46<INICIO!$B$32*2,INICIO!$B$33,0)) -> 268000 | G48: =IF(G31=0,0,IF(G31<INICIO!$B$32*2,INICIO!$B$33,0))+IF(G32=0,0,IF(G32<INICIO!$B$32*2,INICIO!$B$33,0))+IF(G33=0,0,IF(G33<INICIO!$B$32*2,INICIO!$B$33,0))+IF(G34=0,0,IF(G34<INICIO!$B$32*2,INICIO!$B$33,0))+IF(G35=0,0,IF(G35<INICIO!$B$32*2,INICIO!$B$33,0))+IF(G36=0,0,IF(G36<INICIO!$B$32*2,INICIO!$B$33,0))+IF(G37=0,0,IF(G37<INICIO!$B$32*2,INICIO!$B$33,0))+IF(G38=0,0,IF(G38<INICIO!$B$32*2,INICIO!$B$33,0))+IF(G39=0,0,IF(G39<INICIO!$B$32*2,INICIO!$B$33,0))+IF(G40=0,0,IF(G40<INICIO!$B$32*2,INICIO!$B$33,0))+IF(G41=0,0,IF(G41<INICIO!$B$32*2,INICIO!$B$33,0))+IF(G42=0,0,IF(G42<INICIO!$B$32*2,INICIO!$B$33,0))+IF(G43=0,0,IF(G43<INICIO!$B$32*2,INICIO!$B$33,0))+IF(G44=0,0,IF(G44<INICIO!$B$32*2,INICIO!$B$33,0))+IF(G45=0,0,IF(G45<INICIO!$B$32*2,INICIO!$B$33,0))+IF(G46=0,0,IF(G46<INICIO!$B$32*2,INICIO!$B$33,0)) -> 268000 | H48: =IF(H31=0,0,IF(H31<INICIO!$B$32*2,INICIO!$B$33,0))+IF(H32=0,0,IF(H32<INICIO!$B$32*2,INICIO!$B$33,0))+IF(H33=0,0,IF(H33<INICIO!$B$32*2,INICIO!$B$33,0))+IF(H34=0,0,IF(H34<INICIO!$B$32*2,INICIO!$B$33,0))+IF(H35=0,0,IF(H35<INICIO!$B$32*2,INICIO!$B$33,0))+IF(H36=0,0,IF(H36<INICIO!$B$32*2,INICIO!$B$33,0))+IF(H37=0,0,IF(H37<INICIO!$B$32*2,INICIO!$B$33,0))+IF(H38=0,0,IF(H38<INICIO!$B$32*2,INICIO!$B$33,0))+IF(H39=0,0,IF(H39<INICIO!$B$32*2,INICIO!$B$33,0))+IF(H40=0,0,IF(H40<INICIO!$B$32*2,INICIO!$B$33,0))+IF(H41=0,0,IF(H41<INICIO!$B$32*2,INICIO!$B$33,0))+IF(H42=0,0,IF(H42<INICIO!$B$32*2,INICIO!$B$33,0))+IF(H43=0,0,IF(H43<INICIO!$B$32*2,INICIO!$B$33,0))+IF(H44=0,0,IF(H44<INICIO!$B$32*2,INICIO!$B$33,0))+IF(H45=0,0,IF(H45<INICIO!$B$32*2,INICIO!$B$33,0))+IF(H46=0,0,IF(H46<INICIO!$B$32*2,INICIO!$B$33,0)) -> 268000 | I48: =IF(I31=0,0,IF(I31<INICIO!$B$32*2,INICIO!$B$33,0))+IF(I32=0,0,IF(I32<INICIO!$B$32*2,INICIO!$B$33,0))+IF(I33=0,0,IF(I33<INICIO!$B$32*2,INICIO!$B$33,0))+IF(I34=0,0,IF(I34<INICIO!$B$32*2,INICIO!$B$33,0))+IF(I35=0,0,IF(I35<INICIO!$B$32*2,INICIO!$B$33,0))+IF(I36=0,0,IF(I36<INICIO!$B$32*2,INICIO!$B$33,0))+IF(I37=0,0,IF(I37<INICIO!$B$32*2,INICIO!$B$33,0))+IF(I38=0,0,IF(I38<INICIO!$B$32*2,INICIO!$B$33,0))+IF(I39=0,0,IF(I39<INICIO!$B$32*2,INICIO!$B$33,0))+IF(I40=0,0,IF(I40<INICIO!$B$32*2,INICIO!$B$33,0))+IF(I41=0,0,IF(I41<INICIO!$B$32*2,INICIO!$B$33,0))+IF(I42=0,0,IF(I42<INICIO!$B$32*2,INICIO!$B$33,0))+IF(I43=0,0,IF(I43<INICIO!$B$32*2,INICIO!$B$33,0))+IF(I44=0,0,IF(I44<INICIO!$B$32*2,INICIO!$B$33,0))+IF(I45=0,0,IF(I45<INICIO!$B$32*2,INICIO!$B$33,0))+IF(I46=0,0,IF(I46<INICIO!$B$32*2,INICIO!$B$33,0)) -> 268000 | ... M48: =IF(M31=0,0,IF(M31<INICIO!$B$32*2,INICIO!$B$33,0))+IF(M32=0,0,IF(M32<INICIO!$B$32*2,INICIO!$B$33,0))+IF(M33=0,0,IF(M33<INICIO!$B$32*2,INICIO!$B$33,0))+IF(M34=0,0,IF(M34<INICIO!$B$32*2,INICIO!$B$33,0))+IF(M35=0,0,IF(M35<INICIO!$B$32*2,INICIO!$B$33,0))+IF(M36=0,0,IF(M36<INICIO!$B$32*2,INICIO!$B$33,0))+IF(M37=0,0,IF(M37<INICIO!$B$32*2,INICIO!$B$33,0))+IF(M38=0,0,IF(M38<INICIO!$B$32*2,INICIO!$B$33,0))+IF(M39=0,0,IF(M39<INICIO!$B$32*2,INICIO!$B$33,0))+IF(M40=0,0,IF(M40<INICIO!$B$32*2,INICIO!$B$33,0))+IF(M41=0,0,IF(M41<INICIO!$B$32*2,INICIO!$B$33,0))+IF(M42=0,0,IF(M42<INICIO!$B$32*2,INICIO!$B$33,0))+IF(M43=0,0,IF(M43<INICIO!$B$32*2,INICIO!$B$33,0))+IF(M44=0,0,IF(M44<INICIO!$B$32*2,INICIO!$B$33,0))+IF(M45=0,0,IF(M45<INICIO!$B$32*2,INICIO!$B$33,0))+IF(M46=0,0,IF(M46<INICIO!$B$32*2,INICIO!$B$33,0)) -> 268000 | N48: =IF(N31=0,0,IF(N31<INICIO!$C$32*2,INICIO!$C$33,0))+IF(N32=0,0,IF(N32<INICIO!$C$32*2,INICIO!$C$33,0))+IF(N33=0,0,IF(N33<INICIO!$C$32*2,INICIO!$C$33,0))+IF(N34=0,0,IF(N34<INICIO!$C$32*2,INICIO!$C$33,0))+IF(N35=0,0,IF(N35<INICIO!$C$32*2,INICIO!$C$33,0))+IF(N36=0,0,IF(N36<INICIO!$C$32*2,INICIO!$C$33,0))+IF(N37=0,0,IF(N37<INICIO!$C$32*2,INICIO!$C$33,0))+IF(N38=0,0,IF(N38<INICIO!$C$32*2,INICIO!$C$33,0))+IF(N39=0,0,IF(N39<INICIO!$C$32*2,INICIO!$C$33,0))+IF(N40=0,0,IF(N40<INICIO!$C$32*2,INICIO!$C$33,0))+IF(N41=0,0,IF(N41<INICIO!$C$32*2,INICIO!$C$33,0))+IF(N42=0,0,IF(N42<INICIO!$C$32*2,INICIO!$C$33,0))+IF(N43=0,0,IF(N43<INICIO!$C$32*2,INICIO!$C$33,0))+IF(N44=0,0,IF(N44<INICIO!$C$32*2,INICIO!$C$33,0))+IF(N45=0,0,IF(N45<INICIO!$C$32*2,INICIO!$C$33,0))+IF(N46=0,0,IF(N46<INICIO!$C$32*2,INICIO!$C$33,0)) -> 564000 | O48: =IF(O31=0,0,IF(O31<INICIO!$C$32*2,INICIO!$C$33,0))+IF(O32=0,0,IF(O32<INICIO!$C$32*2,INICIO!$C$33,0))+IF(O33=0,0,IF(O33<INICIO!$C$32*2,INICIO!$C$33,0))+IF(O34=0,0,IF(O34<INICIO!$C$32*2,INICIO!$C$33,0))+IF(O35=0,0,IF(O35<INICIO!$C$32*2,INICIO!$C$33,0))+IF(O36=0,0,IF(O36<INICIO!$C$32*2,INICIO!$C$33,0))+IF(O37=0,0,IF(O37<INICIO!$C$32*2,INICIO!$C$33,0))+IF(O38=0,0,IF(O38<INICIO!$C$32*2,INICIO!$C$33,0))+IF(O39=0,0,IF(O39<INICIO!$C$32*2,INICIO!$C$33,0))+IF(O40=0,0,IF(O40<INICIO!$C$32*2,INICIO!$C$33,0))+IF(O41=0,0,IF(O41<INICIO!$C$32*2,INICIO!$C$33,0))+IF(O42=0,0,IF(O42<INICIO!$C$32*2,INICIO!$C$33,0))+IF(O43=0,0,IF(O43<INICIO!$C$32*2,INICIO!$C$33,0))+IF(O44=0,0,IF(O44<INICIO!$C$32*2,INICIO!$C$33,0))+IF(O45=0,0,IF(O45<INICIO!$C$32*2,INICIO!$C$33,0))+IF(O46=0,0,IF(O46<INICIO!$C$32*2,INICIO!$C$33,0)) -> 564000 | P48: =IF(P31=0,0,IF(P31<INICIO!$C$32*2,INICIO!$C$33,0))+IF(P32=0,0,IF(P32<INICIO!$C$32*2,INICIO!$C$33,0))+IF(P33=0,0,IF(P33<INICIO!$C$32*2,INICIO!$C$33,0))+IF(P34=0,0,IF(P34<INICIO!$C$32*2,INICIO!$C$33,0))+IF(P35=0,0,IF(P35<INICIO!$C$32*2,INICIO!$C$33,0))+IF(P36=0,0,IF(P36<INICIO!$C$32*2,INICIO!$C$33,0))+IF(P37=0,0,IF(P37<INICIO!$C$32*2,INICIO!$C$33,0))+IF(P38=0,0,IF(P38<INICIO!$C$32*2,INICIO!$C$33,0))+IF(P39=0,0,IF(P39<INICIO!$C$32*2,INICIO!$C$33,0))+IF(P40=0,0,IF(P40<INICIO!$C$32*2,INICIO!$C$33,0))+IF(P41=0,0,IF(P41<INICIO!$C$32*2,INICIO!$C$33,0))+IF(P42=0,0,IF(P42<INICIO!$C$32*2,INICIO!$C$33,0))+IF(P43=0,0,IF(P43<INICIO!$C$32*2,INICIO!$C$33,0))+IF(P44=0,0,IF(P44<INICIO!$C$32*2,INICIO!$C$33,0))+IF(P45=0,0,IF(P45<INICIO!$C$32*2,INICIO!$C$33,0))+IF(P46=0,0,IF(P46<INICIO!$C$32*2,INICIO!$C$33,0)) -> 564000 | Q48: =IF(Q31=0,0,IF(Q31<INICIO!$C$32*2,INICIO!$C$33,0))+IF(Q32=0,0,IF(Q32<INICIO!$C$32*2,INICIO!$C$33,0))+IF(Q33=0,0,IF(Q33<INICIO!$C$32*2,INICIO!$C$33,0))+IF(Q34=0,0,IF(Q34<INICIO!$C$32*2,INICIO!$C$33,0))+IF(Q35=0,0,IF(Q35<INICIO!$C$32*2,INICIO!$C$33,0))+IF(Q36=0,0,IF(Q36<INICIO!$C$32*2,INICIO!$C$33,0))+IF(Q37=0,0,IF(Q37<INICIO!$C$32*2,INICIO!$C$33,0))+IF(Q38=0,0,IF(Q38<INICIO!$C$32*2,INICIO!$C$33,0))+IF(Q39=0,0,IF(Q39<INICIO!$C$32*2,INICIO!$C$33,0))+IF(Q40=0,0,IF(Q40<INICIO!$C$32*2,INICIO!$C$33,0))+IF(Q41=0,0,IF(Q41<INICIO!$C$32*2,INICIO!$C$33,0))+IF(Q42=0,0,IF(Q42<INICIO!$C$32*2,INICIO!$C$33,0))+IF(Q43=0,0,IF(Q43<INICIO!$C$32*2,INICIO!$C$33,0))+IF(Q44=0,0,IF(Q44<INICIO!$C$32*2,INICIO!$C$33,0))+IF(Q45=0,0,IF(Q45<INICIO!$C$32*2,INICIO!$C$33,0))+IF(Q46=0,0,IF(Q46<INICIO!$C$32*2,INICIO!$C$33,0)) -> 564000 | R48: =IF(R31=0,0,IF(R31<INICIO!$C$32*2,INICIO!$C$33,0))+IF(R32=0,0,IF(R32<INICIO!$C$32*2,INICIO!$C$33,0))+IF(R33=0,0,IF(R33<INICIO!$C$32*2,INICIO!$C$33,0))+IF(R34=0,0,IF(R34<INICIO!$C$32*2,INICIO!$C$33,0))+IF(R35=0,0,IF(R35<INICIO!$C$32*2,INICIO!$C$33,0))+IF(R36=0,0,IF(R36<INICIO!$C$32*2,INICIO!$C$33,0))+IF(R37=0,0,IF(R37<INICIO!$C$32*2,INICIO!$C$33,0))+IF(R38=0,0,IF(R38<INICIO!$C$32*2,INICIO!$C$33,0))+IF(R39=0,0,IF(R39<INICIO!$C$32*2,INICIO!$C$33,0))+IF(R40=0,0,IF(R40<INICIO!$C$32*2,INICIO!$C$33,0))+IF(R41=0,0,IF(R41<INICIO!$C$32*2,INICIO!$C$33,0))+IF(R42=0,0,IF(R42<INICIO!$C$32*2,INICIO!$C$33,0))+IF(R43=0,0,IF(R43<INICIO!$C$32*2,INICIO!$C$33,0))+IF(R44=0,0,IF(R44<INICIO!$C$32*2,INICIO!$C$33,0))+IF(R45=0,0,IF(R45<INICIO!$C$32*2,INICIO!$C$33,0))+IF(R46=0,0,IF(R46<INICIO!$C$32*2,INICIO!$C$33,0)) -> 564000 | S48: =IF(S31=0,0,IF(S31<INICIO!$C$32*2,INICIO!$C$33,0))+IF(S32=0,0,IF(S32<INICIO!$C$32*2,INICIO!$C$33,0))+IF(S33=0,0,IF(S33<INICIO!$C$32*2,INICIO!$C$33,0))+IF(S34=0,0,IF(S34<INICIO!$C$32*2,INICIO!$C$33,0))+IF(S35=0,0,IF(S35<INICIO!$C$32*2,INICIO!$C$33,0))+IF(S36=0,0,IF(S36<INICIO!$C$32*2,INICIO!$C$33,0))+IF(S37=0,0,IF(S37<INICIO!$C$32*2,INICIO!$C$33,0))+IF(S38=0,0,IF(S38<INICIO!$C$32*2,INICIO!$C$33,0))+IF(S39=0,0,IF(S39<INICIO!$C$32*2,INICIO!$C$33,0))+IF(S40=0,0,IF(S40<INICIO!$C$32*2,INICIO!$C$33,0))+IF(S41=0,0,IF(S41<INICIO!$C$32*2,INICIO!$C$33,0))+IF(S42=0,0,IF(S42<INICIO!$C$32*2,INICIO!$C$33,0))+IF(S43=0,0,IF(S43<INICIO!$C$32*2,INICIO!$C$33,0))+IF(S44=0,0,IF(S44<INICIO!$C$32*2,INICIO!$C$33,0))+IF(S45=0,0,IF(S45<INICIO!$C$32*2,INICIO!$C$33,0))+IF(S46=0,0,IF(S46<INICIO!$C$32*2,INICIO!$C$33,0)) -> 564000 | T48: =IF(T31=0,0,IF(T31<INICIO!$C$32*2,INICIO!$C$33,0))+IF(T32=0,0,IF(T32<INICIO!$C$32*2,INICIO!$C$33,0))+IF(T33=0,0,IF(T33<INICIO!$C$32*2,INICIO!$C$33,0))+IF(T34=0,0,IF(T34<INICIO!$C$32*2,INICIO!$C$33,0))+IF(T35=0,0,IF(T35<INICIO!$C$32*2,INICIO!$C$33,0))+IF(T36=0,0,IF(T36<INICIO!$C$32*2,INICIO!$C$33,0))+IF(T37=0,0,IF(T37<INICIO!$C$32*2,INICIO!$C$33,0))+IF(T38=0,0,IF(T38<INICIO!$C$32*2,INICIO!$C$33,0))+IF(T39=0,0,IF(T39<INICIO!$C$32*2,INICIO!$C$33,0))+IF(T40=0,0,IF(T40<INICIO!$C$32*2,INICIO!$C$33,0))+IF(T41=0,0,IF(T41<INICIO!$C$32*2,INICIO!$C$33,0))+IF(T42=0,0,IF(T42<INICIO!$C$32*2,INICIO!$C$33,0))+IF(T43=0,0,IF(T43<INICIO!$C$32*2,INICIO!$C$33,0))+IF(T44=0,0,IF(T44<INICIO!$C$32*2,INICIO!$C$33,0))+IF(T45=0,0,IF(T45<INICIO!$C$32*2,INICIO!$C$33,0))+IF(T46=0,0,IF(T46<INICIO!$C$32*2,INICIO!$C$33,0)) -> 564000 | U48: =IF(U31=0,0,IF(U31<INICIO!$C$32*2,INICIO!$C$33,0))+IF(U32=0,0,IF(U32<INICIO!$C$32*2,INICIO!$C$33,0))+IF(U33=0,0,IF(U33<INICIO!$C$32*2,INICIO!$C$33,0))+IF(U34=0,0,IF(U34<INICIO!$C$32*2,INICIO!$C$33,0))+IF(U35=0,0,IF(U35<INICIO!$C$32*2,INICIO!$C$33,0))+IF(U36=0,0,IF(U36<INICIO!$C$32*2,INICIO!$C$33,0))+IF(U37=0,0,IF(U37<INICIO!$C$32*2,INICIO!$C$33,0))+IF(U38=0,0,IF(U38<INICIO!$C$32*2,INICIO!$C$33,0))+IF(U39=0,0,IF(U39<INICIO!$C$32*2,INICIO!$C$33,0))+IF(U40=0,0,IF(U40<INICIO!$C$32*2,INICIO!$C$33,0))+IF(U41=0,0,IF(U41<INICIO!$C$32*2,INICIO!$C$33,0))+IF(U42=0,0,IF(U42<INICIO!$C$32*2,INICIO!$C$33,0))+IF(U43=0,0,IF(U43<INICIO!$C$32*2,INICIO!$C$33,0))+IF(U44=0,0,IF(U44<INICIO!$C$32*2,INICIO!$C$33,0))+IF(U45=0,0,IF(U45<INICIO!$C$32*2,INICIO!$C$33,0))+IF(U46=0,0,IF(U46<INICIO!$C$32*2,INICIO!$C$33,0)) -> 564000 | ... Y48: =IF(Y31=0,0,IF(Y31<INICIO!$C$32*2,INICIO!$C$33,0))+IF(Y32=0,0,IF(Y32<INICIO!$C$32*2,INICIO!$C$33,0))+IF(Y33=0,0,IF(Y33<INICIO!$C$32*2,INICIO!$C$33,0))+IF(Y34=0,0,IF(Y34<INICIO!$C$32*2,INICIO!$C$33,0))+IF(Y35=0,0,IF(Y35<INICIO!$C$32*2,INICIO!$C$33,0))+IF(Y36=0,0,IF(Y36<INICIO!$C$32*2,INICIO!$C$33,0))+IF(Y37=0,0,IF(Y37<INICIO!$C$32*2,INICIO!$C$33,0))+IF(Y38=0,0,IF(Y38<INICIO!$C$32*2,INICIO!$C$33,0))+IF(Y39=0,0,IF(Y39<INICIO!$C$32*2,INICIO!$C$33,0))+IF(Y40=0,0,IF(Y40<INICIO!$C$32*2,INICIO!$C$33,0))+IF(Y41=0,0,IF(Y41<INICIO!$C$32*2,INICIO!$C$33,0))+IF(Y42=0,0,IF(Y42<INICIO!$C$32*2,INICIO!$C$33,0))+IF(Y43=0,0,IF(Y43<INICIO!$C$32*2,INICIO!$C$33,0))+IF(Y44=0,0,IF(Y44<INICIO!$C$32*2,INICIO!$C$33,0))+IF(Y45=0,0,IF(Y45<INICIO!$C$32*2,INICIO!$C$33,0))+IF(Y46=0,0,IF(Y46<INICIO!$C$32*2,INICIO!$C$33,0)) -> 564000 | Z48: =IF(Z31=0,0,IF(Z31<INICIO!$D$32*2,INICIO!$D$33,0))+IF(Z32=0,0,IF(Z32<INICIO!$D$32*2,INICIO!$D$33,0))+IF(Z33=0,0,IF(Z33<INICIO!$D$32*2,INICIO!$D$33,0))+IF(Z34=0,0,IF(Z34<INICIO!$D$32*2,INICIO!$D$33,0))+IF(Z35=0,0,IF(Z35<INICIO!$D$32*2,INICIO!$D$33,0))+IF(Z36=0,0,IF(Z36<INICIO!$D$32*2,INICIO!$D$33,0))+IF(Z37=0,0,IF(Z37<INICIO!$D$32*2,INICIO!$D$33,0))+IF(Z38=0,0,IF(Z38<INICIO!$D$32*2,INICIO!$D$33,0))+IF(Z39=0,0,IF(Z39<INICIO!$D$32*2,INICIO!$D$33,0))+IF(Z40=0,0,IF(Z40<INICIO!$D$32*2,INICIO!$D$33,0))+IF(Z41=0,0,IF(Z41<INICIO!$D$32*2,INICIO!$D$33,0))+IF(Z42=0,0,IF(Z42<INICIO!$D$32*2,INICIO!$D$33,0))+IF(Z43=0,0,IF(Z43<INICIO!$D$32*2,INICIO!$D$33,0))+IF(Z44=0,0,IF(Z44<INICIO!$D$32*2,INICIO!$D$33,0))+IF(Z45=0,0,IF(Z45<INICIO!$D$32*2,INICIO!$D$33,0))+IF(Z46=0,0,IF(Z46<INICIO!$D$32*2,INICIO!$D$33,0)) -> 588000 | AA48: =IF(AA31=0,0,IF(AA31<INICIO!$D$32*2,INICIO!$D$33,0))+IF(AA32=0,0,IF(AA32<INICIO!$D$32*2,INICIO!$D$33,0))+IF(AA33=0,0,IF(AA33<INICIO!$D$32*2,INICIO!$D$33,0))+IF(AA34=0,0,IF(AA34<INICIO!$D$32*2,INICIO!$D$33,0))+IF(AA35=0,0,IF(AA35<INICIO!$D$32*2,INICIO!$D$33,0))+IF(AA36=0,0,IF(AA36<INICIO!$D$32*2,INICIO!$D$33,0))+IF(AA37=0,0,IF(AA37<INICIO!$D$32*2,INICIO!$D$33,0))+IF(AA38=0,0,IF(AA38<INICIO!$D$32*2,INICIO!$D$33,0))+IF(AA39=0,0,IF(AA39<INICIO!$D$32*2,INICIO!$D$33,0))+IF(AA40=0,0,IF(AA40<INICIO!$D$32*2,INICIO!$D$33,0))+IF(AA41=0,0,IF(AA41<INICIO!$D$32*2,INICIO!$D$33,0))+IF(AA42=0,0,IF(AA42<INICIO!$D$32*2,INICIO!$D$33,0))+IF(AA43=0,0,IF(AA43<INICIO!$D$32*2,INICIO!$D$33,0))+IF(AA44=0,0,IF(AA44<INICIO!$D$32*2,INICIO!$D$33,0))+IF(AA45=0,0,IF(AA45<INICIO!$D$32*2,INICIO!$D$33,0))+IF(AA46=0,0,IF(AA46<INICIO!$D$32*2,INICIO!$D$33,0)) -> 588000 | AB48: =IF(AB31=0,0,IF(AB31<INICIO!$D$32*2,INICIO!$D$33,0))+IF(AB32=0,0,IF(AB32<INICIO!$D$32*2,INICIO!$D$33,0))+IF(AB33=0,0,IF(AB33<INICIO!$D$32*2,INICIO!$D$33,0))+IF(AB34=0,0,IF(AB34<INICIO!$D$32*2,INICIO!$D$33,0))+IF(AB35=0,0,IF(AB35<INICIO!$D$32*2,INICIO!$D$33,0))+IF(AB36=0,0,IF(AB36<INICIO!$D$32*2,INICIO!$D$33,0))+IF(AB37=0,0,IF(AB37<INICIO!$D$32*2,INICIO!$D$33,0))+IF(AB38=0,0,IF(AB38<INICIO!$D$32*2,INICIO!$D$33,0))+IF(AB39=0,0,IF(AB39<INICIO!$D$32*2,INICIO!$D$33,0))+IF(AB40=0,0,IF(AB40<INICIO!$D$32*2,INICIO!$D$33,0))+IF(AB41=0,0,IF(AB41<INICIO!$D$32*2,INICIO!$D$33,0))+IF(AB42=0,0,IF(AB42<INICIO!$D$32*2,INICIO!$D$33,0))+IF(AB43=0,0,IF(AB43<INICIO!$D$32*2,INICIO!$D$33,0))+IF(AB44=0,0,IF(AB44<INICIO!$D$32*2,INICIO!$D$33,0))+IF(AB45=0,0,IF(AB45<INICIO!$D$32*2,INICIO!$D$33,0))+IF(AB46=0,0,IF(AB46<INICIO!$D$32*2,INICIO!$D$33,0)) -> 588000 | AC48: =IF(AC31=0,0,IF(AC31<INICIO!$D$32*2,INICIO!$D$33,0))+IF(AC32=0,0,IF(AC32<INICIO!$D$32*2,INICIO!$D$33,0))+IF(AC33=0,0,IF(AC33<INICIO!$D$32*2,INICIO!$D$33,0))+IF(AC34=0,0,IF(AC34<INICIO!$D$32*2,INICIO!$D$33,0))+IF(AC35=0,0,IF(AC35<INICIO!$D$32*2,INICIO!$D$33,0))+IF(AC36=0,0,IF(AC36<INICIO!$D$32*2,INICIO!$D$33,0))+IF(AC37=0,0,IF(AC37<INICIO!$D$32*2,INICIO!$D$33,0))+IF(AC38=0,0,IF(AC38<INICIO!$D$32*2,INICIO!$D$33,0))+IF(AC39=0,0,IF(AC39<INICIO!$D$32*2,INICIO!$D$33,0))+IF(AC40=0,0,IF(AC40<INICIO!$D$32*2,INICIO!$D$33,0))+IF(AC41=0,0,IF(AC41<INICIO!$D$32*2,INICIO!$D$33,0))+IF(AC42=0,0,IF(AC42<INICIO!$D$32*2,INICIO!$D$33,0))+IF(AC43=0,0,IF(AC43<INICIO!$D$32*2,INICIO!$D$33,0))+IF(AC44=0,0,IF(AC44<INICIO!$D$32*2,INICIO!$D$33,0))+IF(AC45=0,0,IF(AC45<INICIO!$D$32*2,INICIO!$D$33,0))+IF(AC46=0,0,IF(AC46<INICIO!$D$32*2,INICIO!$D$33,0)) -> 588000 | AD48: =IF(AD31=0,0,IF(AD31<INICIO!$D$32*2,INICIO!$D$33,0))+IF(AD32=0,0,IF(AD32<INICIO!$D$32*2,INICIO!$D$33,0))+IF(AD33=0,0,IF(AD33<INICIO!$D$32*2,INICIO!$D$33,0))+IF(AD34=0,0,IF(AD34<INICIO!$D$32*2,INICIO!$D$33,0))+IF(AD35=0,0,IF(AD35<INICIO!$D$32*2,INICIO!$D$33,0))+IF(AD36=0,0,IF(AD36<INICIO!$D$32*2,INICIO!$D$33,0))+IF(AD37=0,0,IF(AD37<INICIO!$D$32*2,INICIO!$D$33,0))+IF(AD38=0,0,IF(AD38<INICIO!$D$32*2,INICIO!$D$33,0))+IF(AD39=0,0,IF(AD39<INICIO!$D$32*2,INICIO!$D$33,0))+IF(AD40=0,0,IF(AD40<INICIO!$D$32*2,INICIO!$D$33,0))+IF(AD41=0,0,IF(AD41<INICIO!$D$32*2,INICIO!$D$33,0))+IF(AD42=0,0,IF(AD42<INICIO!$D$32*2,INICIO!$D$33,0))+IF(AD43=0,0,IF(AD43<INICIO!$D$32*2,INICIO!$D$33,0))+IF(AD44=0,0,IF(AD44<INICIO!$D$32*2,INICIO!$D$33,0))+IF(AD45=0,0,IF(AD45<INICIO!$D$32*2,INICIO!$D$33,0))+IF(AD46=0,0,IF(AD46<INICIO!$D$32*2,INICIO!$D$33,0)) -> 588000 | AE48: =IF(AE31=0,0,IF(AE31<INICIO!$D$32*2,INICIO!$D$33,0))+IF(AE32=0,0,IF(AE32<INICIO!$D$32*2,INICIO!$D$33,0))+IF(AE33=0,0,IF(AE33<INICIO!$D$32*2,INICIO!$D$33,0))+IF(AE34=0,0,IF(AE34<INICIO!$D$32*2,INICIO!$D$33,0))+IF(AE35=0,0,IF(AE35<INICIO!$D$32*2,INICIO!$D$33,0))+IF(AE36=0,0,IF(AE36<INICIO!$D$32*2,INICIO!$D$33,0))+IF(AE37=0,0,IF(AE37<INICIO!$D$32*2,INICIO!$D$33,0))+IF(AE38=0,0,IF(AE38<INICIO!$D$32*2,INICIO!$D$33,0))+IF(AE39=0,0,IF(AE39<INICIO!$D$32*2,INICIO!$D$33,0))+IF(AE40=0,0,IF(AE40<INICIO!$D$32*2,INICIO!$D$33,0))+IF(AE41=0,0,IF(AE41<INICIO!$D$32*2,INICIO!$D$33,0))+IF(AE42=0,0,IF(AE42<INICIO!$D$32*2,INICIO!$D$33,0))+IF(AE43=0,0,IF(AE43<INICIO!$D$32*2,INICIO!$D$33,0))+IF(AE44=0,0,IF(AE44<INICIO!$D$32*2,INICIO!$D$33,0))+IF(AE45=0,0,IF(AE45<INICIO!$D$32*2,INICIO!$D$33,0))+IF(AE46=0,0,IF(AE46<INICIO!$D$32*2,INICIO!$D$33,0)) -> 588000 | AF48: =IF(AF31=0,0,IF(AF31<INICIO!$D$32*2,INICIO!$D$33,0))+IF(AF32=0,0,IF(AF32<INICIO!$D$32*2,INICIO!$D$33,0))+IF(AF33=0,0,IF(AF33<INICIO!$D$32*2,INICIO!$D$33,0))+IF(AF34=0,0,IF(AF34<INICIO!$D$32*2,INICIO!$D$33,0))+IF(AF35=0,0,IF(AF35<INICIO!$D$32*2,INICIO!$D$33,0))+IF(AF36=0,0,IF(AF36<INICIO!$D$32*2,INICIO!$D$33,0))+IF(AF37=0,0,IF(AF37<INICIO!$D$32*2,INICIO!$D$33,0))+IF(AF38=0,0,IF(AF38<INICIO!$D$32*2,INICIO!$D$33,0))+IF(AF39=0,0,IF(AF39<INICIO!$D$32*2,INICIO!$D$33,0))+IF(AF40=0,0,IF(AF40<INICIO!$D$32*2,INICIO!$D$33,0))+IF(AF41=0,0,IF(AF41<INICIO!$D$32*2,INICIO!$D$33,0))+IF(AF42=0,0,IF(AF42<INICIO!$D$32*2,INICIO!$D$33,0))+IF(AF43=0,0,IF(AF43<INICIO!$D$32*2,INICIO!$D$33,0))+IF(AF44=0,0,IF(AF44<INICIO!$D$32*2,INICIO!$D$33,0))+IF(AF45=0,0,IF(AF45<INICIO!$D$32*2,INICIO!$D$33,0))+IF(AF46=0,0,IF(AF46<INICIO!$D$32*2,INICIO!$D$33,0)) -> 588000 | AG48: =IF(AG31=0,0,IF(AG31<INICIO!$D$32*2,INICIO!$D$33,0))+IF(AG32=0,0,IF(AG32<INICIO!$D$32*2,INICIO!$D$33,0))+IF(AG33=0,0,IF(AG33<INICIO!$D$32*2,INICIO!$D$33,0))+IF(AG34=0,0,IF(AG34<INICIO!$D$32*2,INICIO!$D$33,0))+IF(AG35=0,0,IF(AG35<INICIO!$D$32*2,INICIO!$D$33,0))+IF(AG36=0,0,IF(AG36<INICIO!$D$32*2,INICIO!$D$33,0))+IF(AG37=0,0,IF(AG37<INICIO!$D$32*2,INICIO!$D$33,0))+IF(AG38=0,0,IF(AG38<INICIO!$D$32*2,INICIO!$D$33,0))+IF(AG39=0,0,IF(AG39<INICIO!$D$32*2,INICIO!$D$33,0))+IF(AG40=0,0,IF(AG40<INICIO!$D$32*2,INICIO!$D$33,0))+IF(AG41=0,0,IF(AG41<INICIO!$D$32*2,INICIO!$D$33,0))+IF(AG42=0,0,IF(AG42<INICIO!$D$32*2,INICIO!$D$33,0))+IF(AG43=0,0,IF(AG43<INICIO!$D$32*2,INICIO!$D$33,0))+IF(AG44=0,0,IF(AG44<INICIO!$D$32*2,INICIO!$D$33,0))+IF(AG45=0,0,IF(AG45<INICIO!$D$32*2,INICIO!$D$33,0))+IF(AG46=0,0,IF(AG46<INICIO!$D$32*2,INICIO!$D$33,0)) -> 588000 | ... AK48: =IF(AK31=0,0,IF(AK31<INICIO!$D$32*2,INICIO!$D$33,0))+IF(AK32=0,0,IF(AK32<INICIO!$D$32*2,INICIO!$D$33,0))+IF(AK33=0,0,IF(AK33<INICIO!$D$32*2,INICIO!$D$33,0))+IF(AK34=0,0,IF(AK34<INICIO!$D$32*2,INICIO!$D$33,0))+IF(AK35=0,0,IF(AK35<INICIO!$D$32*2,INICIO!$D$33,0))+IF(AK36=0,0,IF(AK36<INICIO!$D$32*2,INICIO!$D$33,0))+IF(AK37=0,0,IF(AK37<INICIO!$D$32*2,INICIO!$D$33,0))+IF(AK38=0,0,IF(AK38<INICIO!$D$32*2,INICIO!$D$33,0))+IF(AK39=0,0,IF(AK39<INICIO!$D$32*2,INICIO!$D$33,0))+IF(AK40=0,0,IF(AK40<INICIO!$D$32*2,INICIO!$D$33,0))+IF(AK41=0,0,IF(AK41<INICIO!$D$32*2,INICIO!$D$33,0))+IF(AK42=0,0,IF(AK42<INICIO!$D$32*2,INICIO!$D$33,0))+IF(AK43=0,0,IF(AK43<INICIO!$D$32*2,INICIO!$D$33,0))+IF(AK44=0,0,IF(AK44<INICIO!$D$32*2,INICIO!$D$33,0))+IF(AK45=0,0,IF(AK45<INICIO!$D$32*2,INICIO!$D$33,0))+IF(AK46=0,0,IF(AK46<INICIO!$D$32*2,INICIO!$D$33,0)) -> 588000 | AL48: =IF(AL31=0,0,IF(AL31<INICIO!$E$32*2,INICIO!$E$33,0))+IF(AL32=0,0,IF(AL32<INICIO!$E$32*2,INICIO!$E$33,0))+IF(AL33=0,0,IF(AL33<INICIO!$E$32*2,INICIO!$E$33,0))+IF(AL34=0,0,IF(AL34<INICIO!$E$32*2,INICIO!$E$33,0))+IF(AL35=0,0,IF(AL35<INICIO!$E$32*2,INICIO!$E$33,0))+IF(AL36=0,0,IF(AL36<INICIO!$E$32*2,INICIO!$E$33,0))+IF(AL37=0,0,IF(AL37<INICIO!$E$32*2,INICIO!$E$33,0))+IF(AL38=0,0,IF(AL38<INICIO!$E$32*2,INICIO!$E$33,0))+IF(AL39=0,0,IF(AL39<INICIO!$E$32*2,INICIO!$E$33,0))+IF(AL40=0,0,IF(AL40<INICIO!$E$32*2,INICIO!$E$33,0))+IF(AL41=0,0,IF(AL41<INICIO!$E$32*2,INICIO!$E$33,0))+IF(AL42=0,0,IF(AL42<INICIO!$E$32*2,INICIO!$E$33,0))+IF(AL43=0,0,IF(AL43<INICIO!$E$32*2,INICIO!$E$33,0))+IF(AL44=0,0,IF(AL44<INICIO!$E$32*2,INICIO!$E$33,0))+IF(AL45=0,0,IF(AL45<INICIO!$E$32*2,INICIO!$E$33,0))+IF(AL46=0,0,IF(AL46<INICIO!$E$32*2,INICIO!$E$33,0)) -> 612000 | AM48: =IF(AM31=0,0,IF(AM31<INICIO!$E$32*2,INICIO!$E$33,0))+IF(AM32=0,0,IF(AM32<INICIO!$E$32*2,INICIO!$E$33,0))+IF(AM33=0,0,IF(AM33<INICIO!$E$32*2,INICIO!$E$33,0))+IF(AM34=0,0,IF(AM34<INICIO!$E$32*2,INICIO!$E$33,0))+IF(AM35=0,0,IF(AM35<INICIO!$E$32*2,INICIO!$E$33,0))+IF(AM36=0,0,IF(AM36<INICIO!$E$32*2,INICIO!$E$33,0))+IF(AM37=0,0,IF(AM37<INICIO!$E$32*2,INICIO!$E$33,0))+IF(AM38=0,0,IF(AM38<INICIO!$E$32*2,INICIO!$E$33,0))+IF(AM39=0,0,IF(AM39<INICIO!$E$32*2,INICIO!$E$33,0))+IF(AM40=0,0,IF(AM40<INICIO!$E$32*2,INICIO!$E$33,0))+IF(AM41=0,0,IF(AM41<INICIO!$E$32*2,INICIO!$E$33,0))+IF(AM42=0,0,IF(AM42<INICIO!$E$32*2,INICIO!$E$33,0))+IF(AM43=0,0,IF(AM43<INICIO!$E$32*2,INICIO!$E$33,0))+IF(AM44=0,0,IF(AM44<INICIO!$E$32*2,INICIO!$E$33,0))+IF(AM45=0,0,IF(AM45<INICIO!$E$32*2,INICIO!$E$33,0))+IF(AM46=0,0,IF(AM46<INICIO!$E$32*2,INICIO!$E$33,0)) -> 612000 | AN48: =IF(AN31=0,0,IF(AN31<INICIO!$E$32*2,INICIO!$E$33,0))+IF(AN32=0,0,IF(AN32<INICIO!$E$32*2,INICIO!$E$33,0))+IF(AN33=0,0,IF(AN33<INICIO!$E$32*2,INICIO!$E$33,0))+IF(AN34=0,0,IF(AN34<INICIO!$E$32*2,INICIO!$E$33,0))+IF(AN35=0,0,IF(AN35<INICIO!$E$32*2,INICIO!$E$33,0))+IF(AN36=0,0,IF(AN36<INICIO!$E$32*2,INICIO!$E$33,0))+IF(AN37=0,0,IF(AN37<INICIO!$E$32*2,INICIO!$E$33,0))+IF(AN38=0,0,IF(AN38<INICIO!$E$32*2,INICIO!$E$33,0))+IF(AN39=0,0,IF(AN39<INICIO!$E$32*2,INICIO!$E$33,0))+IF(AN40=0,0,IF(AN40<INICIO!$E$32*2,INICIO!$E$33,0))+IF(AN41=0,0,IF(AN41<INICIO!$E$32*2,INICIO!$E$33,0))+IF(AN42=0,0,IF(AN42<INICIO!$E$32*2,INICIO!$E$33,0))+IF(AN43=0,0,IF(AN43<INICIO!$E$32*2,INICIO!$E$33,0))+IF(AN44=0,0,IF(AN44<INICIO!$E$32*2,INICIO!$E$33,0))+IF(AN45=0,0,IF(AN45<INICIO!$E$32*2,INICIO!$E$33,0))+IF(AN46=0,0,IF(AN46<INICIO!$E$32*2,INICIO!$E$33,0)) -> 612000 | AO48: =IF(AO31=0,0,IF(AO31<INICIO!$E$32*2,INICIO!$E$33,0))+IF(AO32=0,0,IF(AO32<INICIO!$E$32*2,INICIO!$E$33,0))+IF(AO33=0,0,IF(AO33<INICIO!$E$32*2,INICIO!$E$33,0))+IF(AO34=0,0,IF(AO34<INICIO!$E$32*2,INICIO!$E$33,0))+IF(AO35=0,0,IF(AO35<INICIO!$E$32*2,INICIO!$E$33,0))+IF(AO36=0,0,IF(AO36<INICIO!$E$32*2,INICIO!$E$33,0))+IF(AO37=0,0,IF(AO37<INICIO!$E$32*2,INICIO!$E$33,0))+IF(AO38=0,0,IF(AO38<INICIO!$E$32*2,INICIO!$E$33,0))+IF(AO39=0,0,IF(AO39<INICIO!$E$32*2,INICIO!$E$33,0))+IF(AO40=0,0,IF(AO40<INICIO!$E$32*2,INICIO!$E$33,0))+IF(AO41=0,0,IF(AO41<INICIO!$E$32*2,INICIO!$E$33,0))+IF(AO42=0,0,IF(AO42<INICIO!$E$32*2,INICIO!$E$33,0))+IF(AO43=0,0,IF(AO43<INICIO!$E$32*2,INICIO!$E$33,0))+IF(AO44=0,0,IF(AO44<INICIO!$E$32*2,INICIO!$E$33,0))+IF(AO45=0,0,IF(AO45<INICIO!$E$32*2,INICIO!$E$33,0))+IF(AO46=0,0,IF(AO46<INICIO!$E$32*2,INICIO!$E$33,0)) -> 612000 | AP48: =IF(AP31=0,0,IF(AP31<INICIO!$E$32*2,INICIO!$E$33,0))+IF(AP32=0,0,IF(AP32<INICIO!$E$32*2,INICIO!$E$33,0))+IF(AP33=0,0,IF(AP33<INICIO!$E$32*2,INICIO!$E$33,0))+IF(AP34=0,0,IF(AP34<INICIO!$E$32*2,INICIO!$E$33,0))+IF(AP35=0,0,IF(AP35<INICIO!$E$32*2,INICIO!$E$33,0))+IF(AP36=0,0,IF(AP36<INICIO!$E$32*2,INICIO!$E$33,0))+IF(AP37=0,0,IF(AP37<INICIO!$E$32*2,INICIO!$E$33,0))+IF(AP38=0,0,IF(AP38<INICIO!$E$32*2,INICIO!$E$33,0))+IF(AP39=0,0,IF(AP39<INICIO!$E$32*2,INICIO!$E$33,0))+IF(AP40=0,0,IF(AP40<INICIO!$E$32*2,INICIO!$E$33,0))+IF(AP41=0,0,IF(AP41<INICIO!$E$32*2,INICIO!$E$33,0))+IF(AP42=0,0,IF(AP42<INICIO!$E$32*2,INICIO!$E$33,0))+IF(AP43=0,0,IF(AP43<INICIO!$E$32*2,INICIO!$E$33,0))+IF(AP44=0,0,IF(AP44<INICIO!$E$32*2,INICIO!$E$33,0))+IF(AP45=0,0,IF(AP45<INICIO!$E$32*2,INICIO!$E$33,0))+IF(AP46=0,0,IF(AP46<INICIO!$E$32*2,INICIO!$E$33,0)) -> 612000 | AQ48: =IF(AQ31=0,0,IF(AQ31<INICIO!$E$32*2,INICIO!$E$33,0))+IF(AQ32=0,0,IF(AQ32<INICIO!$E$32*2,INICIO!$E$33,0))+IF(AQ33=0,0,IF(AQ33<INICIO!$E$32*2,INICIO!$E$33,0))+IF(AQ34=0,0,IF(AQ34<INICIO!$E$32*2,INICIO!$E$33,0))+IF(AQ35=0,0,IF(AQ35<INICIO!$E$32*2,INICIO!$E$33,0))+IF(AQ36=0,0,IF(AQ36<INICIO!$E$32*2,INICIO!$E$33,0))+IF(AQ37=0,0,IF(AQ37<INICIO!$E$32*2,INICIO!$E$33,0))+IF(AQ38=0,0,IF(AQ38<INICIO!$E$32*2,INICIO!$E$33,0))+IF(AQ39=0,0,IF(AQ39<INICIO!$E$32*2,INICIO!$E$33,0))+IF(AQ40=0,0,IF(AQ40<INICIO!$E$32*2,INICIO!$E$33,0))+IF(AQ41=0,0,IF(AQ41<INICIO!$E$32*2,INICIO!$E$33,0))+IF(AQ42=0,0,IF(AQ42<INICIO!$E$32*2,INICIO!$E$33,0))+IF(AQ43=0,0,IF(AQ43<INICIO!$E$32*2,INICIO!$E$33,0))+IF(AQ44=0,0,IF(AQ44<INICIO!$E$32*2,INICIO!$E$33,0))+IF(AQ45=0,0,IF(AQ45<INICIO!$E$32*2,INICIO!$E$33,0))+IF(AQ46=0,0,IF(AQ46<INICIO!$E$32*2,INICIO!$E$33,0)) -> 612000 | AR48: =IF(AR31=0,0,IF(AR31<INICIO!$E$32*2,INICIO!$E$33,0))+IF(AR32=0,0,IF(AR32<INICIO!$E$32*2,INICIO!$E$33,0))+IF(AR33=0,0,IF(AR33<INICIO!$E$32*2,INICIO!$E$33,0))+IF(AR34=0,0,IF(AR34<INICIO!$E$32*2,INICIO!$E$33,0))+IF(AR35=0,0,IF(AR35<INICIO!$E$32*2,INICIO!$E$33,0))+IF(AR36=0,0,IF(AR36<INICIO!$E$32*2,INICIO!$E$33,0))+IF(AR37=0,0,IF(AR37<INICIO!$E$32*2,INICIO!$E$33,0))+IF(AR38=0,0,IF(AR38<INICIO!$E$32*2,INICIO!$E$33,0))+IF(AR39=0,0,IF(AR39<INICIO!$E$32*2,INICIO!$E$33,0))+IF(AR40=0,0,IF(AR40<INICIO!$E$32*2,INICIO!$E$33,0))+IF(AR41=0,0,IF(AR41<INICIO!$E$32*2,INICIO!$E$33,0))+IF(AR42=0,0,IF(AR42<INICIO!$E$32*2,INICIO!$E$33,0))+IF(AR43=0,0,IF(AR43<INICIO!$E$32*2,INICIO!$E$33,0))+IF(AR44=0,0,IF(AR44<INICIO!$E$32*2,INICIO!$E$33,0))+IF(AR45=0,0,IF(AR45<INICIO!$E$32*2,INICIO!$E$33,0))+IF(AR46=0,0,IF(AR46<INICIO!$E$32*2,INICIO!$E$33,0)) -> 612000 | AS48: =IF(AS31=0,0,IF(AS31<INICIO!$E$32*2,INICIO!$E$33,0))+IF(AS32=0,0,IF(AS32<INICIO!$E$32*2,INICIO!$E$33,0))+IF(AS33=0,0,IF(AS33<INICIO!$E$32*2,INICIO!$E$33,0))+IF(AS34=0,0,IF(AS34<INICIO!$E$32*2,INICIO!$E$33,0))+IF(AS35=0,0,IF(AS35<INICIO!$E$32*2,INICIO!$E$33,0))+IF(AS36=0,0,IF(AS36<INICIO!$E$32*2,INICIO!$E$33,0))+IF(AS37=0,0,IF(AS37<INICIO!$E$32*2,INICIO!$E$33,0))+IF(AS38=0,0,IF(AS38<INICIO!$E$32*2,INICIO!$E$33,0))+IF(AS39=0,0,IF(AS39<INICIO!$E$32*2,INICIO!$E$33,0))+IF(AS40=0,0,IF(AS40<INICIO!$E$32*2,INICIO!$E$33,0))+IF(AS41=0,0,IF(AS41<INICIO!$E$32*2,INICIO!$E$33,0))+IF(AS42=0,0,IF(AS42<INICIO!$E$32*2,INICIO!$E$33,0))+IF(AS43=0,0,IF(AS43<INICIO!$E$32*2,INICIO!$E$33,0))+IF(AS44=0,0,IF(AS44<INICIO!$E$32*2,INICIO!$E$33,0))+IF(AS45=0,0,IF(AS45<INICIO!$E$32*2,INICIO!$E$33,0))+IF(AS46=0,0,IF(AS46<INICIO!$E$32*2,INICIO!$E$33,0)) -> 612000 | ... AW48: =IF(AW31=0,0,IF(AW31<INICIO!$E$32*2,INICIO!$E$33,0))+IF(AW32=0,0,IF(AW32<INICIO!$E$32*2,INICIO!$E$33,0))+IF(AW33=0,0,IF(AW33<INICIO!$E$32*2,INICIO!$E$33,0))+IF(AW34=0,0,IF(AW34<INICIO!$E$32*2,INICIO!$E$33,0))+IF(AW35=0,0,IF(AW35<INICIO!$E$32*2,INICIO!$E$33,0))+IF(AW36=0,0,IF(AW36<INICIO!$E$32*2,INICIO!$E$33,0))+IF(AW37=0,0,IF(AW37<INICIO!$E$32*2,INICIO!$E$33,0))+IF(AW38=0,0,IF(AW38<INICIO!$E$32*2,INICIO!$E$33,0))+IF(AW39=0,0,IF(AW39<INICIO!$E$32*2,INICIO!$E$33,0))+IF(AW40=0,0,IF(AW40<INICIO!$E$32*2,INICIO!$E$33,0))+IF(AW41=0,0,IF(AW41<INICIO!$E$32*2,INICIO!$E$33,0))+IF(AW42=0,0,IF(AW42<INICIO!$E$32*2,INICIO!$E$33,0))+IF(AW43=0,0,IF(AW43<INICIO!$E$32*2,INICIO!$E$33,0))+IF(AW44=0,0,IF(AW44<INICIO!$E$32*2,INICIO!$E$33,0))+IF(AW45=0,0,IF(AW45<INICIO!$E$32*2,INICIO!$E$33,0))+IF(AW46=0,0,IF(AW46<INICIO!$E$32*2,INICIO!$E$33,0)) -> 612000 | AX48: =IF(AX31=0,0,IF(AX31<INICIO!$F$32*2,INICIO!$F$33,0))+IF(AX32=0,0,IF(AX32<INICIO!$F$32*2,INICIO!$F$33,0))+IF(AX33=0,0,IF(AX33<INICIO!$F$32*2,INICIO!$F$33,0))+IF(AX34=0,0,IF(AX34<INICIO!$F$32*2,INICIO!$F$33,0))+IF(AX35=0,0,IF(AX35<INICIO!$F$32*2,INICIO!$F$33,0))+IF(AX36=0,0,IF(AX36<INICIO!$F$32*2,INICIO!$F$33,0))+IF(AX37=0,0,IF(AX37<INICIO!$F$32*2,INICIO!$F$33,0))+IF(AX38=0,0,IF(AX38<INICIO!$F$32*2,INICIO!$F$33,0))+IF(AX39=0,0,IF(AX39<INICIO!$F$32*2,INICIO!$F$33,0))+IF(AX40=0,0,IF(AX40<INICIO!$F$32*2,INICIO!$F$33,0))+IF(AX41=0,0,IF(AX41<INICIO!$F$32*2,INICIO!$F$33,0))+IF(AX42=0,0,IF(AX42<INICIO!$F$32*2,INICIO!$F$33,0))+IF(AX43=0,0,IF(AX43<INICIO!$F$32*2,INICIO!$F$33,0))+IF(AX44=0,0,IF(AX44<INICIO!$F$32*2,INICIO!$F$33,0))+IF(AX45=0,0,IF(AX45<INICIO!$F$32*2,INICIO!$F$33,0))+IF(AX46=0,0,IF(AX46<INICIO!$F$32*2,INICIO!$F$33,0)) -> 636000 | AY48: =IF(AY31=0,0,IF(AY31<INICIO!$F$32*2,INICIO!$F$33,0))+IF(AY32=0,0,IF(AY32<INICIO!$F$32*2,INICIO!$F$33,0))+IF(AY33=0,0,IF(AY33<INICIO!$F$32*2,INICIO!$F$33,0))+IF(AY34=0,0,IF(AY34<INICIO!$F$32*2,INICIO!$F$33,0))+IF(AY35=0,0,IF(AY35<INICIO!$F$32*2,INICIO!$F$33,0))+IF(AY36=0,0,IF(AY36<INICIO!$F$32*2,INICIO!$F$33,0))+IF(AY37=0,0,IF(AY37<INICIO!$F$32*2,INICIO!$F$33,0))+IF(AY38=0,0,IF(AY38<INICIO!$F$32*2,INICIO!$F$33,0))+IF(AY39=0,0,IF(AY39<INICIO!$F$32*2,INICIO!$F$33,0))+IF(AY40=0,0,IF(AY40<INICIO!$F$32*2,INICIO!$F$33,0))+IF(AY41=0,0,IF(AY41<INICIO!$F$32*2,INICIO!$F$33,0))+IF(AY42=0,0,IF(AY42<INICIO!$F$32*2,INICIO!$F$33,0))+IF(AY43=0,0,IF(AY43<INICIO!$F$32*2,INICIO!$F$33,0))+IF(AY44=0,0,IF(AY44<INICIO!$F$32*2,INICIO!$F$33,0))+IF(AY45=0,0,IF(AY45<INICIO!$F$32*2,INICIO!$F$33,0))+IF(AY46=0,0,IF(AY46<INICIO!$F$32*2,INICIO!$F$33,0)) -> 0 | AZ48: =IF(AZ31=0,0,IF(AZ31<INICIO!$F$32*2,INICIO!$F$33,0))+IF(AZ32=0,0,IF(AZ32<INICIO!$F$32*2,INICIO!$F$33,0))+IF(AZ33=0,0,IF(AZ33<INICIO!$F$32*2,INICIO!$F$33,0))+IF(AZ34=0,0,IF(AZ34<INICIO!$F$32*2,INICIO!$F$33,0))+IF(AZ35=0,0,IF(AZ35<INICIO!$F$32*2,INICIO!$F$33,0))+IF(AZ36=0,0,IF(AZ36<INICIO!$F$32*2,INICIO!$F$33,0))+IF(AZ37=0,0,IF(AZ37<INICIO!$F$32*2,INICIO!$F$33,0))+IF(AZ38=0,0,IF(AZ38<INICIO!$F$32*2,INICIO!$F$33,0))+IF(AZ39=0,0,IF(AZ39<INICIO!$F$32*2,INICIO!$F$33,0))+IF(AZ40=0,0,IF(AZ40<INICIO!$F$32*2,INICIO!$F$33,0))+IF(AZ41=0,0,IF(AZ41<INICIO!$F$32*2,INICIO!$F$33,0))+IF(AZ42=0,0,IF(AZ42<INICIO!$F$32*2,INICIO!$F$33,0))+IF(AZ43=0,0,IF(AZ43<INICIO!$F$32*2,INICIO!$F$33,0))+IF(AZ44=0,0,IF(AZ44<INICIO!$F$32*2,INICIO!$F$33,0))+IF(AZ45=0,0,IF(AZ45<INICIO!$F$32*2,INICIO!$F$33,0))+IF(AZ46=0,0,IF(AZ46<INICIO!$F$32*2,INICIO!$F$33,0)) -> 0 | BA48: =IF(BA31=0,0,IF(BA31<INICIO!$F$32*2,INICIO!$F$33,0))+IF(BA32=0,0,IF(BA32<INICIO!$F$32*2,INICIO!$F$33,0))+IF(BA33=0,0,IF(BA33<INICIO!$F$32*2,INICIO!$F$33,0))+IF(BA34=0,0,IF(BA34<INICIO!$F$32*2,INICIO!$F$33,0))+IF(BA35=0,0,IF(BA35<INICIO!$F$32*2,INICIO!$F$33,0))+IF(BA36=0,0,IF(BA36<INICIO!$F$32*2,INICIO!$F$33,0))+IF(BA37=0,0,IF(BA37<INICIO!$F$32*2,INICIO!$F$33,0))+IF(BA38=0,0,IF(BA38<INICIO!$F$32*2,INICIO!$F$33,0))+IF(BA39=0,0,IF(BA39<INICIO!$F$32*2,INICIO!$F$33,0))+IF(BA40=0,0,IF(BA40<INICIO!$F$32*2,INICIO!$F$33,0))+IF(BA41=0,0,IF(BA41<INICIO!$F$32*2,INICIO!$F$33,0))+IF(BA42=0,0,IF(BA42<INICIO!$F$32*2,INICIO!$F$33,0))+IF(BA43=0,0,IF(BA43<INICIO!$F$32*2,INICIO!$F$33,0))+IF(BA44=0,0,IF(BA44<INICIO!$F$32*2,INICIO!$F$33,0))+IF(BA45=0,0,IF(BA45<INICIO!$F$32*2,INICIO!$F$33,0))+IF(BA46=0,0,IF(BA46<INICIO!$F$32*2,INICIO!$F$33,0)) -> 0 | BB48: =IF(BB31=0,0,IF(BB31<INICIO!$F$32*2,INICIO!$F$33,0))+IF(BB32=0,0,IF(BB32<INICIO!$F$32*2,INICIO!$F$33,0))+IF(BB33=0,0,IF(BB33<INICIO!$F$32*2,INICIO!$F$33,0))+IF(BB34=0,0,IF(BB34<INICIO!$F$32*2,INICIO!$F$33,0))+IF(BB35=0,0,IF(BB35<INICIO!$F$32*2,INICIO!$F$33,0))+IF(BB36=0,0,IF(BB36<INICIO!$F$32*2,INICIO!$F$33,0))+IF(BB37=0,0,IF(BB37<INICIO!$F$32*2,INICIO!$F$33,0))+IF(BB38=0,0,IF(BB38<INICIO!$F$32*2,INICIO!$F$33,0))+IF(BB39=0,0,IF(BB39<INICIO!$F$32*2,INICIO!$F$33,0))+IF(BB40=0,0,IF(BB40<INICIO!$F$32*2,INICIO!$F$33,0))+IF(BB41=0,0,IF(BB41<INICIO!$F$32*2,INICIO!$F$33,0))+IF(BB42=0,0,IF(BB42<INICIO!$F$32*2,INICIO!$F$33,0))+IF(BB43=0,0,IF(BB43<INICIO!$F$32*2,INICIO!$F$33,0))+IF(BB44=0,0,IF(BB44<INICIO!$F$32*2,INICIO!$F$33,0))+IF(BB45=0,0,IF(BB45<INICIO!$F$32*2,INICIO!$F$33,0))+IF(BB46=0,0,IF(BB46<INICIO!$F$32*2,INICIO!$F$33,0)) -> 0 | BC48: =IF(BC31=0,0,IF(BC31<INICIO!$F$32*2,INICIO!$F$33,0))+IF(BC32=0,0,IF(BC32<INICIO!$F$32*2,INICIO!$F$33,0))+IF(BC33=0,0,IF(BC33<INICIO!$F$32*2,INICIO!$F$33,0))+IF(BC34=0,0,IF(BC34<INICIO!$F$32*2,INICIO!$F$33,0))+IF(BC35=0,0,IF(BC35<INICIO!$F$32*2,INICIO!$F$33,0))+IF(BC36=0,0,IF(BC36<INICIO!$F$32*2,INICIO!$F$33,0))+IF(BC37=0,0,IF(BC37<INICIO!$F$32*2,INICIO!$F$33,0))+IF(BC38=0,0,IF(BC38<INICIO!$F$32*2,INICIO!$F$33,0))+IF(BC39=0,0,IF(BC39<INICIO!$F$32*2,INICIO!$F$33,0))+IF(BC40=0,0,IF(BC40<INICIO!$F$32*2,INICIO!$F$33,0))+IF(BC41=0,0,IF(BC41<INICIO!$F$32*2,INICIO!$F$33,0))+IF(BC42=0,0,IF(BC42<INICIO!$F$32*2,INICIO!$F$33,0))+IF(BC43=0,0,IF(BC43<INICIO!$F$32*2,INICIO!$F$33,0))+IF(BC44=0,0,IF(BC44<INICIO!$F$32*2,INICIO!$F$33,0))+IF(BC45=0,0,IF(BC45<INICIO!$F$32*2,INICIO!$F$33,0))+IF(BC46=0,0,IF(BC46<INICIO!$F$32*2,INICIO!$F$33,0)) -> 0 | BD48: =IF(BD31=0,0,IF(BD31<INICIO!$F$32*2,INICIO!$F$33,0))+IF(BD32=0,0,IF(BD32<INICIO!$F$32*2,INICIO!$F$33,0))+IF(BD33=0,0,IF(BD33<INICIO!$F$32*2,INICIO!$F$33,0))+IF(BD34=0,0,IF(BD34<INICIO!$F$32*2,INICIO!$F$33,0))+IF(BD35=0,0,IF(BD35<INICIO!$F$32*2,INICIO!$F$33,0))+IF(BD36=0,0,IF(BD36<INICIO!$F$32*2,INICIO!$F$33,0))+IF(BD37=0,0,IF(BD37<INICIO!$F$32*2,INICIO!$F$33,0))+IF(BD38=0,0,IF(BD38<INICIO!$F$32*2,INICIO!$F$33,0))+IF(BD39=0,0,IF(BD39<INICIO!$F$32*2,INICIO!$F$33,0))+IF(BD40=0,0,IF(BD40<INICIO!$F$32*2,INICIO!$F$33,0))+IF(BD41=0,0,IF(BD41<INICIO!$F$32*2,INICIO!$F$33,0))+IF(BD42=0,0,IF(BD42<INICIO!$F$32*2,INICIO!$F$33,0))+IF(BD43=0,0,IF(BD43<INICIO!$F$32*2,INICIO!$F$33,0))+IF(BD44=0,0,IF(BD44<INICIO!$F$32*2,INICIO!$F$33,0))+IF(BD45=0,0,IF(BD45<INICIO!$F$32*2,INICIO!$F$33,0))+IF(BD46=0,0,IF(BD46<INICIO!$F$32*2,INICIO!$F$33,0)) -> 0 | BE48: =IF(BE31=0,0,IF(BE31<INICIO!$F$32*2,INICIO!$F$33,0))+IF(BE32=0,0,IF(BE32<INICIO!$F$32*2,INICIO!$F$33,0))+IF(BE33=0,0,IF(BE33<INICIO!$F$32*2,INICIO!$F$33,0))+IF(BE34=0,0,IF(BE34<INICIO!$F$32*2,INICIO!$F$33,0))+IF(BE35=0,0,IF(BE35<INICIO!$F$32*2,INICIO!$F$33,0))+IF(BE36=0,0,IF(BE36<INICIO!$F$32*2,INICIO!$F$33,0))+IF(BE37=0,0,IF(BE37<INICIO!$F$32*2,INICIO!$F$33,0))+IF(BE38=0,0,IF(BE38<INICIO!$F$32*2,INICIO!$F$33,0))+IF(BE39=0,0,IF(BE39<INICIO!$F$32*2,INICIO!$F$33,0))+IF(BE40=0,0,IF(BE40<INICIO!$F$32*2,INICIO!$F$33,0))+IF(BE41=0,0,IF(BE41<INICIO!$F$32*2,INICIO!$F$33,0))+IF(BE42=0,0,IF(BE42<INICIO!$F$32*2,INICIO!$F$33,0))+IF(BE43=0,0,IF(BE43<INICIO!$F$32*2,INICIO!$F$33,0))+IF(BE44=0,0,IF(BE44<INICIO!$F$32*2,INICIO!$F$33,0))+IF(BE45=0,0,IF(BE45<INICIO!$F$32*2,INICIO!$F$33,0))+IF(BE46=0,0,IF(BE46<INICIO!$F$32*2,INICIO!$F$33,0)) -> 0 | ... BI48: =IF(BI31=0,0,IF(BI31<INICIO!$F$32*2,INICIO!$F$33,0))+IF(BI32=0,0,IF(BI32<INICIO!$F$32*2,INICIO!$F$33,0))+IF(BI33=0,0,IF(BI33<INICIO!$F$32*2,INICIO!$F$33,0))+IF(BI34=0,0,IF(BI34<INICIO!$F$32*2,INICIO!$F$33,0))+IF(BI35=0,0,IF(BI35<INICIO!$F$32*2,INICIO!$F$33,0))+IF(BI36=0,0,IF(BI36<INICIO!$F$32*2,INICIO!$F$33,0))+IF(BI37=0,0,IF(BI37<INICIO!$F$32*2,INICIO!$F$33,0))+IF(BI38=0,0,IF(BI38<INICIO!$F$32*2,INICIO!$F$33,0))+IF(BI39=0,0,IF(BI39<INICIO!$F$32*2,INICIO!$F$33,0))+IF(BI40=0,0,IF(BI40<INICIO!$F$32*2,INICIO!$F$33,0))+IF(BI41=0,0,IF(BI41<INICIO!$F$32*2,INICIO!$F$33,0))+IF(BI42=0,0,IF(BI42<INICIO!$F$32*2,INICIO!$F$33,0))+IF(BI43=0,0,IF(BI43<INICIO!$F$32*2,INICIO!$F$33,0))+IF(BI44=0,0,IF(BI44<INICIO!$F$32*2,INICIO!$F$33,0))+IF(BI45=0,0,IF(BI45<INICIO!$F$32*2,INICIO!$F$33,0))+IF(BI46=0,0,IF(BI46<INICIO!$F$32*2,INICIO!$F$33,0)) -> 0
A49: ARL | B49: =B47*2.436% -> 85260 | C49: =C47*2.436% -> 85260 | D49: =D47*2.436% -> 85260 | E49: =E47*2.436% -> 85260 | F49: =F47*2.436% -> 85260 | G49: =G47*2.436% -> 85260 | H49: =H47*2.436% -> 85260 | I49: =I47*2.436% -> 85260 | ... BI49: =BI47*2.436% -> 0
A50: EPS | B50: =B47*8.5% -> 297500 | C50: =C47*8.5% -> 297500 | D50: =D47*8.5% -> 297500 | E50: =E47*8.5% -> 297500 | F50: =F47*8.5% -> 297500 | G50: =G47*8.5% -> 297500 | H50: =H47*8.5% -> 297500 | I50: =I47*8.5% -> 297500 | ... BI50: =BI47*8.5% -> 0
A51: AFP | B51: =B47*12% -> 420000 | C51: =C47*12% -> 420000 | D51: =D47*12% -> 420000 | E51: =E47*12% -> 420000 | F51: =F47*12% -> 420000 | G51: =G47*12% -> 420000 | H51: =H47*12% -> 420000 | I51: =I47*12% -> 420000 | ... BI51: =BI47*12% -> 0
A52: Caja de Compensación | B52: =B47*4% -> 140000 | C52: =C47*4% -> 140000 | D52: =D47*4% -> 140000 | E52: =E47*4% -> 140000 | F52: =F47*4% -> 140000 | G52: =G47*4% -> 140000 | H52: =H47*4% -> 140000 | I52: =I47*4% -> 140000 | ... BI52: =BI47*4% -> 0
A53: Primas | B53: =B47*(100%/12) -> 291666.67 | C53: =C47*(100%/12) -> 291666.67 | D53: =D47*(100%/12) -> 291666.67 | E53: =E47*(100%/12) -> 291666.67 | F53: =F47*(100%/12) -> 291666.67 | G53: =G47*(100%/12) -> 291666.67 | H53: =H47*(100%/12) -> 291666.67 | I53: =I47*(100%/12) -> 291666.67 | ... BI53: =BI47*(100%/12) -> 0
A54: Cesantías | B54: =B47*(100%/12) -> 291666.67 | C54: =C47*(100%/12) -> 291666.67 | D54: =D47*(100%/12) -> 291666.67 | E54: =E47*(100%/12) -> 291666.67 | F54: =F47*(100%/12) -> 291666.67 | G54: =G47*(100%/12) -> 291666.67 | H54: =H47*(100%/12) -> 291666.67 | I54: =I47*(100%/12) -> 291666.67 | ... BI54: =BI47*(100%/12) -> 0
A55: Int a las Cesantías | B55: =B54*1% -> 2916.6667 | C55: =C54*1% -> 2916.6667 | D55: =D54*1% -> 2916.6667 | E55: =E54*1% -> 2916.6667 | F55: =F54*1% -> 2916.6667 | G55: =G54*1% -> 2916.6667 | H55: =H54*1% -> 2916.6667 | I55: =I54*1% -> 2916.6667 | ... BI55: =BI54*1% -> 0
A56: Vacaciones | B56: =B47*(100%/24) -> 145833.33 | C56: =C47*(100%/24) -> 145833.33 | D56: =D47*(100%/24) -> 145833.33 | E56: =E47*(100%/24) -> 145833.33 | F56: =F47*(100%/24) -> 145833.33 | G56: =G47*(100%/24) -> 145833.33 | H56: =H47*(100%/24) -> 145833.33 | I56: =I47*(100%/24) -> 145833.33 | ... BI56: =BI47*(100%/24) -> 0
A57: TOTAL PRESTACIONES (OPERATIVAS) | B57: =SUM(B48:B56) -> 1942843.3 | C57: =SUM(C48:C56) -> 1942843.3 | D57: =SUM(D48:D56) -> 1942843.3 | E57: =SUM(E48:E56) -> 1942843.3 | F57: =SUM(F48:F56) -> 1942843.3 | G57: =SUM(G48:G56) -> 1942843.3 | H57: =SUM(H48:H56) -> 1942843.3 | I57: =SUM(I48:I56) -> 1942843.3 | ... BI57: =SUM(BI48:BI56) -> 0
A60: PLAZO DE PAGO Y PLAZO DE INVENTARIOS | B60: =Año1 -> 2027 | N60: =Año2 -> 2028 | Z60: =Año3 -> 2029 | AL60: =Año4 -> 2030 | AX60: =Año5 -> 2031
B61: =B29 -> Mes 1 | C61: =C29 -> Mes 2 | D61: =D29 -> Mes 3 | E61: =E29 -> Mes 4 | F61: =F29 -> Mes 5 | G61: =G29 -> Mes 6 | H61: =H29 -> Mes 7 | I61: =I29 -> Mes 8 | ... BI61: =BI29 -> Mes 60
A62: Plazo que le otorgarán los proveedores para pagar (en días) | B62: 0 | C62: 0 | D62: 0 | E62: 0 | F62: 0 | G62: 0 | H62: 0 | I62: 0 | J62: 0 | K62: 0 | L62: 0 | M62: 0 | N62: 0 | O62: 0 | P62: 0 | Q62: 0 | R62: 0 | S62: 0 | T62: 0 | U62: 0 | V62: 0 | W62: 0 | X62: 0 | Y62: 0 | Z62: 0 | AA62: 0 | AB62: 0 | AC62: 0 | AD62: 0 | AE62: 0 | AF62: 0 | AG62: 0 | AH62: 0 | AI62: 0 | AJ62: 0 | AK62: 0 | AL62: 0 | AM62: 0 | AN62: 0 | AO62: 0 | AP62: 0 | AQ62: 0 | AR62: 0 | AS62: 0 | AT62: 0 | AU62: 0 | AV62: 0 | AW62: 0 | AX62: 0 | AY62: 0 | AZ62: 0 | BA62: 0 | BB62: 0 | BC62: 0 | BD62: 0 | BE62: 0 | BF62: 0 | BG62: 0 | BH62: 0 | BI62: 0
A63: Tiempo promedio en el que mantendrán inventarios (en días)
A65: TOTAL COSTOS | B65: =B25+B47+B57 -> 5612170.3 | C65: =C25+C47+C57 -> 5615490.3 | D65: =D25+D47+D57 -> 5620138.3 | E65: =E25+E47+E57 -> 5625450.3 | F65: =F25+F47+F57 -> 5630762.3 | G65: =G25+G47+G57 -> 5635410.3 | H65: =H25+H47+H57 -> 5745800.3 | I65: =I25+I47+I57 -> 5752440.3 | ... BI65: =BI25+BI47+BI57 -> 0
A68: Plantilla Realizada por María Teresa Macías Joven
A69: Universidad de La Sabana
A70: Versión 2021
A71: ®Todos los derechos reservados
A72: Si desea utilizar esta plantilla por fuera del programa Expo-Empresarial, clase de proyecto empresarial de la Universidad de La Sabana, asegúrese de poseer los derechos de uso por parte de la autora de la plantilla, con una autorización clara, expresa y por escrito.

Sheet GASTOS
B1: =CONCATENATE(INICIO!$B$10," ",INICIO!$B$11) -> TIZA S.A.S
B5: PRESUPUESTO DE GASTOS
A8: GASTOS DE DISTRIBUCIÓN | B8: =Año1 -> 2027 | N8: =Año2 -> 2028 | Z8: =Año3 -> 2029 | AL8: =Año4 -> 2030 | AX8: =Año5 -> 2031
B9: Mes 1 | C9: Mes 2 | D9: Mes 3 | E9: Mes 4 | F9: Mes 5 | G9: Mes 6 | H9: Mes 7 | I9: Mes 8 | J9: Mes 9 | K9: Mes 10 | L9: Mes 11 | M9: Mes 12 | N9: Mes 13 | O9: Mes 14 | P9: Mes 15 | Q9: Mes 16 | R9: Mes 17 | S9: Mes 18 | T9: Mes 19 | U9: Mes 20 | V9: Mes 21 | W9: Mes 22 | X9: Mes 23 | Y9: Mes 24 | Z9: Mes 25 | AA9: Mes 26 | AB9: Mes 27 | AC9: Mes 28 | AD9: Mes 29 | AE9: Mes 30 | AF9: Mes 31 | AG9: Mes 32 | AH9: Mes 33 | AI9: Mes 34 | AJ9: Mes 35 | AK9: Mes 36 | AL9: Mes 37 | AM9: Mes 38 | AN9: Mes 39 | AO9: Mes 40 | AP9: Mes 41 | AQ9: Mes 42 | AR9: Mes 43 | AS9: Mes 44 | AT9: Mes 45 | AU9: Mes 46 | AV9: Mes 47 | AW9: Mes 48 | AX9: Mes 49 | AY9: Mes 50 | AZ9: Mes 51 | BA9: Mes 52 | BB9: Mes 53 | BC9: Mes 54 | BD9: Mes 55 | BE9: Mes 56 | BF9: Mes 57 | BG9: Mes 58 | BH9: Mes 59 | BI9: Mes 60
A10: Empaque y embalaje
A11: Transporte, fletes y acarreos
A15: TOTAL GASTOS DE DISTRIBUCIÓN | B15: =SUM(B10:B14) -> 0 | C15: =SUM(C10:C14) -> 0 | D15: =SUM(D10:D14) -> 0 | E15: =SUM(E10:E14) -> 0 | F15: =SUM(F10:F14) -> 0 | G15: =SUM(G10:G14) -> 0 | H15: =SUM(H10:H14) -> 0 | I15: =SUM(I10:I14) -> 0 | ... BI15: =SUM(BI10:BI14) -> 0
A17: GASTOS DE VENTAS | B17: =Año1 -> 2027 | N17: =Año2 -> 2028 | Z17: =Año3 -> 2029 | AL17: =Año4 -> 2030 | AX17: =Año5 -> 2031
B18: =B9 -> Mes 1 | C18: =C9 -> Mes 2 | D18: =D9 -> Mes 3 | E18: =E9 -> Mes 4 | F18: =F9 -> Mes 5 | G18: =G9 -> Mes 6 | H18: =H9 -> Mes 7 | I18: =I9 -> Mes 8 | ... BI18: =BI9 -> Mes 60
A19: Publicidad, Propaganda y Promoción | B19: 300000 | C19: 300000 | D19: 300000 | E19: 300000 | F19: 300000 | G19: 300000 | H19: 300000 | I19: 300000 | J19: 300000 | K19: 300000 | L19: 300000 | M19: 300000 | N19: 500000 | O19: 500000 | P19: 500000 | Q19: 500000 | R19: 500000 | S19: 500000 | T19: 500000 | U19: 500000 | V19: 500000 | W19: 500000 | X19: 500000 | Y19: 500000 | Z19: 800000 | AA19: 800000 | AB19: 800000 | AC19: 800000 | AD19: 800000 | AE19: 800000 | AF19: 800000 | AG19: 800000 | AH19: 800000 | AI19: 800000 | AJ19: 800000 | AK19: 800000 | AL19: 1200000 | AM19: 1200000 | AN19: 1200000 | AO19: 1200000 | AP19: 1200000 | AQ19: 1200000 | AR19: 1200000 | AS19: 1200000 | AT19: 1200000 | AU19: 1200000 | AV19: 1200000 | AW19: 1200000 | AX19: 1500000
A20: Comisiones de ventas | B20: 0 | C20: 0 | D20: 0 | E20: 0 | F20: 0 | G20: 0 | H20: 0 | I20: 0 | J20: 0 | K20: 0 | L20: 0 | M20: 0 | N20: 0 | O20: 0 | P20: 0 | Q20: 0 | R20: 0 | S20: 0 | T20: 0 | U20: 0 | V20: 0 | W20: 0 | X20: 0 | Y20: 0 | Z20: 0 | AA20: 0 | AB20: 0 | AC20: 0 | AD20: 0 | AE20: 0 | AF20: 0 | AG20: 0 | AH20: 0 | AI20: 0 | AJ20: 0 | AK20: 0 | AL20: 0 | AM20: 0 | AN20: 0 | AO20: 0 | AP20: 0 | AQ20: 0 | AR20: 0 | AS20: 0 | AT20: 0 | AU20: 0 | AV20: 0 | AW20: 0 | AX20: 0
A24: TOTAL GASTOS DE VENTAS | B24: =SUM(B19:B23) -> 300000 | C24: =SUM(C19:C23) -> 300000 | D24: =SUM(D19:D23) -> 300000 | E24: =SUM(E19:E23) -> 300000 | F24: =SUM(F19:F23) -> 300000 | G24: =SUM(G19:G23) -> 300000 | H24: =SUM(H19:H23) -> 300000 | I24: =SUM(I19:I23) -> 300000 | ... BI24: =SUM(BI19:BI23) -> 0
A26: GASTOS ADMINISTRATIVOS | B26: =Año1 -> 2027 | N26: =Año2 -> 2028 | Z26: =Año3 -> 2029 | AL26: =Año4 -> 2030 | AX26: =Año5 -> 2031
B27: =B18 -> Mes 1 | C27: =C18 -> Mes 2 | D27: =D18 -> Mes 3 | E27: =E18 -> Mes 4 | F27: =F18 -> Mes 5 | G27: =G18 -> Mes 6 | H27: =H18 -> Mes 7 | I27: =I18 -> Mes 8 | ... BI27: =BI18 -> Mes 60
A28: Alquiler de oficinas y tiendas al público (no incluye Leasing) | B28: 0 | C28: 0 | D28: 0 | E28: 0 | F28: 0 | G28: 0 | H28: 0 | I28: 0 | J28: 0 | K28: 0 | L28: 0 | M28: 0 | N28: 0 | O28: 0 | P28: 0 | Q28: 0 | R28: 0 | S28: 0 | T28: 0 | U28: 0 | V28: 0 | W28: 0 | X28: 0 | Y28: 0 | Z28: 0 | AA28: 0 | AB28: 0 | AC28: 0 | AD28: 0 | AE28: 0 | AF28: 0 | AG28: 0 | AH28: 0 | AI28: 0 | AJ28: 0 | AK28: 0 | AL28: 0 | AM28: 0 | AN28: 0 | AO28: 0 | AP28: 0 | AQ28: 0 | AR28: 0 | AS28: 0 | AT28: 0 | AU28: 0 | AV28: 0 | AW28: 0 | AX28: 0
A29: Servicios públicos de oficinas administrativas y comerciales | B29: 0 | C29: 0 | D29: 0 | E29: 0 | F29: 0 | G29: 0 | H29: 0 | I29: 0 | J29: 0 | K29: 0 | L29: 0 | M29: 0 | N29: 0 | O29: 0 | P29: 0 | Q29: 0 | R29: 0 | S29: 0 | T29: 0 | U29: 0 | V29: 0 | W29: 0 | X29: 0 | Y29: 0 | Z29: 0 | AA29: 0 | AB29: 0 | AC29: 0 | AD29: 0 | AE29: 0 | AF29: 0 | AG29: 0 | AH29: 0 | AI29: 0 | AJ29: 0 | AK29: 0 | AL29: 0 | AM29: 0 | AN29: 0 | AO29: 0 | AP29: 0 | AQ29: 0 | AR29: 0 | AS29: 0 | AT29: 0 | AU29: 0 | AV29: 0 | AW29: 0 | AX29: 0
A30: Mantenimiento y reparación de la propiedad, planta y equipo | B30: 0 | C30: 0 | D30: 0 | E30: 0 | F30: 0 | G30: 0 | H30: 0 | I30: 0 | J30: 0 | K30: 0 | L30: 0 | M30: 0 | N30: 0 | O30: 0 | P30: 0 | Q30: 0 | R30: 0 | S30: 0 | T30: 0 | U30: 0 | V30: 0 | W30: 0 | X30: 0 | Y30: 0 | Z30: 0 | AA30: 0 | AB30: 0 | AC30: 0 | AD30: 0 | AE30: 0 | AF30: 0 | AG30: 0 | AH30: 0 | AI30: 0 | AJ30: 0 | AK30: 0 | AL30: 0 | AM30: 0 | AN30: 0 | AO30: 0 | AP30: 0 | AQ30: 0 | AR30: 0 | AS30: 0 | AT30: 0 | AU30: 0 | AV30: 0 | AW30: 0 | AX30: 0
A31: Honorario de asesores (contables y/o legales) - supuestos | B31: 0 | C31: 0 | D31: 0 | E31: 0 | F31: 0 | G31: 0 | H31: 0 | I31: 0 | J31: 0 | K31: 0 | L31: 0 | M31: 0 | N31: 500000 | O31: 500000 | P31: 500000 | Q31: 500000 | R31: 500000 | S31: 500000 | T31: 500000 | U31: 500000 | V31: 500000 | W31: 500000 | X31: 500000 | Y31: 500000 | Z31: 600000 | AA31: 600000 | AB31: 600000 | AC31: 600000 | AD31: 600000 | AE31: 600000 | AF31: 600000 | AG31: 600000 | AH31: 600000 | AI31: 600000 | AJ31: 600000 | AK31: 600000 | AL31: 700000 | AM31: 700000 | AN31: 700000 | AO31: 700000 | AP31: 700000 | AQ31: 700000 | AR31: 700000 | AS31: 700000 | AT31: 700000 | AU31: 700000 | AV31: 700000 | AW31: 700000 | AX31: 800000
A32: Servicios de seguridad (pagados a terceros) - | B32: 0 | C32: 0 | D32: 0 | E32: 0 | F32: 0 | G32: 0 | H32: 0 | I32: 0 | J32: 0 | K32: 0 | L32: 0 | M32: 0 | N32: 0 | O32: 0 | P32: 0 | Q32: 0 | R32: 0 | S32: 0 | T32: 0 | U32: 0 | V32: 0 | W32: 0 | X32: 0 | Y32: 0 | Z32: 0 | AA32: 0 | AB32: 0 | AC32: 0 | AD32: 0 | AE32: 0 | AF32: 0 | AG32: 0 | AH32: 0 | AI32: 0 | AJ32: 0 | AK32: 0 | AL32: 0 | AM32: 0 | AN32: 0 | AO32: 0 | AP32: 0 | AQ32: 0 | AR32: 0 | AS32: 0 | AT32: 0 | AU32: 0 | AV32: 0 | AW32: 0 | AX32: 0
A33: Gastos de Papelería - supuestos | B33: 0 | C33: 0 | D33: 0 | E33: 0 | F33: 0 | G33: 0 | H33: 0 | I33: 0 | J33: 0 | K33: 0 | L33: 0 | M33: 0 | N33: 0 | O33: 0 | P33: 0 | Q33: 0 | R33: 0 | S33: 0 | T33: 0 | U33: 0 | V33: 0 | W33: 0 | X33: 0 | Y33: 0 | Z33: 0 | AA33: 0 | AB33: 0 | AC33: 0 | AD33: 0 | AE33: 0 | AF33: 0 | AG33: 0 | AH33: 0 | AI33: 0 | AJ33: 0 | AK33: 0 | AL33: 0 | AM33: 0 | AN33: 0 | AO33: 0 | AP33: 0 | AQ33: 0 | AR33: 0 | AS33: 0 | AT33: 0 | AU33: 0 | AV33: 0 | AW33: 0 | AX33: 0
A34: Gastos de aseo y cafetería - supuestos | B34: 0 | C34: 0 | D34: 0 | E34: 0 | F34: 0 | G34: 0 | H34: 0 | I34: 0 | J34: 0 | K34: 0 | L34: 0 | M34: 0 | N34: 0 | O34: 0 | P34: 0 | Q34: 0 | R34: 0 | S34: 0 | T34: 0 | U34: 0 | V34: 0 | W34: 0 | X34: 0 | Y34: 0 | Z34: 0 | AA34: 0 | AB34: 0 | AC34: 0 | AD34: 0 | AE34: 0 | AF34: 0 | AG34: 0 | AH34: 0 | AI34: 0 | AJ34: 0 | AK34: 0 | AL34: 0 | AM34: 0 | AN34: 0 | AO34: 0 | AP34: 0 | AQ34: 0 | AR34: 0 | AS34: 0 | AT34: 0 | AU34: 0 | AV34: 0 | AW34: 0 | AX34: 0
A35: Internet (Uso de internet en parte administrativa) | B35: 17000 | C35: 17000 | D35: 17000 | E35: 17000 | F35: 17000 | G35: 17000 | H35: 17000 | I35: 17000 | J35: 17000 | K35: 17000 | L35: 17000 | M35: 17000 | N35: 17800 | O35: 17800 | P35: 17800 | Q35: 17800 | R35: 17800 | S35: 17800 | T35: 17800 | U35: 17800 | V35: 17800 | W35: 17800 | X35: 17800 | Y35: 17800 | Z35: 18600 | AA35: 18600 | AB35: 18600 | AC35: 18600 | AD35: 18600 | AE35: 18600 | AF35: 18600 | AG35: 18600 | AH35: 18600 | AI35: 18600 | AJ35: 18600 | AK35: 18600 | AL35: 19400 | AM35: 19400 | AN35: 19400 | AO35: 19400 | AP35: 19400 | AQ35: 19400 | AR35: 19400 | AS35: 19400 | AT35: 19400 | AU35: 19400 | AV35: 19400 | AW35: 19400 | AX35: 20200
A38: TOTAL GASTOS ADMINISTRATIVOS | B38: =SUM(B28:B37) -> 17000 | C38: =SUM(C28:C37) -> 17000 | D38: =SUM(D28:D37) -> 17000 | E38: =SUM(E28:E37) -> 17000 | F38: =SUM(F28:F37) -> 17000 | G38: =SUM(G28:G37) -> 17000 | H38: =SUM(H28:H37) -> 17000 | I38: =SUM(I28:I37) -> 17000 | ... BI38: =SUM(BI28:BI37) -> 0
A40: PRONÓSTICO DE NÓMINA ADMINISTRATIVA Y COMERCIAL | B40: =Año1 -> 2027 | N40: =Año2 -> 2028 | Z40: =Año3 -> 2029 | AL40: =Año4 -> 2030 | AX40: =Año5 -> 2031
B41: =B27 -> Mes 1 | C41: =C27 -> Mes 2 | D41: =D27 -> Mes 3 | E41: =E27 -> Mes 4 | F41: =F27 -> Mes 5 | G41: =G27 -> Mes 6 | H41: =H27 -> Mes 7 | I41: =I27 -> Mes 8 | ... BI41: =BI27 -> Mes 60
A42: Cargo | B42: Salario mensual | C42: Salario mensual | D42: Salario mensual | E42: Salario mensual | F42: Salario mensual | G42: Salario mensual | H42: Salario mensual | I42: Salario mensual | J42: Salario mensual | K42: Salario mensual | L42: Salario mensual | M42: Salario mensual | N42: Salario mensual | O42: Salario mensual | P42: Salario mensual | Q42: Salario mensual | R42: Salario mensual | S42: Salario mensual | T42: Salario mensual | U42: Salario mensual | V42: Salario mensual | W42: Salario mensual | X42: Salario mensual | Y42: Salario mensual | Z42: Salario mensual | AA42: Salario mensual | AB42: Salario mensual | AC42: Salario mensual | AD42: Salario mensual | AE42: Salario mensual | AF42: Salario mensual | AG42: Salario mensual | AH42: Salario mensual | AI42: Salario mensual | AJ42: Salario mensual | AK42: Salario mensual | AL42: Salario mensual | AM42: Salario mensual | AN42: Salario mensual | AO42: Salario mensual | AP42: Salario mensual | AQ42: Salario mensual | AR42: Salario mensual | AS42: Salario mensual | AT42: Salario mensual | AU42: Salario mensual | AV42: Salario mensual | AW42: Salario mensual | AX42: Salario mensual | AY42: Salario mensual | AZ42: Salario mensual | BA42: Salario mensual | BB42: Salario mensual | BC42: Salario mensual | BD42: Salario mensual | BE42: Salario mensual | BF42: Salario mensual | BG42: Salario mensual | BH42: Salario mensual | BI42: Salario mensual
A43: Community Manager | B43: 0 | C43: 0 | D43: 0 | E43: 0 | F43: 0 | G43: 0 | H43: 0 | I43: 0 | J43: 0 | K43: 0 | L43: 0 | M43: 0 | N43: 2500000 | O43: 2500000 | P43: 2500000 | Q43: 2500000 | R43: 2500000 | S43: 2500000 | T43: 2500000 | U43: 2500000 | V43: 2500000 | W43: 2500000 | X43: 2500000 | Y43: 2500000 | Z43: 2600000 | AA43: 2600000 | AB43: 2600000 | AC43: 2600000 | AD43: 2600000 | AE43: 2600000 | AF43: 2600000 | AG43: 2600000 | AH43: 2600000 | AI43: 2600000 | AJ43: 2600000 | AK43: 2600000 | AL43: 2700000 | AM43: 2700000 | AN43: 2700000 | AO43: 2700000 | AP43: 2700000 | AQ43: 2700000 | AR43: 2700000 | AS43: 2700000 | AT43: 2700000 | AU43: 2700000 | AV43: 2700000 | AW43: 2700000 | AX43: 2700000
A44: Soporte al Cliente | B44: 0 | C44: 0 | D44: 0 | E44: 0 | F44: 0 | G44: 0 | H44: 0 | I44: 0 | J44: 0 | K44: 0 | L44: 0 | M44: 0 | N44: 0 | O44: 0 | P44: 0 | Q44: 0 | R44: 0 | S44: 0 | T44: 0 | U44: 0 | V44: 0 | W44: 0 | X44: 0 | Y44: 0 | Z44: 2200000 | AA44: 2200000 | AB44: 2200000 | AC44: 2200000 | AD44: 2200000 | AE44: 2200000 | AF44: 2200000 | AG44: 2200000 | AH44: 2200000 | AI44: 2200000 | AJ44: 2200000 | AK44: 2200000 | AL44: 2300000 | AM44: 2300000 | AN44: 2300000 | AO44: 2300000 | AP44: 2300000 | AQ44: 2300000 | AR44: 2300000 | AS44: 2300000 | AT44: 2300000 | AU44: 2300000 | AV44: 2300000 | AW44: 2300000 | AX44: 2300000
A59: TOTAL NÓMINA ADMINISTRATIVA Y COMERCIAL | B59: =SUM(B43:B58) -> 0 | C59: =SUM(C43:C58) -> 0 | D59: =SUM(D43:D58) -> 0 | E59: =SUM(E43:E58) -> 0 | F59: =SUM(F43:F58) -> 0 | G59: =SUM(G43:G58) -> 0 | H59: =SUM(H43:H58) -> 0 | I59: =SUM(I43:I58) -> 0 | ... BI59: =SUM(BI43:BI58) -> 0
A60: Auxilios de Transporte | B60: =IF(B43=0,0,IF(B43<INICIO!$B$32*2,INICIO!$B$33,0))+IF(B44=0,0,IF(B44<INICIO!$B$32*2,INICIO!$B$33,0))+IF(B45=0,0,IF(B45<INICIO!$B$32*2,INICIO!$B$33,0))+IF(B46=0,0,IF(B46<INICIO!$B$32*2,INICIO!$B$33,0))+IF(B47=0,0,IF(B47<INICIO!$B$32*2,INICIO!$B$33,0))+IF(B48=0,0,IF(B48<INICIO!$B$32*2,INICIO!$B$33,0))+IF(B49=0,0,IF(B49<INICIO!$B$32*2,INICIO!$B$33,0))+IF(B50=0,0,IF(B50<INICIO!$B$32*2,INICIO!$B$33,0))+IF(B51=0,0,IF(B51<INICIO!$B$32*2,INICIO!$B$33,0))+IF(B52=0,0,IF(B52<INICIO!$B$32*2,INICIO!$B$33,0))+IF(B53=0,0,IF(B53<INICIO!$B$32*2,INICIO!$B$33,0))+IF(B54=0,0,IF(B54<INICIO!$B$32*2,INICIO!$B$33,0))+IF(B55=0,0,IF(B55<INICIO!$B$32*2,INICIO!$B$33,0))+IF(B56=0,0,IF(B56<INICIO!$B$32*2,INICIO!$B$33,0))+IF(B57=0,0,IF(B57<INICIO!$B$32*2,INICIO!$B$33,0))+IF(B58=0,0,IF(B58<INICIO!$B$32*2,INICIO!$B$33,0)) -> 0 | C60: =IF(C43=0,0,IF(C43<INICIO!$B$32*2,INICIO!$B$33,0))+IF(C44=0,0,IF(C44<INICIO!$B$32*2,INICIO!$B$33,0))+IF(C45=0,0,IF(C45<INICIO!$B$32*2,INICIO!$B$33,0))+IF(C46=0,0,IF(C46<INICIO!$B$32*2,INICIO!$B$33,0))+IF(C47=0,0,IF(C47<INICIO!$B$32*2,INICIO!$B$33,0))+IF(C48=0,0,IF(C48<INICIO!$B$32*2,INICIO!$B$33,0))+IF(C49=0,0,IF(C49<INICIO!$B$32*2,INICIO!$B$33,0))+IF(C50=0,0,IF(C50<INICIO!$B$32*2,INICIO!$B$33,0))+IF(C51=0,0,IF(C51<INICIO!$B$32*2,INICIO!$B$33,0))+IF(C52=0,0,IF(C52<INICIO!$B$32*2,INICIO!$B$33,0))+IF(C53=0,0,IF(C53<INICIO!$B$32*2,INICIO!$B$33,0))+IF(C54=0,0,IF(C54<INICIO!$B$32*2,INICIO!$B$33,0))+IF(C55=0,0,IF(C55<INICIO!$B$32*2,INICIO!$B$33,0))+IF(C56=0,0,IF(C56<INICIO!$B$32*2,INICIO!$B$33,0))+IF(C57=0,0,IF(C57<INICIO!$B$32*2,INICIO!$B$33,0))+IF(C58=0,0,IF(C58<INICIO!$B$32*2,INICIO!$B$33,0)) -> 0 | D60: =IF(D43=0,0,IF(D43<INICIO!$B$32*2,INICIO!$B$33,0))+IF(D44=0,0,IF(D44<INICIO!$B$32*2,INICIO!$B$33,0))+IF(D45=0,0,IF(D45<INICIO!$B$32*2,INICIO!$B$33,0))+IF(D46=0,0,IF(D46<INICIO!$B$32*2,INICIO!$B$33,0))+IF(D47=0,0,IF(D47<INICIO!$B$32*2,INICIO!$B$33,0))+IF(D48=0,0,IF(D48<INICIO!$B$32*2,INICIO!$B$33,0))+IF(D49=0,0,IF(D49<INICIO!$B$32*2,INICIO!$B$33,0))+IF(D50=0,0,IF(D50<INICIO!$B$32*2,INICIO!$B$33,0))+IF(D51=0,0,IF(D51<INICIO!$B$32*2,INICIO!$B$33,0))+IF(D52=0,0,IF(D52<INICIO!$B$32*2,INICIO!$B$33,0))+IF(D53=0,0,IF(D53<INICIO!$B$32*2,INICIO!$B$33,0))+IF(D54=0,0,IF(D54<INICIO!$B$32*2,INICIO!$B$33,0))+IF(D55=0,0,IF(D55<INICIO!$B$32*2,INICIO!$B$33,0))+IF(D56=0,0,IF(D56<INICIO!$B$32*2,INICIO!$B$33,0))+IF(D57=0,0,IF(D57<INICIO!$B$32*2,INICIO!$B$33,0))+IF(D58=0,0,IF(D58<INICIO!$B$32*2,INICIO!$B$33,0)) -> 0 | E60: =IF(E43=0,0,IF(E43<INICIO!$B$32*2,INICIO!$B$33,0))+IF(E44=0,0,IF(E44<INICIO!$B$32*2,INICIO!$B$33,0))+IF(E45=0,0,IF(E45<INICIO!$B$32*2,INICIO!$B$33,0))+IF(E46=0,0,IF(E46<INICIO!$B$32*2,INICIO!$B$33,0))+IF(E47=0,0,IF(E47<INICIO!$B$32*2,INICIO!$B$33,0))+IF(E48=0,0,IF(E48<INICIO!$B$32*2,INICIO!$B$33,0))+IF(E49=0,0,IF(E49<INICIO!$B$32*2,INICIO!$B$33,0))+IF(E50=0,0,IF(E50<INICIO!$B$32*2,INICIO!$B$33,0))+IF(E51=0,0,IF(E51<INICIO!$B$32*2,INICIO!$B$33,0))+IF(E52=0,0,IF(E52<INICIO!$B$32*2,INICIO!$B$33,0))+IF(E53=0,0,IF(E53<INICIO!$B$32*2,INICIO!$B$33,0))+IF(E54=0,0,IF(E54<INICIO!$B$32*2,INICIO!$B$33,0))+IF(E55=0,0,IF(E55<INICIO!$B$32*2,INICIO!$B$33,0))+IF(E56=0,0,IF(E56<INICIO!$B$32*2,INICIO!$B$33,0))+IF(E57=0,0,IF(E57<INICIO!$B$32*2,INICIO!$B$33,0))+IF(E58=0,0,IF(E58<INICIO!$B$32*2,INICIO!$B$33,0)) -> 0 | F60: =IF(F43=0,0,IF(F43<INICIO!$B$32*2,INICIO!$B$33,0))+IF(F44=0,0,IF(F44<INICIO!$B$32*2,INICIO!$B$33,0))+IF(F45=0,0,IF(F45<INICIO!$B$32*2,INICIO!$B$33,0))+IF(F46=0,0,IF(F46<INICIO!$B$32*2,INICIO!$B$33,0))+IF(F47=0,0,IF(F47<INICIO!$B$32*2,INICIO!$B$33,0))+IF(F48=0,0,IF(F48<INICIO!$B$32*2,INICIO!$B$33,0))+IF(F49=0,0,IF(F49<INICIO!$B$32*2,INICIO!$B$33,0))+IF(F50=0,0,IF(F50<INICIO!$B$32*2,INICIO!$B$33,0))+IF(F51=0,0,IF(F51<INICIO!$B$32*2,INICIO!$B$33,0))+IF(F52=0,0,IF(F52<INICIO!$B$32*2,INICIO!$B$33,0))+IF(F53=0,0,IF(F53<INICIO!$B$32*2,INICIO!$B$33,0))+IF(F54=0,0,IF(F54<INICIO!$B$32*2,INICIO!$B$33,0))+IF(F55=0,0,IF(F55<INICIO!$B$32*2,INICIO!$B$33,0))+IF(F56=0,0,IF(F56<INICIO!$B$32*2,INICIO!$B$33,0))+IF(F57=0,0,IF(F57<INICIO!$B$32*2,INICIO!$B$33,0))+IF(F58=0,0,IF(F58<INICIO!$B$32*2,INICIO!$B$33,0)) -> 0 | G60: =IF(G43=0,0,IF(G43<INICIO!$B$32*2,INICIO!$B$33,0))+IF(G44=0,0,IF(G44<INICIO!$B$32*2,INICIO!$B$33,0))+IF(G45=0,0,IF(G45<INICIO!$B$32*2,INICIO!$B$33,0))+IF(G46=0,0,IF(G46<INICIO!$B$32*2,INICIO!$B$33,0))+IF(G47=0,0,IF(G47<INICIO!$B$32*2,INICIO!$B$33,0))+IF(G48=0,0,IF(G48<INICIO!$B$32*2,INICIO!$B$33,0))+IF(G49=0,0,IF(G49<INICIO!$B$32*2,INICIO!$B$33,0))+IF(G50=0,0,IF(G50<INICIO!$B$32*2,INICIO!$B$33,0))+IF(G51=0,0,IF(G51<INICIO!$B$32*2,INICIO!$B$33,0))+IF(G52=0,0,IF(G52<INICIO!$B$32*2,INICIO!$B$33,0))+IF(G53=0,0,IF(G53<INICIO!$B$32*2,INICIO!$B$33,0))+IF(G54=0,0,IF(G54<INICIO!$B$32*2,INICIO!$B$33,0))+IF(G55=0,0,IF(G55<INICIO!$B$32*2,INICIO!$B$33,0))+IF(G56=0,0,IF(G56<INICIO!$B$32*2,INICIO!$B$33,0))+IF(G57=0,0,IF(G57<INICIO!$B$32*2,INICIO!$B$33,0))+IF(G58=0,0,IF(G58<INICIO!$B$32*2,INICIO!$B$33,0)) -> 0 | H60: =IF(H43=0,0,IF(H43<INICIO!$B$32*2,INICIO!$B$33,0))+IF(H44=0,0,IF(H44<INICIO!$B$32*2,INICIO!$B$33,0))+IF(H45=0,0,IF(H45<INICIO!$B$32*2,INICIO!$B$33,0))+IF(H46=0,0,IF(H46<INICIO!$B$32*2,INICIO!$B$33,0))+IF(H47=0,0,IF(H47<INICIO!$B$32*2,INICIO!$B$33,0))+IF(H48=0,0,IF(H48<INICIO!$B$32*2,INICIO!$B$33,0))+IF(H49=0,0,IF(H49<INICIO!$B$32*2,INICIO!$B$33,0))+IF(H50=0,0,IF(H50<INICIO!$B$32*2,INICIO!$B$33,0))+IF(H51=0,0,IF(H51<INICIO!$B$32*2,INICIO!$B$33,0))+IF(H52=0,0,IF(H52<INICIO!$B$32*2,INICIO!$B$33,0))+IF(H53=0,0,IF(H53<INICIO!$B$32*2,INICIO!$B$33,0))+IF(H54=0,0,IF(H54<INICIO!$B$32*2,INICIO!$B$33,0))+IF(H55=0,0,IF(H55<INICIO!$B$32*2,INICIO!$B$33,0))+IF(H56=0,0,IF(H56<INICIO!$B$32*2,INICIO!$B$33,0))+IF(H57=0,0,IF(H57<INICIO!$B$32*2,INICIO!$B$33,0))+IF(H58=0,0,IF(H58<INICIO!$B$32*2,INICIO!$B$33,0)) -> 0 | I60: =IF(I43=0,0,IF(I43<INICIO!$B$32*2,INICIO!$B$33,0))+IF(I44=0,0,IF(I44<INICIO!$B$32*2,INICIO!$B$33,0))+IF(I45=0,0,IF(I45<INICIO!$B$32*2,INICIO!$B$33,0))+IF(I46=0,0,IF(I46<INICIO!$B$32*2,INICIO!$B$33,0))+IF(I47=0,0,IF(I47<INICIO!$B$32*2,INICIO!$B$33,0))+IF(I48=0,0,IF(I48<INICIO!$B$32*2,INICIO!$B$33,0))+IF(I49=0,0,IF(I49<INICIO!$B$32*2,INICIO!$B$33,0))+IF(I50=0,0,IF(I50<INICIO!$B$32*2,INICIO!$B$33,0))+IF(I51=0,0,IF(I51<INICIO!$B$32*2,INICIO!$B$33,0))+IF(I52=0,0,IF(I52<INICIO!$B$32*2,INICIO!$B$33,0))+IF(I53=0,0,IF(I53<INICIO!$B$32*2,INICIO!$B$33,0))+IF(I54=0,0,IF(I54<INICIO!$B$32*2,INICIO!$B$33,0))+IF(I55=0,0,IF(I55<INICIO!$B$32*2,INICIO!$B$33,0))+IF(I56=0,0,IF(I56<INICIO!$B$32*2,INICIO!$B$33,0))+IF(I57=0,0,IF(I57<INICIO!$B$32*2,INICIO!$B$33,0))+IF(I58=0,0,IF(I58<INICIO!$B$32*2,INICIO!$B$33,0)) -> 0 | ... M60: =IF(M43=0,0,IF(M43<INICIO!$B$32*2,INICIO!$B$33,0))+IF(M44=0,0,IF(M44<INICIO!$B$32*2,INICIO!$B$33,0))+IF(M45=0,0,IF(M45<INICIO!$B$32*2,INICIO!$B$33,0))+IF(M46=0,0,IF(M46<INICIO!$B$32*2,INICIO!$B$33,0))+IF(M47=0,0,IF(M47<INICIO!$B$32*2,INICIO!$B$33,0))+IF(M48=0,0,IF(M48<INICIO!$B$32*2,INICIO!$B$33,0))+IF(M49=0,0,IF(M49<INICIO!$B$32*2,INICIO!$B$33,0))+IF(M50=0,0,IF(M50<INICIO!$B$32*2,INICIO!$B$33,0))+IF(M51=0,0,IF(M51<INICIO!$B$32*2,INICIO!$B$33,0))+IF(M52=0,0,IF(M52<INICIO!$B$32*2,INICIO!$B$33,0))+IF(M53=0,0,IF(M53<INICIO!$B$32*2,INICIO!$B$33,0))+IF(M54=0,0,IF(M54<INICIO!$B$32*2,INICIO!$B$33,0))+IF(M55=0,0,IF(M55<INICIO!$B$32*2,INICIO!$B$33,0))+IF(M56=0,0,IF(M56<INICIO!$B$32*2,INICIO!$B$33,0))+IF(M57=0,0,IF(M57<INICIO!$B$32*2,INICIO!$B$33,0))+IF(M58=0,0,IF(M58<INICIO!$B$32*2,INICIO!$B$33,0)) -> 0 | N60: =IF(N43=0,0,IF(N43<INICIO!$C$32*2,INICIO!$C$33,0))+IF(N44=0,0,IF(N44<INICIO!$C$32*2,INICIO!$C$33,0))+IF(N45=0,0,IF(N45<INICIO!$C$32*2,INICIO!$C$33,0))+IF(N46=0,0,IF(N46<INICIO!$C$32*2,INICIO!$C$33,0))+IF(N47=0,0,IF(N47<INICIO!$C$32*2,INICIO!$C$33,0))+IF(N48=0,0,IF(N48<INICIO!$C$32*2,INICIO!$C$33,0))+IF(N49=0,0,IF(N49<INICIO!$C$32*2,INICIO!$C$33,0))+IF(N50=0,0,IF(N50<INICIO!$C$32*2,INICIO!$C$33,0))+IF(N51=0,0,IF(N51<INICIO!$C$32*2,INICIO!$C$33,0))+IF(N52=0,0,IF(N52<INICIO!$C$32*2,INICIO!$C$33,0))+IF(N53=0,0,IF(N53<INICIO!$C$32*2,INICIO!$C$33,0))+IF(N54=0,0,IF(N54<INICIO!$C$32*2,INICIO!$C$33,0))+IF(N55=0,0,IF(N55<INICIO!$C$32*2,INICIO!$C$33,0))+IF(N56=0,0,IF(N56<INICIO!$C$32*2,INICIO!$C$33,0))+IF(N57=0,0,IF(N57<INICIO!$C$32*2,INICIO!$C$33,0))+IF(N58=0,0,IF(N58<INICIO!$C$32*2,INICIO!$C$33,0)) -> 282000 | O60: =IF(O43=0,0,IF(O43<INICIO!$C$32*2,INICIO!$C$33,0))+IF(O44=0,0,IF(O44<INICIO!$C$32*2,INICIO!$C$33,0))+IF(O45=0,0,IF(O45<INICIO!$C$32*2,INICIO!$C$33,0))+IF(O46=0,0,IF(O46<INICIO!$C$32*2,INICIO!$C$33,0))+IF(O47=0,0,IF(O47<INICIO!$C$32*2,INICIO!$C$33,0))+IF(O48=0,0,IF(O48<INICIO!$C$32*2,INICIO!$C$33,0))+IF(O49=0,0,IF(O49<INICIO!$C$32*2,INICIO!$C$33,0))+IF(O50=0,0,IF(O50<INICIO!$C$32*2,INICIO!$C$33,0))+IF(O51=0,0,IF(O51<INICIO!$C$32*2,INICIO!$C$33,0))+IF(O52=0,0,IF(O52<INICIO!$C$32*2,INICIO!$C$33,0))+IF(O53=0,0,IF(O53<INICIO!$C$32*2,INICIO!$C$33,0))+IF(O54=0,0,IF(O54<INICIO!$C$32*2,INICIO!$C$33,0))+IF(O55=0,0,IF(O55<INICIO!$C$32*2,INICIO!$C$33,0))+IF(O56=0,0,IF(O56<INICIO!$C$32*2,INICIO!$C$33,0))+IF(O57=0,0,IF(O57<INICIO!$C$32*2,INICIO!$C$33,0))+IF(O58=0,0,IF(O58<INICIO!$C$32*2,INICIO!$C$33,0)) -> 282000 | P60: =IF(P43=0,0,IF(P43<INICIO!$C$32*2,INICIO!$C$33,0))+IF(P44=0,0,IF(P44<INICIO!$C$32*2,INICIO!$C$33,0))+IF(P45=0,0,IF(P45<INICIO!$C$32*2,INICIO!$C$33,0))+IF(P46=0,0,IF(P46<INICIO!$C$32*2,INICIO!$C$33,0))+IF(P47=0,0,IF(P47<INICIO!$C$32*2,INICIO!$C$33,0))+IF(P48=0,0,IF(P48<INICIO!$C$32*2,INICIO!$C$33,0))+IF(P49=0,0,IF(P49<INICIO!$C$32*2,INICIO!$C$33,0))+IF(P50=0,0,IF(P50<INICIO!$C$32*2,INICIO!$C$33,0))+IF(P51=0,0,IF(P51<INICIO!$C$32*2,INICIO!$C$33,0))+IF(P52=0,0,IF(P52<INICIO!$C$32*2,INICIO!$C$33,0))+IF(P53=0,0,IF(P53<INICIO!$C$32*2,INICIO!$C$33,0))+IF(P54=0,0,IF(P54<INICIO!$C$32*2,INICIO!$C$33,0))+IF(P55=0,0,IF(P55<INICIO!$C$32*2,INICIO!$C$33,0))+IF(P56=0,0,IF(P56<INICIO!$C$32*2,INICIO!$C$33,0))+IF(P57=0,0,IF(P57<INICIO!$C$32*2,INICIO!$C$33,0))+IF(P58=0,0,IF(P58<INICIO!$C$32*2,INICIO!$C$33,0)) -> 282000 | Q60: =IF(Q43=0,0,IF(Q43<INICIO!$C$32*2,INICIO!$C$33,0))+IF(Q44=0,0,IF(Q44<INICIO!$C$32*2,INICIO!$C$33,0))+IF(Q45=0,0,IF(Q45<INICIO!$C$32*2,INICIO!$C$33,0))+IF(Q46=0,0,IF(Q46<INICIO!$C$32*2,INICIO!$C$33,0))+IF(Q47=0,0,IF(Q47<INICIO!$C$32*2,INICIO!$C$33,0))+IF(Q48=0,0,IF(Q48<INICIO!$C$32*2,INICIO!$C$33,0))+IF(Q49=0,0,IF(Q49<INICIO!$C$32*2,INICIO!$C$33,0))+IF(Q50=0,0,IF(Q50<INICIO!$C$32*2,INICIO!$C$33,0))+IF(Q51=0,0,IF(Q51<INICIO!$C$32*2,INICIO!$C$33,0))+IF(Q52=0,0,IF(Q52<INICIO!$C$32*2,INICIO!$C$33,0))+IF(Q53=0,0,IF(Q53<INICIO!$C$32*2,INICIO!$C$33,0))+IF(Q54=0,0,IF(Q54<INICIO!$C$32*2,INICIO!$C$33,0))+IF(Q55=0,0,IF(Q55<INICIO!$C$32*2,INICIO!$C$33,0))+IF(Q56=0,0,IF(Q56<INICIO!$C$32*2,INICIO!$C$33,0))+IF(Q57=0,0,IF(Q57<INICIO!$C$32*2,INICIO!$C$33,0))+IF(Q58=0,0,IF(Q58<INICIO!$C$32*2,INICIO!$C$33,0)) -> 282000 | R60: =IF(R43=0,0,IF(R43<INICIO!$C$32*2,INICIO!$C$33,0))+IF(R44=0,0,IF(R44<INICIO!$C$32*2,INICIO!$C$33,0))+IF(R45=0,0,IF(R45<INICIO!$C$32*2,INICIO!$C$33,0))+IF(R46=0,0,IF(R46<INICIO!$C$32*2,INICIO!$C$33,0))+IF(R47=0,0,IF(R47<INICIO!$C$32*2,INICIO!$C$33,0))+IF(R48=0,0,IF(R48<INICIO!$C$32*2,INICIO!$C$33,0))+IF(R49=0,0,IF(R49<INICIO!$C$32*2,INICIO!$C$33,0))+IF(R50=0,0,IF(R50<INICIO!$C$32*2,INICIO!$C$33,0))+IF(R51=0,0,IF(R51<INICIO!$C$32*2,INICIO!$C$33,0))+IF(R52=0,0,IF(R52<INICIO!$C$32*2,INICIO!$C$33,0))+IF(R53=0,0,IF(R53<INICIO!$C$32*2,INICIO!$C$33,0))+IF(R54=0,0,IF(R54<INICIO!$C$32*2,INICIO!$C$33,0))+IF(R55=0,0,IF(R55<INICIO!$C$32*2,INICIO!$C$33,0))+IF(R56=0,0,IF(R56<INICIO!$C$32*2,INICIO!$C$33,0))+IF(R57=0,0,IF(R57<INICIO!$C$32*2,INICIO!$C$33,0))+IF(R58=0,0,IF(R58<INICIO!$C$32*2,INICIO!$C$33,0)) -> 282000 | S60: =IF(S43=0,0,IF(S43<INICIO!$C$32*2,INICIO!$C$33,0))+IF(S44=0,0,IF(S44<INICIO!$C$32*2,INICIO!$C$33,0))+IF(S45=0,0,IF(S45<INICIO!$C$32*2,INICIO!$C$33,0))+IF(S46=0,0,IF(S46<INICIO!$C$32*2,INICIO!$C$33,0))+IF(S47=0,0,IF(S47<INICIO!$C$32*2,INICIO!$C$33,0))+IF(S48=0,0,IF(S48<INICIO!$C$32*2,INICIO!$C$33,0))+IF(S49=0,0,IF(S49<INICIO!$C$32*2,INICIO!$C$33,0))+IF(S50=0,0,IF(S50<INICIO!$C$32*2,INICIO!$C$33,0))+IF(S51=0,0,IF(S51<INICIO!$C$32*2,INICIO!$C$33,0))+IF(S52=0,0,IF(S52<INICIO!$C$32*2,INICIO!$C$33,0))+IF(S53=0,0,IF(S53<INICIO!$C$32*2,INICIO!$C$33,0))+IF(S54=0,0,IF(S54<INICIO!$C$32*2,INICIO!$C$33,0))+IF(S55=0,0,IF(S55<INICIO!$C$32*2,INICIO!$C$33,0))+IF(S56=0,0,IF(S56<INICIO!$C$32*2,INICIO!$C$33,0))+IF(S57=0,0,IF(S57<INICIO!$C$32*2,INICIO!$C$33,0))+IF(S58=0,0,IF(S58<INICIO!$C$32*2,INICIO!$C$33,0)) -> 282000 | T60: =IF(T43=0,0,IF(T43<INICIO!$C$32*2,INICIO!$C$33,0))+IF(T44=0,0,IF(T44<INICIO!$C$32*2,INICIO!$C$33,0))+IF(T45=0,0,IF(T45<INICIO!$C$32*2,INICIO!$C$33,0))+IF(T46=0,0,IF(T46<INICIO!$C$32*2,INICIO!$C$33,0))+IF(T47=0,0,IF(T47<INICIO!$C$32*2,INICIO!$C$33,0))+IF(T48=0,0,IF(T48<INICIO!$C$32*2,INICIO!$C$33,0))+IF(T49=0,0,IF(T49<INICIO!$C$32*2,INICIO!$C$33,0))+IF(T50=0,0,IF(T50<INICIO!$C$32*2,INICIO!$C$33,0))+IF(T51=0,0,IF(T51<INICIO!$C$32*2,INICIO!$C$33,0))+IF(T52=0,0,IF(T52<INICIO!$C$32*2,INICIO!$C$33,0))+IF(T53=0,0,IF(T53<INICIO!$C$32*2,INICIO!$C$33,0))+IF(T54=0,0,IF(T54<INICIO!$C$32*2,INICIO!$C$33,0))+IF(T55=0,0,IF(T55<INICIO!$C$32*2,INICIO!$C$33,0))+IF(T56=0,0,IF(T56<INICIO!$C$32*2,INICIO!$C$33,0))+IF(T57=0,0,IF(T57<INICIO!$C$32*2,INICIO!$C$33,0))+IF(T58=0,0,IF(T58<INICIO!$C$32*2,INICIO!$C$33,0)) -> 282000 | U60: =IF(U43=0,0,IF(U43<INICIO!$C$32*2,INICIO!$C$33,0))+IF(U44=0,0,IF(U44<INICIO!$C$32*2,INICIO!$C$33,0))+IF(U45=0,0,IF(U45<INICIO!$C$32*2,INICIO!$C$33,0))+IF(U46=0,0,IF(U46<INICIO!$C$32*2,INICIO!$C$33,0))+IF(U47=0,0,IF(U47<INICIO!$C$32*2,INICIO!$C$33,0))+IF(U48=0,0,IF(U48<INICIO!$C$32*2,INICIO!$C$33,0))+IF(U49=0,0,IF(U49<INICIO!$C$32*2,INICIO!$C$33,0))+IF(U50=0,0,IF(U50<INICIO!$C$32*2,INICIO!$C$33,0))+IF(U51=0,0,IF(U51<INICIO!$C$32*2,INICIO!$C$33,0))+IF(U52=0,0,IF(U52<INICIO!$C$32*2,INICIO!$C$33,0))+IF(U53=0,0,IF(U53<INICIO!$C$32*2,INICIO!$C$33,0))+IF(U54=0,0,IF(U54<INICIO!$C$32*2,INICIO!$C$33,0))+IF(U55=0,0,IF(U55<INICIO!$C$32*2,INICIO!$C$33,0))+IF(U56=0,0,IF(U56<INICIO!$C$32*2,INICIO!$C$33,0))+IF(U57=0,0,IF(U57<INICIO!$C$32*2,INICIO!$C$33,0))+IF(U58=0,0,IF(U58<INICIO!$C$32*2,INICIO!$C$33,0)) -> 282000 | ... Y60: =IF(Y43=0,0,IF(Y43<INICIO!$C$32*2,INICIO!$C$33,0))+IF(Y44=0,0,IF(Y44<INICIO!$C$32*2,INICIO!$C$33,0))+IF(Y45=0,0,IF(Y45<INICIO!$C$32*2,INICIO!$C$33,0))+IF(Y46=0,0,IF(Y46<INICIO!$C$32*2,INICIO!$C$33,0))+IF(Y47=0,0,IF(Y47<INICIO!$C$32*2,INICIO!$C$33,0))+IF(Y48=0,0,IF(Y48<INICIO!$C$32*2,INICIO!$C$33,0))+IF(Y49=0,0,IF(Y49<INICIO!$C$32*2,INICIO!$C$33,0))+IF(Y50=0,0,IF(Y50<INICIO!$C$32*2,INICIO!$C$33,0))+IF(Y51=0,0,IF(Y51<INICIO!$C$32*2,INICIO!$C$33,0))+IF(Y52=0,0,IF(Y52<INICIO!$C$32*2,INICIO!$C$33,0))+IF(Y53=0,0,IF(Y53<INICIO!$C$32*2,INICIO!$C$33,0))+IF(Y54=0,0,IF(Y54<INICIO!$C$32*2,INICIO!$C$33,0))+IF(Y55=0,0,IF(Y55<INICIO!$C$32*2,INICIO!$C$33,0))+IF(Y56=0,0,IF(Y56<INICIO!$C$32*2,INICIO!$C$33,0))+IF(Y57=0,0,IF(Y57<INICIO!$C$32*2,INICIO!$C$33,0))+IF(Y58=0,0,IF(Y58<INICIO!$C$32*2,INICIO!$C$33,0)) -> 282000 | Z60: =IF(Z43=0,0,IF(Z43<INICIO!$D$32*2,INICIO!$D$33,0))+IF(Z44=0,0,IF(Z44<INICIO!$D$32*2,INICIO!$D$33,0))+IF(Z45=0,0,IF(Z45<INICIO!$D$32*2,INICIO!$D$33,0))+IF(Z46=0,0,IF(Z46<INICIO!$D$32*2,INICIO!$D$33,0))+IF(Z47=0,0,IF(Z47<INICIO!$D$32*2,INICIO!$D$33,0))+IF(Z48=0,0,IF(Z48<INICIO!$D$32*2,INICIO!$D$33,0))+IF(Z49=0,0,IF(Z49<INICIO!$D$32*2,INICIO!$D$33,0))+IF(Z50=0,0,IF(Z50<INICIO!$D$32*2,INICIO!$D$33,0))+IF(Z51=0,0,IF(Z51<INICIO!$D$32*2,INICIO!$D$33,0))+IF(Z52=0,0,IF(Z52<INICIO!$D$32*2,INICIO!$D$33,0))+IF(Z53=0,0,IF(Z53<INICIO!$D$32*2,INICIO!$D$33,0))+IF(Z54=0,0,IF(Z54<INICIO!$D$32*2,INICIO!$D$33,0))+IF(Z55=0,0,IF(Z55<INICIO!$D$32*2,INICIO!$D$33,0))+IF(Z56=0,0,IF(Z56<INICIO!$D$32*2,INICIO!$D$33,0))+IF(Z57=0,0,IF(Z57<INICIO!$D$32*2,INICIO!$D$33,0))+IF(Z58=0,0,IF(Z58<INICIO!$D$32*2,INICIO!$D$33,0)) -> 588000 | AA60: =IF(AA43=0,0,IF(AA43<INICIO!$D$32*2,INICIO!$D$33,0))+IF(AA44=0,0,IF(AA44<INICIO!$D$32*2,INICIO!$D$33,0))+IF(AA45=0,0,IF(AA45<INICIO!$D$32*2,INICIO!$D$33,0))+IF(AA46=0,0,IF(AA46<INICIO!$D$32*2,INICIO!$D$33,0))+IF(AA47=0,0,IF(AA47<INICIO!$D$32*2,INICIO!$D$33,0))+IF(AA48=0,0,IF(AA48<INICIO!$D$32*2,INICIO!$D$33,0))+IF(AA49=0,0,IF(AA49<INICIO!$D$32*2,INICIO!$D$33,0))+IF(AA50=0,0,IF(AA50<INICIO!$D$32*2,INICIO!$D$33,0))+IF(AA51=0,0,IF(AA51<INICIO!$D$32*2,INICIO!$D$33,0))+IF(AA52=0,0,IF(AA52<INICIO!$D$32*2,INICIO!$D$33,0))+IF(AA53=0,0,IF(AA53<INICIO!$D$32*2,INICIO!$D$33,0))+IF(AA54=0,0,IF(AA54<INICIO!$D$32*2,INICIO!$D$33,0))+IF(AA55=0,0,IF(AA55<INICIO!$D$32*2,INICIO!$D$33,0))+IF(AA56=0,0,IF(AA56<INICIO!$D$32*2,INICIO!$D$33,0))+IF(AA57=0,0,IF(AA57<INICIO!$D$32*2,INICIO!$D$33,0))+IF(AA58=0,0,IF(AA58<INICIO!$D$32*2,INICIO!$D$33,0)) -> 588000 | AB60: =IF(AB43=0,0,IF(AB43<INICIO!$D$32*2,INICIO!$D$33,0))+IF(AB44=0,0,IF(AB44<INICIO!$D$32*2,INICIO!$D$33,0))+IF(AB45=0,0,IF(AB45<INICIO!$D$32*2,INICIO!$D$33,0))+IF(AB46=0,0,IF(AB46<INICIO!$D$32*2,INICIO!$D$33,0))+IF(AB47=0,0,IF(AB47<INICIO!$D$32*2,INICIO!$D$33,0))+IF(AB48=0,0,IF(AB48<INICIO!$D$32*2,INICIO!$D$33,0))+IF(AB49=0,0,IF(AB49<INICIO!$D$32*2,INICIO!$D$33,0))+IF(AB50=0,0,IF(AB50<INICIO!$D$32*2,INICIO!$D$33,0))+IF(AB51=0,0,IF(AB51<INICIO!$D$32*2,INICIO!$D$33,0))+IF(AB52=0,0,IF(AB52<INICIO!$D$32*2,INICIO!$D$33,0))+IF(AB53=0,0,IF(AB53<INICIO!$D$32*2,INICIO!$D$33,0))+IF(AB54=0,0,IF(AB54<INICIO!$D$32*2,INICIO!$D$33,0))+IF(AB55=0,0,IF(AB55<INICIO!$D$32*2,INICIO!$D$33,0))+IF(AB56=0,0,IF(AB56<INICIO!$D$32*2,INICIO!$D$33,0))+IF(AB57=0,0,IF(AB57<INICIO!$D$32*2,INICIO!$D$33,0))+IF(AB58=0,0,IF(AB58<INICIO!$D$32*2,INICIO!$D$33,0)) -> 588000 | AC60: =IF(AC43=0,0,IF(AC43<INICIO!$D$32*2,INICIO!$D$33,0))+IF(AC44=0,0,IF(AC44<INICIO!$D$32*2,INICIO!$D$33,0))+IF(AC45=0,0,IF(AC45<INICIO!$D$32*2,INICIO!$D$33,0))+IF(AC46=0,0,IF(AC46<INICIO!$D$32*2,INICIO!$D$33,0))+IF(AC47=0,0,IF(AC47<INICIO!$D$32*2,INICIO!$D$33,0))+IF(AC48=0,0,IF(AC48<INICIO!$D$32*2,INICIO!$D$33,0))+IF(AC49=0,0,IF(AC49<INICIO!$D$32*2,INICIO!$D$33,0))+IF(AC50=0,0,IF(AC50<INICIO!$D$32*2,INICIO!$D$33,0))+IF(AC51=0,0,IF(AC51<INICIO!$D$32*2,INICIO!$D$33,0))+IF(AC52=0,0,IF(AC52<INICIO!$D$32*2,INICIO!$D$33,0))+IF(AC53=0,0,IF(AC53<INICIO!$D$32*2,INICIO!$D$33,0))+IF(AC54=0,0,IF(AC54<INICIO!$D$32*2,INICIO!$D$33,0))+IF(AC55=0,0,IF(AC55<INICIO!$D$32*2,INICIO!$D$33,0))+IF(AC56=0,0,IF(AC56<INICIO!$D$32*2,INICIO!$D$33,0))+IF(AC57=0,0,IF(AC57<INICIO!$D$32*2,INICIO!$D$33,0))+IF(AC58=0,0,IF(AC58<INICIO!$D$32*2,INICIO!$D$33,0)) -> 588000 | AD60: =IF(AD43=0,0,IF(AD43<INICIO!$D$32*2,INICIO!$D$33,0))+IF(AD44=0,0,IF(AD44<INICIO!$D$32*2,INICIO!$D$33,0))+IF(AD45=0,0,IF(AD45<INICIO!$D$32*2,INICIO!$D$33,0))+IF(AD46=0,0,IF(AD46<INICIO!$D$32*2,INICIO!$D$33,0))+IF(AD47=0,0,IF(AD47<INICIO!$D$32*2,INICIO!$D$33,0))+IF(AD48=0,0,IF(AD48<INICIO!$D$32*2,INICIO!$D$33,0))+IF(AD49=0,0,IF(AD49<INICIO!$D$32*2,INICIO!$D$33,0))+IF(AD50=0,0,IF(AD50<INICIO!$D$32*2,INICIO!$D$33,0))+IF(AD51=0,0,IF(AD51<INICIO!$D$32*2,INICIO!$D$33,0))+IF(AD52=0,0,IF(AD52<INICIO!$D$32*2,INICIO!$D$33,0))+IF(AD53=0,0,IF(AD53<INICIO!$D$32*2,INICIO!$D$33,0))+IF(AD54=0,0,IF(AD54<INICIO!$D$32*2,INICIO!$D$33,0))+IF(AD55=0,0,IF(AD55<INICIO!$D$32*2,INICIO!$D$33,0))+IF(AD56=0,0,IF(AD56<INICIO!$D$32*2,INICIO!$D$33,0))+IF(AD57=0,0,IF(AD57<INICIO!$D$32*2,INICIO!$D$33,0))+IF(AD58=0,0,IF(AD58<INICIO!$D$32*2,INICIO!$D$33,0)) -> 588000 | AE60: =IF(AE43=0,0,IF(AE43<INICIO!$D$32*2,INICIO!$D$33,0))+IF(AE44=0,0,IF(AE44<INICIO!$D$32*2,INICIO!$D$33,0))+IF(AE45=0,0,IF(AE45<INICIO!$D$32*2,INICIO!$D$33,0))+IF(AE46=0,0,IF(AE46<INICIO!$D$32*2,INICIO!$D$33,0))+IF(AE47=0,0,IF(AE47<INICIO!$D$32*2,INICIO!$D$33,0))+IF(AE48=0,0,IF(AE48<INICIO!$D$32*2,INICIO!$D$33,0))+IF(AE49=0,0,IF(AE49<INICIO!$D$32*2,INICIO!$D$33,0))+IF(AE50=0,0,IF(AE50<INICIO!$D$32*2,INICIO!$D$33,0))+IF(AE51=0,0,IF(AE51<INICIO!$D$32*2,INICIO!$D$33,0))+IF(AE52=0,0,IF(AE52<INICIO!$D$32*2,INICIO!$D$33,0))+IF(AE53=0,0,IF(AE53<INICIO!$D$32*2,INICIO!$D$33,0))+IF(AE54=0,0,IF(AE54<INICIO!$D$32*2,INICIO!$D$33,0))+IF(AE55=0,0,IF(AE55<INICIO!$D$32*2,INICIO!$D$33,0))+IF(AE56=0,0,IF(AE56<INICIO!$D$32*2,INICIO!$D$33,0))+IF(AE57=0,0,IF(AE57<INICIO!$D$32*2,INICIO!$D$33,0))+IF(AE58=0,0,IF(AE58<INICIO!$D$32*2,INICIO!$D$33,0)) -> 588000 | AF60: =IF(AF43=0,0,IF(AF43<INICIO!$D$32*2,INICIO!$D$33,0))+IF(AF44=0,0,IF(AF44<INICIO!$D$32*2,INICIO!$D$33,0))+IF(AF45=0,0,IF(AF45<INICIO!$D$32*2,INICIO!$D$33,0))+IF(AF46=0,0,IF(AF46<INICIO!$D$32*2,INICIO!$D$33,0))+IF(AF47=0,0,IF(AF47<INICIO!$D$32*2,INICIO!$D$33,0))+IF(AF48=0,0,IF(AF48<INICIO!$D$32*2,INICIO!$D$33,0))+IF(AF49=0,0,IF(AF49<INICIO!$D$32*2,INICIO!$D$33,0))+IF(AF50=0,0,IF(AF50<INICIO!$D$32*2,INICIO!$D$33,0))+IF(AF51=0,0,IF(AF51<INICIO!$D$32*2,INICIO!$D$33,0))+IF(AF52=0,0,IF(AF52<INICIO!$D$32*2,INICIO!$D$33,0))+IF(AF53=0,0,IF(AF53<INICIO!$D$32*2,INICIO!$D$33,0))+IF(AF54=0,0,IF(AF54<INICIO!$D$32*2,INICIO!$D$33,0))+IF(AF55=0,0,IF(AF55<INICIO!$D$32*2,INICIO!$D$33,0))+IF(AF56=0,0,IF(AF56<INICIO!$D$32*2,INICIO!$D$33,0))+IF(AF57=0,0,IF(AF57<INICIO!$D$32*2,INICIO!$D$33,0))+IF(AF58=0,0,IF(AF58<INICIO!$D$32*2,INICIO!$D$33,0)) -> 588000 | AG60: =IF(AG43=0,0,IF(AG43<INICIO!$D$32*2,INICIO!$D$33,0))+IF(AG44=0,0,IF(AG44<INICIO!$D$32*2,INICIO!$D$33,0))+IF(AG45=0,0,IF(AG45<INICIO!$D$32*2,INICIO!$D$33,0))+IF(AG46=0,0,IF(AG46<INICIO!$D$32*2,INICIO!$D$33,0))+IF(AG47=0,0,IF(AG47<INICIO!$D$32*2,INICIO!$D$33,0))+IF(AG48=0,0,IF(AG48<INICIO!$D$32*2,INICIO!$D$33,0))+IF(AG49=0,0,IF(AG49<INICIO!$D$32*2,INICIO!$D$33,0))+IF(AG50=0,0,IF(AG50<INICIO!$D$32*2,INICIO!$D$33,0))+IF(AG51=0,0,IF(AG51<INICIO!$D$32*2,INICIO!$D$33,0))+IF(AG52=0,0,IF(AG52<INICIO!$D$32*2,INICIO!$D$33,0))+IF(AG53=0,0,IF(AG53<INICIO!$D$32*2,INICIO!$D$33,0))+IF(AG54=0,0,IF(AG54<INICIO!$D$32*2,INICIO!$D$33,0))+IF(AG55=0,0,IF(AG55<INICIO!$D$32*2,INICIO!$D$33,0))+IF(AG56=0,0,IF(AG56<INICIO!$D$32*2,INICIO!$D$33,0))+IF(AG57=0,0,IF(AG57<INICIO!$D$32*2,INICIO!$D$33,0))+IF(AG58=0,0,IF(AG58<INICIO!$D$32*2,INICIO!$D$33,0)) -> 588000 | ... AK60: =IF(AK43=0,0,IF(AK43<INICIO!$D$32*2,INICIO!$D$33,0))+IF(AK44=0,0,IF(AK44<INICIO!$D$32*2,INICIO!$D$33,0))+IF(AK45=0,0,IF(AK45<INICIO!$D$32*2,INICIO!$D$33,0))+IF(AK46=0,0,IF(AK46<INICIO!$D$32*2,INICIO!$D$33,0))+IF(AK47=0,0,IF(AK47<INICIO!$D$32*2,INICIO!$D$33,0))+IF(AK48=0,0,IF(AK48<INICIO!$D$32*2,INICIO!$D$33,0))+IF(AK49=0,0,IF(AK49<INICIO!$D$32*2,INICIO!$D$33,0))+IF(AK50=0,0,IF(AK50<INICIO!$D$32*2,INICIO!$D$33,0))+IF(AK51=0,0,IF(AK51<INICIO!$D$32*2,INICIO!$D$33,0))+IF(AK52=0,0,IF(AK52<INICIO!$D$32*2,INICIO!$D$33,0))+IF(AK53=0,0,IF(AK53<INICIO!$D$32*2,INICIO!$D$33,0))+IF(AK54=0,0,IF(AK54<INICIO!$D$32*2,INICIO!$D$33,0))+IF(AK55=0,0,IF(AK55<INICIO!$D$32*2,INICIO!$D$33,0))+IF(AK56=0,0,IF(AK56<INICIO!$D$32*2,INICIO!$D$33,0))+IF(AK57=0,0,IF(AK57<INICIO!$D$32*2,INICIO!$D$33,0))+IF(AK58=0,0,IF(AK58<INICIO!$D$32*2,INICIO!$D$33,0)) -> 588000 | AL60: =IF(AL43=0,0,IF(AL43<INICIO!$E$32*2,INICIO!$E$33,0))+IF(AL44=0,0,IF(AL44<INICIO!$E$32*2,INICIO!$E$33,0))+IF(AL45=0,0,IF(AL45<INICIO!$E$32*2,INICIO!$E$33,0))+IF(AL46=0,0,IF(AL46<INICIO!$E$32*2,INICIO!$E$33,0))+IF(AL47=0,0,IF(AL47<INICIO!$E$32*2,INICIO!$E$33,0))+IF(AL48=0,0,IF(AL48<INICIO!$E$32*2,INICIO!$E$33,0))+IF(AL49=0,0,IF(AL49<INICIO!$E$32*2,INICIO!$E$33,0))+IF(AL50=0,0,IF(AL50<INICIO!$E$32*2,INICIO!$E$33,0))+IF(AL51=0,0,IF(AL51<INICIO!$E$32*2,INICIO!$E$33,0))+IF(AL52=0,0,IF(AL52<INICIO!$E$32*2,INICIO!$E$33,0))+IF(AL53=0,0,IF(AL53<INICIO!$E$32*2,INICIO!$E$33,0))+IF(AL54=0,0,IF(AL54<INICIO!$E$32*2,INICIO!$E$33,0))+IF(AL55=0,0,IF(AL55<INICIO!$E$32*2,INICIO!$E$33,0))+IF(AL56=0,0,IF(AL56<INICIO!$E$32*2,INICIO!$E$33,0))+IF(AL57=0,0,IF(AL57<INICIO!$E$32*2,INICIO!$E$33,0))+IF(AL58=0,0,IF(AL58<INICIO!$E$32*2,INICIO!$E$33,0)) -> 612000 | AM60: =IF(AM43=0,0,IF(AM43<INICIO!$E$32*2,INICIO!$E$33,0))+IF(AM44=0,0,IF(AM44<INICIO!$E$32*2,INICIO!$E$33,0))+IF(AM45=0,0,IF(AM45<INICIO!$E$32*2,INICIO!$E$33,0))+IF(AM46=0,0,IF(AM46<INICIO!$E$32*2,INICIO!$E$33,0))+IF(AM47=0,0,IF(AM47<INICIO!$E$32*2,INICIO!$E$33,0))+IF(AM48=0,0,IF(AM48<INICIO!$E$32*2,INICIO!$E$33,0))+IF(AM49=0,0,IF(AM49<INICIO!$E$32*2,INICIO!$E$33,0))+IF(AM50=0,0,IF(AM50<INICIO!$E$32*2,INICIO!$E$33,0))+IF(AM51=0,0,IF(AM51<INICIO!$E$32*2,INICIO!$E$33,0))+IF(AM52=0,0,IF(AM52<INICIO!$E$32*2,INICIO!$E$33,0))+IF(AM53=0,0,IF(AM53<INICIO!$E$32*2,INICIO!$E$33,0))+IF(AM54=0,0,IF(AM54<INICIO!$E$32*2,INICIO!$E$33,0))+IF(AM55=0,0,IF(AM55<INICIO!$E$32*2,INICIO!$E$33,0))+IF(AM56=0,0,IF(AM56<INICIO!$E$32*2,INICIO!$E$33,0))+IF(AM57=0,0,IF(AM57<INICIO!$E$32*2,INICIO!$E$33,0))+IF(AM58=0,0,IF(AM58<INICIO!$E$32*2,INICIO!$E$33,0)) -> 612000 | AN60: =IF(AN43=0,0,IF(AN43<INICIO!$E$32*2,INICIO!$E$33,0))+IF(AN44=0,0,IF(AN44<INICIO!$E$32*2,INICIO!$E$33,0))+IF(AN45=0,0,IF(AN45<INICIO!$E$32*2,INICIO!$E$33,0))+IF(AN46=0,0,IF(AN46<INICIO!$E$32*2,INICIO!$E$33,0))+IF(AN47=0,0,IF(AN47<INICIO!$E$32*2,INICIO!$E$33,0))+IF(AN48=0,0,IF(AN48<INICIO!$E$32*2,INICIO!$E$33,0))+IF(AN49=0,0,IF(AN49<INICIO!$E$32*2,INICIO!$E$33,0))+IF(AN50=0,0,IF(AN50<INICIO!$E$32*2,INICIO!$E$33,0))+IF(AN51=0,0,IF(AN51<INICIO!$E$32*2,INICIO!$E$33,0))+IF(AN52=0,0,IF(AN52<INICIO!$E$32*2,INICIO!$E$33,0))+IF(AN53=0,0,IF(AN53<INICIO!$E$32*2,INICIO!$E$33,0))+IF(AN54=0,0,IF(AN54<INICIO!$E$32*2,INICIO!$E$33,0))+IF(AN55=0,0,IF(AN55<INICIO!$E$32*2,INICIO!$E$33,0))+IF(AN56=0,0,IF(AN56<INICIO!$E$32*2,INICIO!$E$33,0))+IF(AN57=0,0,IF(AN57<INICIO!$E$32*2,INICIO!$E$33,0))+IF(AN58=0,0,IF(AN58<INICIO!$E$32*2,INICIO!$E$33,0)) -> 612000 | AO60: =IF(AO43=0,0,IF(AO43<INICIO!$E$32*2,INICIO!$E$33,0))+IF(AO44=0,0,IF(AO44<INICIO!$E$32*2,INICIO!$E$33,0))+IF(AO45=0,0,IF(AO45<INICIO!$E$32*2,INICIO!$E$33,0))+IF(AO46=0,0,IF(AO46<INICIO!$E$32*2,INICIO!$E$33,0))+IF(AO47=0,0,IF(AO47<INICIO!$E$32*2,INICIO!$E$33,0))+IF(AO48=0,0,IF(AO48<INICIO!$E$32*2,INICIO!$E$33,0))+IF(AO49=0,0,IF(AO49<INICIO!$E$32*2,INICIO!$E$33,0))+IF(AO50=0,0,IF(AO50<INICIO!$E$32*2,INICIO!$E$33,0))+IF(AO51=0,0,IF(AO51<INICIO!$E$32*2,INICIO!$E$33,0))+IF(AO52=0,0,IF(AO52<INICIO!$E$32*2,INICIO!$E$33,0))+IF(AO53=0,0,IF(AO53<INICIO!$E$32*2,INICIO!$E$33,0))+IF(AO54=0,0,IF(AO54<INICIO!$E$32*2,INICIO!$E$33,0))+IF(AO55=0,0,IF(AO55<INICIO!$E$32*2,INICIO!$E$33,0))+IF(AO56=0,0,IF(AO56<INICIO!$E$32*2,INICIO!$E$33,0))+IF(AO57=0,0,IF(AO57<INICIO!$E$32*2,INICIO!$E$33,0))+IF(AO58=0,0,IF(AO58<INICIO!$E$32*2,INICIO!$E$33,0)) -> 612000 | AP60: =IF(AP43=0,0,IF(AP43<INICIO!$E$32*2,INICIO!$E$33,0))+IF(AP44=0,0,IF(AP44<INICIO!$E$32*2,INICIO!$E$33,0))+IF(AP45=0,0,IF(AP45<INICIO!$E$32*2,INICIO!$E$33,0))+IF(AP46=0,0,IF(AP46<INICIO!$E$32*2,INICIO!$E$33,0))+IF(AP47=0,0,IF(AP47<INICIO!$E$32*2,INICIO!$E$33,0))+IF(AP48=0,0,IF(AP48<INICIO!$E$32*2,INICIO!$E$33,0))+IF(AP49=0,0,IF(AP49<INICIO!$E$32*2,INICIO!$E$33,0))+IF(AP50=0,0,IF(AP50<INICIO!$E$32*2,INICIO!$E$33,0))+IF(AP51=0,0,IF(AP51<INICIO!$E$32*2,INICIO!$E$33,0))+IF(AP52=0,0,IF(AP52<INICIO!$E$32*2,INICIO!$E$33,0))+IF(AP53=0,0,IF(AP53<INICIO!$E$32*2,INICIO!$E$33,0))+IF(AP54=0,0,IF(AP54<INICIO!$E$32*2,INICIO!$E$33,0))+IF(AP55=0,0,IF(AP55<INICIO!$E$32*2,INICIO!$E$33,0))+IF(AP56=0,0,IF(AP56<INICIO!$E$32*2,INICIO!$E$33,0))+IF(AP57=0,0,IF(AP57<INICIO!$E$32*2,INICIO!$E$33,0))+IF(AP58=0,0,IF(AP58<INICIO!$E$32*2,INICIO!$E$33,0)) -> 612000 | AQ60: =IF(AQ43=0,0,IF(AQ43<INICIO!$E$32*2,INICIO!$E$33,0))+IF(AQ44=0,0,IF(AQ44<INICIO!$E$32*2,INICIO!$E$33,0))+IF(AQ45=0,0,IF(AQ45<INICIO!$E$32*2,INICIO!$E$33,0))+IF(AQ46=0,0,IF(AQ46<INICIO!$E$32*2,INICIO!$E$33,0))+IF(AQ47=0,0,IF(AQ47<INICIO!$E$32*2,INICIO!$E$33,0))+IF(AQ48=0,0,IF(AQ48<INICIO!$E$32*2,INICIO!$E$33,0))+IF(AQ49=0,0,IF(AQ49<INICIO!$E$32*2,INICIO!$E$33,0))+IF(AQ50=0,0,IF(AQ50<INICIO!$E$32*2,INICIO!$E$33,0))+IF(AQ51=0,0,IF(AQ51<INICIO!$E$32*2,INICIO!$E$33,0))+IF(AQ52=0,0,IF(AQ52<INICIO!$E$32*2,INICIO!$E$33,0))+IF(AQ53=0,0,IF(AQ53<INICIO!$E$32*2,INICIO!$E$33,0))+IF(AQ54=0,0,IF(AQ54<INICIO!$E$32*2,INICIO!$E$33,0))+IF(AQ55=0,0,IF(AQ55<INICIO!$E$32*2,INICIO!$E$33,0))+IF(AQ56=0,0,IF(AQ56<INICIO!$E$32*2,INICIO!$E$33,0))+IF(AQ57=0,0,IF(AQ57<INICIO!$E$32*2,INICIO!$E$33,0))+IF(AQ58=0,0,IF(AQ58<INICIO!$E$32*2,INICIO!$E$33,0)) -> 612000 | AR60: =IF(AR43=0,0,IF(AR43<INICIO!$E$32*2,INICIO!$E$33,0))+IF(AR44=0,0,IF(AR44<INICIO!$E$32*2,INICIO!$E$33,0))+IF(AR45=0,0,IF(AR45<INICIO!$E$32*2,INICIO!$E$33,0))+IF(AR46=0,0,IF(AR46<INICIO!$E$32*2,INICIO!$E$33,0))+IF(AR47=0,0,IF(AR47<INICIO!$E$32*2,INICIO!$E$33,0))+IF(AR48=0,0,IF(AR48<INICIO!$E$32*2,INICIO!$E$33,0))+IF(AR49=0,0,IF(AR49<INICIO!$E$32*2,INICIO!$E$33,0))+IF(AR50=0,0,IF(AR50<INICIO!$E$32*2,INICIO!$E$33,0))+IF(AR51=0,0,IF(AR51<INICIO!$E$32*2,INICIO!$E$33,0))+IF(AR52=0,0,IF(AR52<INICIO!$E$32*2,INICIO!$E$33,0))+IF(AR53=0,0,IF(AR53<INICIO!$E$32*2,INICIO!$E$33,0))+IF(AR54=0,0,IF(AR54<INICIO!$E$32*2,INICIO!$E$33,0))+IF(AR55=0,0,IF(AR55<INICIO!$E$32*2,INICIO!$E$33,0))+IF(AR56=0,0,IF(AR56<INICIO!$E$32*2,INICIO!$E$33,0))+IF(AR57=0,0,IF(AR57<INICIO!$E$32*2,INICIO!$E$33,0))+IF(AR58=0,0,IF(AR58<INICIO!$E$32*2,INICIO!$E$33,0)) -> 612000 | AS60: =IF(AS43=0,0,IF(AS43<INICIO!$E$32*2,INICIO!$E$33,0))+IF(AS44=0,0,IF(AS44<INICIO!$E$32*2,INICIO!$E$33,0))+IF(AS45=0,0,IF(AS45<INICIO!$E$32*2,INICIO!$E$33,0))+IF(AS46=0,0,IF(AS46<INICIO!$E$32*2,INICIO!$E$33,0))+IF(AS47=0,0,IF(AS47<INICIO!$E$32*2,INICIO!$E$33,0))+IF(AS48=0,0,IF(AS48<INICIO!$E$32*2,INICIO!$E$33,0))+IF(AS49=0,0,IF(AS49<INICIO!$E$32*2,INICIO!$E$33,0))+IF(AS50=0,0,IF(AS50<INICIO!$E$32*2,INICIO!$E$33,0))+IF(AS51=0,0,IF(AS51<INICIO!$E$32*2,INICIO!$E$33,0))+IF(AS52=0,0,IF(AS52<INICIO!$E$32*2,INICIO!$E$33,0))+IF(AS53=0,0,IF(AS53<INICIO!$E$32*2,INICIO!$E$33,0))+IF(AS54=0,0,IF(AS54<INICIO!$E$32*2,INICIO!$E$33,0))+IF(AS55=0,0,IF(AS55<INICIO!$E$32*2,INICIO!$E$33,0))+IF(AS56=0,0,IF(AS56<INICIO!$E$32*2,INICIO!$E$33,0))+IF(AS57=0,0,IF(AS57<INICIO!$E$32*2,INICIO!$E$33,0))+IF(AS58=0,0,IF(AS58<INICIO!$E$32*2,INICIO!$E$33,0)) -> 612000 | ... AW60: =IF(AW43=0,0,IF(AW43<INICIO!$E$32*2,INICIO!$E$33,0))+IF(AW44=0,0,IF(AW44<INICIO!$E$32*2,INICIO!$E$33,0))+IF(AW45=0,0,IF(AW45<INICIO!$E$32*2,INICIO!$E$33,0))+IF(AW46=0,0,IF(AW46<INICIO!$E$32*2,INICIO!$E$33,0))+IF(AW47=0,0,IF(AW47<INICIO!$E$32*2,INICIO!$E$33,0))+IF(AW48=0,0,IF(AW48<INICIO!$E$32*2,INICIO!$E$33,0))+IF(AW49=0,0,IF(AW49<INICIO!$E$32*2,INICIO!$E$33,0))+IF(AW50=0,0,IF(AW50<INICIO!$E$32*2,INICIO!$E$33,0))+IF(AW51=0,0,IF(AW51<INICIO!$E$32*2,INICIO!$E$33,0))+IF(AW52=0,0,IF(AW52<INICIO!$E$32*2,INICIO!$E$33,0))+IF(AW53=0,0,IF(AW53<INICIO!$E$32*2,INICIO!$E$33,0))+IF(AW54=0,0,IF(AW54<INICIO!$E$32*2,INICIO!$E$33,0))+IF(AW55=0,0,IF(AW55<INICIO!$E$32*2,INICIO!$E$33,0))+IF(AW56=0,0,IF(AW56<INICIO!$E$32*2,INICIO!$E$33,0))+IF(AW57=0,0,IF(AW57<INICIO!$E$32*2,INICIO!$E$33,0))+IF(AW58=0,0,IF(AW58<INICIO!$E$32*2,INICIO!$E$33,0)) -> 612000 | AX60: =IF(AX43=0,0,IF(AX43<INICIO!$F$32*2,INICIO!$F$33,0))+IF(AX44=0,0,IF(AX44<INICIO!$F$32*2,INICIO!$F$33,0))+IF(AX45=0,0,IF(AX45<INICIO!$F$32*2,INICIO!$F$33,0))+IF(AX46=0,0,IF(AX46<INICIO!$F$32*2,INICIO!$F$33,0))+IF(AX47=0,0,IF(AX47<INICIO!$F$32*2,INICIO!$F$33,0))+IF(AX48=0,0,IF(AX48<INICIO!$F$32*2,INICIO!$F$33,0))+IF(AX49=0,0,IF(AX49<INICIO!$F$32*2,INICIO!$F$33,0))+IF(AX50=0,0,IF(AX50<INICIO!$F$32*2,INICIO!$F$33,0))+IF(AX51=0,0,IF(AX51<INICIO!$F$32*2,INICIO!$F$33,0))+IF(AX52=0,0,IF(AX52<INICIO!$F$32*2,INICIO!$F$33,0))+IF(AX53=0,0,IF(AX53<INICIO!$F$32*2,INICIO!$F$33,0))+IF(AX54=0,0,IF(AX54<INICIO!$F$32*2,INICIO!$F$33,0))+IF(AX55=0,0,IF(AX55<INICIO!$F$32*2,INICIO!$F$33,0))+IF(AX56=0,0,IF(AX56<INICIO!$F$32*2,INICIO!$F$33,0))+IF(AX57=0,0,IF(AX57<INICIO!$F$32*2,INICIO!$F$33,0))+IF(AX58=0,0,IF(AX58<INICIO!$F$32*2,INICIO!$F$33,0)) -> 636000 | AY60: =IF(AY43=0,0,IF(AY43<INICIO!$F$32*2,INICIO!$F$33,0))+IF(AY44=0,0,IF(AY44<INICIO!$F$32*2,INICIO!$F$33,0))+IF(AY45=0,0,IF(AY45<INICIO!$F$32*2,INICIO!$F$33,0))+IF(AY46=0,0,IF(AY46<INICIO!$F$32*2,INICIO!$F$33,0))+IF(AY47=0,0,IF(AY47<INICIO!$F$32*2,INICIO!$F$33,0))+IF(AY48=0,0,IF(AY48<INICIO!$F$32*2,INICIO!$F$33,0))+IF(AY49=0,0,IF(AY49<INICIO!$F$32*2,INICIO!$F$33,0))+IF(AY50=0,0,IF(AY50<INICIO!$F$32*2,INICIO!$F$33,0))+IF(AY51=0,0,IF(AY51<INICIO!$F$32*2,INICIO!$F$33,0))+IF(AY52=0,0,IF(AY52<INICIO!$F$32*2,INICIO!$F$33,0))+IF(AY53=0,0,IF(AY53<INICIO!$F$32*2,INICIO!$F$33,0))+IF(AY54=0,0,IF(AY54<INICIO!$F$32*2,INICIO!$F$33,0))+IF(AY55=0,0,IF(AY55<INICIO!$F$32*2,INICIO!$F$33,0))+IF(AY56=0,0,IF(AY56<INICIO!$F$32*2,INICIO!$F$33,0))+IF(AY57=0,0,IF(AY57<INICIO!$F$32*2,INICIO!$F$33,0))+IF(AY58=0,0,IF(AY58<INICIO!$F$32*2,INICIO!$F$33,0)) -> 0 | AZ60: =IF(AZ43=0,0,IF(AZ43<INICIO!$F$32*2,INICIO!$F$33,0))+IF(AZ44=0,0,IF(AZ44<INICIO!$F$32*2,INICIO!$F$33,0))+IF(AZ45=0,0,IF(AZ45<INICIO!$F$32*2,INICIO!$F$33,0))+IF(AZ46=0,0,IF(AZ46<INICIO!$F$32*2,INICIO!$F$33,0))+IF(AZ47=0,0,IF(AZ47<INICIO!$F$32*2,INICIO!$F$33,0))+IF(AZ48=0,0,IF(AZ48<INICIO!$F$32*2,INICIO!$F$33,0))+IF(AZ49=0,0,IF(AZ49<INICIO!$F$32*2,INICIO!$F$33,0))+IF(AZ50=0,0,IF(AZ50<INICIO!$F$32*2,INICIO!$F$33,0))+IF(AZ51=0,0,IF(AZ51<INICIO!$F$32*2,INICIO!$F$33,0))+IF(AZ52=0,0,IF(AZ52<INICIO!$F$32*2,INICIO!$F$33,0))+IF(AZ53=0,0,IF(AZ53<INICIO!$F$32*2,INICIO!$F$33,0))+IF(AZ54=0,0,IF(AZ54<INICIO!$F$32*2,INICIO!$F$33,0))+IF(AZ55=0,0,IF(AZ55<INICIO!$F$32*2,INICIO!$F$33,0))+IF(AZ56=0,0,IF(AZ56<INICIO!$F$32*2,INICIO!$F$33,0))+IF(AZ57=0,0,IF(AZ57<INICIO!$F$32*2,INICIO!$F$33,0))+IF(AZ58=0,0,IF(AZ58<INICIO!$F$32*2,INICIO!$F$33,0)) -> 0 | BA60: =IF(BA43=0,0,IF(BA43<INICIO!$F$32*2,INICIO!$F$33,0))+IF(BA44=0,0,IF(BA44<INICIO!$F$32*2,INICIO!$F$33,0))+IF(BA45=0,0,IF(BA45<INICIO!$F$32*2,INICIO!$F$33,0))+IF(BA46=0,0,IF(BA46<INICIO!$F$32*2,INICIO!$F$33,0))+IF(BA47=0,0,IF(BA47<INICIO!$F$32*2,INICIO!$F$33,0))+IF(BA48=0,0,IF(BA48<INICIO!$F$32*2,INICIO!$F$33,0))+IF(BA49=0,0,IF(BA49<INICIO!$F$32*2,INICIO!$F$33,0))+IF(BA50=0,0,IF(BA50<INICIO!$F$32*2,INICIO!$F$33,0))+IF(BA51=0,0,IF(BA51<INICIO!$F$32*2,INICIO!$F$33,0))+IF(BA52=0,0,IF(BA52<INICIO!$F$32*2,INICIO!$F$33,0))+IF(BA53=0,0,IF(BA53<INICIO!$F$32*2,INICIO!$F$33,0))+IF(BA54=0,0,IF(BA54<INICIO!$F$32*2,INICIO!$F$33,0))+IF(BA55=0,0,IF(BA55<INICIO!$F$32*2,INICIO!$F$33,0))+IF(BA56=0,0,IF(BA56<INICIO!$F$32*2,INICIO!$F$33,0))+IF(BA57=0,0,IF(BA57<INICIO!$F$32*2,INICIO!$F$33,0))+IF(BA58=0,0,IF(BA58<INICIO!$F$32*2,INICIO!$F$33,0)) -> 0 | BB60: =IF(BB43=0,0,IF(BB43<INICIO!$F$32*2,INICIO!$F$33,0))+IF(BB44=0,0,IF(BB44<INICIO!$F$32*2,INICIO!$F$33,0))+IF(BB45=0,0,IF(BB45<INICIO!$F$32*2,INICIO!$F$33,0))+IF(BB46=0,0,IF(BB46<INICIO!$F$32*2,INICIO!$F$33,0))+IF(BB47=0,0,IF(BB47<INICIO!$F$32*2,INICIO!$F$33,0))+IF(BB48=0,0,IF(BB48<INICIO!$F$32*2,INICIO!$F$33,0))+IF(BB49=0,0,IF(BB49<INICIO!$F$32*2,INICIO!$F$33,0))+IF(BB50=0,0,IF(BB50<INICIO!$F$32*2,INICIO!$F$33,0))+IF(BB51=0,0,IF(BB51<INICIO!$F$32*2,INICIO!$F$33,0))+IF(BB52=0,0,IF(BB52<INICIO!$F$32*2,INICIO!$F$33,0))+IF(BB53=0,0,IF(BB53<INICIO!$F$32*2,INICIO!$F$33,0))+IF(BB54=0,0,IF(BB54<INICIO!$F$32*2,INICIO!$F$33,0))+IF(BB55=0,0,IF(BB55<INICIO!$F$32*2,INICIO!$F$33,0))+IF(BB56=0,0,IF(BB56<INICIO!$F$32*2,INICIO!$F$33,0))+IF(BB57=0,0,IF(BB57<INICIO!$F$32*2,INICIO!$F$33,0))+IF(BB58=0,0,IF(BB58<INICIO!$F$32*2,INICIO!$F$33,0)) -> 0 | BC60: =IF(BC43=0,0,IF(BC43<INICIO!$F$32*2,INICIO!$F$33,0))+IF(BC44=0,0,IF(BC44<INICIO!$F$32*2,INICIO!$F$33,0))+IF(BC45=0,0,IF(BC45<INICIO!$F$32*2,INICIO!$F$33,0))+IF(BC46=0,0,IF(BC46<INICIO!$F$32*2,INICIO!$F$33,0))+IF(BC47=0,0,IF(BC47<INICIO!$F$32*2,INICIO!$F$33,0))+IF(BC48=0,0,IF(BC48<INICIO!$F$32*2,INICIO!$F$33,0))+IF(BC49=0,0,IF(BC49<INICIO!$F$32*2,INICIO!$F$33,0))+IF(BC50=0,0,IF(BC50<INICIO!$F$32*2,INICIO!$F$33,0))+IF(BC51=0,0,IF(BC51<INICIO!$F$32*2,INICIO!$F$33,0))+IF(BC52=0,0,IF(BC52<INICIO!$F$32*2,INICIO!$F$33,0))+IF(BC53=0,0,IF(BC53<INICIO!$F$32*2,INICIO!$F$33,0))+IF(BC54=0,0,IF(BC54<INICIO!$F$32*2,INICIO!$F$33,0))+IF(BC55=0,0,IF(BC55<INICIO!$F$32*2,INICIO!$F$33,0))+IF(BC56=0,0,IF(BC56<INICIO!$F$32*2,INICIO!$F$33,0))+IF(BC57=0,0,IF(BC57<INICIO!$F$32*2,INICIO!$F$33,0))+IF(BC58=0,0,IF(BC58<INICIO!$F$32*2,INICIO!$F$33,0)) -> 0 | BD60: =IF(BD43=0,0,IF(BD43<INICIO!$F$32*2,INICIO!$F$33,0))+IF(BD44=0,0,IF(BD44<INICIO!$F$32*2,INICIO!$F$33,0))+IF(BD45=0,0,IF(BD45<INICIO!$F$32*2,INICIO!$F$33,0))+IF(BD46=0,0,IF(BD46<INICIO!$F$32*2,INICIO!$F$33,0))+IF(BD47=0,0,IF(BD47<INICIO!$F$32*2,INICIO!$F$33,0))+IF(BD48=0,0,IF(BD48<INICIO!$F$32*2,INICIO!$F$33,0))+IF(BD49=0,0,IF(BD49<INICIO!$F$32*2,INICIO!$F$33,0))+IF(BD50=0,0,IF(BD50<INICIO!$F$32*2,INICIO!$F$33,0))+IF(BD51=0,0,IF(BD51<INICIO!$F$32*2,INICIO!$F$33,0))+IF(BD52=0,0,IF(BD52<INICIO!$F$32*2,INICIO!$F$33,0))+IF(BD53=0,0,IF(BD53<INICIO!$F$32*2,INICIO!$F$33,0))+IF(BD54=0,0,IF(BD54<INICIO!$F$32*2,INICIO!$F$33,0))+IF(BD55=0,0,IF(BD55<INICIO!$F$32*2,INICIO!$F$33,0))+IF(BD56=0,0,IF(BD56<INICIO!$F$32*2,INICIO!$F$33,0))+IF(BD57=0,0,IF(BD57<INICIO!$F$32*2,INICIO!$F$33,0))+IF(BD58=0,0,IF(BD58<INICIO!$F$32*2,INICIO!$F$33,0)) -> 0 | BE60: =IF(BE43=0,0,IF(BE43<INICIO!$F$32*2,INICIO!$F$33,0))+IF(BE44=0,0,IF(BE44<INICIO!$F$32*2,INICIO!$F$33,0))+IF(BE45=0,0,IF(BE45<INICIO!$F$32*2,INICIO!$F$33,0))+IF(BE46=0,0,IF(BE46<INICIO!$F$32*2,INICIO!$F$33,0))+IF(BE47=0,0,IF(BE47<INICIO!$F$32*2,INICIO!$F$33,0))+IF(BE48=0,0,IF(BE48<INICIO!$F$32*2,INICIO!$F$33,0))+IF(BE49=0,0,IF(BE49<INICIO!$F$32*2,INICIO!$F$33,0))+IF(BE50=0,0,IF(BE50<INICIO!$F$32*2,INICIO!$F$33,0))+IF(BE51=0,0,IF(BE51<INICIO!$F$32*2,INICIO!$F$33,0))+IF(BE52=0,0,IF(BE52<INICIO!$F$32*2,INICIO!$F$33,0))+IF(BE53=0,0,IF(BE53<INICIO!$F$32*2,INICIO!$F$33,0))+IF(BE54=0,0,IF(BE54<INICIO!$F$32*2,INICIO!$F$33,0))+IF(BE55=0,0,IF(BE55<INICIO!$F$32*2,INICIO!$F$33,0))+IF(BE56=0,0,IF(BE56<INICIO!$F$32*2,INICIO!$F$33,0))+IF(BE57=0,0,IF(BE57<INICIO!$F$32*2,INICIO!$F$33,0))+IF(BE58=0,0,IF(BE58<INICIO!$F$32*2,INICIO!$F$33,0)) -> 0 | ... BI60: =IF(BI43=0,0,IF(BI43<INICIO!$F$32*2,INICIO!$F$33,0))+IF(BI44=0,0,IF(BI44<INICIO!$F$32*2,INICIO!$F$33,0))+IF(BI45=0,0,IF(BI45<INICIO!$F$32*2,INICIO!$F$33,0))+IF(BI46=0,0,IF(BI46<INICIO!$F$32*2,INICIO!$F$33,0))+IF(BI47=0,0,IF(BI47<INICIO!$F$32*2,INICIO!$F$33,0))+IF(BI48=0,0,IF(BI48<INICIO!$F$32*2,INICIO!$F$33,0))+IF(BI49=0,0,IF(BI49<INICIO!$F$32*2,INICIO!$F$33,0))+IF(BI50=0,0,IF(BI50<INICIO!$F$32*2,INICIO!$F$33,0))+IF(BI51=0,0,IF(BI51<INICIO!$F$32*2,INICIO!$F$33,0))+IF(BI52=0,0,IF(BI52<INICIO!$F$32*2,INICIO!$F$33,0))+IF(BI53=0,0,IF(BI53<INICIO!$F$32*2,INICIO!$F$33,0))+IF(BI54=0,0,IF(BI54<INICIO!$F$32*2,INICIO!$F$33,0))+IF(BI55=0,0,IF(BI55<INICIO!$F$32*2,INICIO!$F$33,0))+IF(BI56=0,0,IF(BI56<INICIO!$F$32*2,INICIO!$F$33,0))+IF(BI57=0,0,IF(BI57<INICIO!$F$32*2,INICIO!$F$33,0))+IF(BI58=0,0,IF(BI58<INICIO!$F$32*2,INICIO!$F$33,0)) -> 0
A61: ARL | B61: =B59*0.522% -> 0 | C61: =C59*0.522% -> 0 | D61: =D59*0.522% -> 0 | E61: =E59*0.522% -> 0 | F61: =F59*0.522% -> 0 | G61: =G59*0.522% -> 0 | H61: =H59*0.522% -> 0 | I61: =I59*0.522% -> 0 | ... BI61: =BI59*0.522% -> 0
A62: EPS | B62: =B59*8.5% -> 0 | C62: =C59*8.5% -> 0 | D62: =D59*8.5% -> 0 | E62: =E59*8.5% -> 0 | F62: =F59*8.5% -> 0 | G62: =G59*8.5% -> 0 | H62: =H59*8.5% -> 0 | I62: =I59*8.5% -> 0 | ... BI62: =BI59*8.5% -> 0
A63: AFP | B63: =B59*12% -> 0 | C63: =C59*12% -> 0 | D63: =D59*12% -> 0 | E63: =E59*12% -> 0 | F63: =F59*12% -> 0 | G63: =G59*12% -> 0 | H63: =H59*12% -> 0 | I63: =I59*12% -> 0 | ... BI63: =BI59*12% -> 0
A64: Caja de Compensación | B64: =B59*4% -> 0 | C64: =C59*4% -> 0 | D64: =D59*4% -> 0 | E64: =E59*4% -> 0 | F64: =F59*4% -> 0 | G64: =G59*4% -> 0 | H64: =H59*4% -> 0 | I64: =I59*4% -> 0 | ... BI64: =BI59*4% -> 0
A65: Primas | B65: =B59*(100%/12) -> 0 | C65: =C59*(100%/12) -> 0 | D65: =D59*(100%/12) -> 0 | E65: =E59*(100%/12) -> 0 | F65: =F59*(100%/12) -> 0 | G65: =G59*(100%/12) -> 0 | H65: =H59*(100%/12) -> 0 | I65: =I59*(100%/12) -> 0 | ... BI65: =BI59*(100%/12) -> 0
A66: Cesantías | B66: =B59*(100%/12) -> 0 | C66: =C59*(100%/12) -> 0 | D66: =D59*(100%/12) -> 0 | E66: =E59*(100%/12) -> 0 | F66: =F59*(100%/12) -> 0 | G66: =G59*(100%/12) -> 0 | H66: =H59*(100%/12) -> 0 | I66: =I59*(100%/12) -> 0 | ... BI66: =BI59*(100%/12) -> 0
A67: Int a las Cesantías | B67: =B66*1% -> 0 | C67: =C66*1% -> 0 | D67: =D66*1% -> 0 | E67: =E66*1% -> 0 | F67: =F66*1% -> 0 | G67: =G66*1% -> 0 | H67: =H66*1% -> 0 | I67: =I66*1% -> 0 | ... BI67: =BI66*1% -> 0
A68: Vacaciones | B68: =B59*(100%/24) -> 0 | C68: =C59*(100%/24) -> 0 | D68: =D59*(100%/24) -> 0 | E68: =E59*(100%/24) -> 0 | F68: =F59*(100%/24) -> 0 | G68: =G59*(100%/24) -> 0 | H68: =H59*(100%/24) -> 0 | I68: =I59*(100%/24) -> 0 | ... BI68: =BI59*(100%/24) -> 0
A69: TOTAL PRESTACIONES (ADMINISTRACIÓN Y VENTAS) | B69: =SUM(B60:B68) -> 0 | C69: =SUM(C60:C68) -> 0 | D69: =SUM(D60:D68) -> 0 | E69: =SUM(E60:E68) -> 0 | F69: =SUM(F60:F68) -> 0 | G69: =SUM(G60:G68) -> 0 | H69: =SUM(H60:H68) -> 0 | I69: =SUM(I60:I68) -> 0 | ... BI69: =SUM(BI60:BI68) -> 0
A71: TOTAL GASTOS | B71: =Año1 -> 2027 | N71: =Año2 -> 2028 | Z71: =Año3 -> 2029 | AL71: =Año4 -> 2030 | AX71: =Año5 -> 2031
B72: Mes 1 | C72: Mes 2 | D72: Mes 3 | E72: Mes 4 | F72: Mes 5 | G72: Mes 6 | H72: Mes 7 | I72: Mes 8 | J72: Mes 9 | K72: Mes 10 | L72: Mes 11 | M72: Mes 12 | N72: Mes 13 | O72: Mes 14 | P72: Mes 15 | Q72: Mes 16 | R72: Mes 17 | S72: Mes 18 | T72: Mes 19 | U72: Mes 20 | V72: Mes 21 | W72: Mes 22 | X72: Mes 23 | Y72: Mes 24 | Z72: Mes 25 | AA72: Mes 26 | AB72: Mes 27 | AC72: Mes 28 | AD72: Mes 29 | AE72: Mes 30 | AF72: Mes 31 | AG72: Mes 32 | AH72: Mes 33 | AI72: Mes 34 | AJ72: Mes 35 | AK72: Mes 36 | AL72: Mes 37 | AM72: Mes 38 | AN72: Mes 39 | AO72: Mes 40 | AP72: Mes 41 | AQ72: Mes 42 | AR72: Mes 43 | AS72: Mes 44 | AT72: Mes 45 | AU72: Mes 46 | AV72: Mes 47 | AW72: Mes 48 | AX72: Mes 49 | AY72: Mes 50 | AZ72: Mes 51 | BA72: Mes 52 | BB72: Mes 53 | BC72: Mes 54 | BD72: Mes 55 | BE72: Mes 56 | BF72: Mes 57 | BG72: Mes 58 | BH72: Mes 59 | BI72: Mes 60
A73: Gastos de Distribución | B73: =B15 -> 0 | C73: =C15 -> 0 | D73: =D15 -> 0 | E73: =E15 -> 0 | F73: =F15 -> 0 | G73: =G15 -> 0 | H73: =H15 -> 0 | I73: =I15 -> 0 | ... BI73: =BI15 -> 0
A74: Gastos de Ventas | B74: =B24 -> 300000 | C74: =C24 -> 300000 | D74: =D24 -> 300000 | E74: =E24 -> 300000 | F74: =F24 -> 300000 | G74: =G24 -> 300000 | H74: =H24 -> 300000 | I74: =I24 -> 300000 | ... BI74: =BI24 -> 0
A75: Gastos Administrativos | B75: =B38 -> 17000 | C75: =C38 -> 17000 | D75: =D38 -> 17000 | E75: =E38 -> 17000 | F75: =F38 -> 17000 | G75: =G38 -> 17000 | H75: =H38 -> 17000 | I75: =I38 -> 17000 | ... BI75: =BI38 -> 0
A76: Gastos de Nomina Administrativa y Comercial | B76: =B59+B69 -> 0 | C76: =C59+C69 -> 0 | D76: =D59+D69 -> 0 | E76: =E59+E69 -> 0 | F76: =F59+F69 -> 0 | G76: =G59+G69 -> 0 | H76: =H59+H69 -> 0 | I76: =I59+I69 -> 0 | ... BI76: =BI59+BI69 -> 0
A77: TOTAL GASTOS | B77: =SUM(B73:B76) -> 317000 | C77: =SUM(C73:C76) -> 317000 | D77: =SUM(D73:D76) -> 317000 | E77: =SUM(E73:E76) -> 317000 | F77: =SUM(F73:F76) -> 317000 | G77: =SUM(G73:G76) -> 317000 | H77: =SUM(H73:H76) -> 317000 | I77: =SUM(I73:I76) -> 317000 | ... BI77: =SUM(BI73:BI76) -> 0
A79: CESANTIAS E INTERESES POR PAGAR | B79: =Año1 -> 2027 | N79: =Año2 -> 2028 | Z79: =Año3 -> 2029 | AL79: =Año4 -> 2030 | AX79: =Año5 -> 2031
B80: Mes 1 | C80: Mes 2 | D80: Mes 3 | E80: Mes 4 | F80: Mes 5 | G80: Mes 6 | H80: Mes 7 | I80: Mes 8 | J80: Mes 9 | K80: Mes 10 | L80: Mes 11 | M80: Mes 12 | N80: Mes 13 | O80: Mes 14 | P80: Mes 15 | Q80: Mes 16 | R80: Mes 17 | S80: Mes 18 | T80: Mes 19 | U80: Mes 20 | V80: Mes 21 | W80: Mes 22 | X80: Mes 23 | Y80: Mes 24 | Z80: Mes 25 | AA80: Mes 26 | AB80: Mes 27 | AC80: Mes 28 | AD80: Mes 29 | AE80: Mes 30 | AF80: Mes 31 | AG80: Mes 32 | AH80: Mes 33 | AI80: Mes 34 | AJ80: Mes 35 | AK80: Mes 36 | AL80: Mes 37 | AM80: Mes 38 | AN80: Mes 39 | AO80: Mes 40 | AP80: Mes 41 | AQ80: Mes 42 | AR80: Mes 43 | AS80: Mes 44 | AT80: Mes 45 | AU80: Mes 46 | AV80: Mes 47 | AW80: Mes 48 | AX80: Mes 49 | AY80: Mes 50 | AZ80: Mes 51 | BA80: Mes 52 | BB80: Mes 53 | BC80: Mes 54 | BD80: Mes 55 | BE80: Mes 56 | BF80: Mes 57 | BG80: Mes 58 | BH80: Mes 59 | BI80: Mes 60
A81: Cesantias Mano de Obra Operativa | B81: =SUM(COSTOS!$B$54:B54) -> 291666.67 | C81: =SUM(COSTOS!$B$54:C54) -> 583333.33 | D81: =SUM(COSTOS!$B$54:D54) -> 875000 | E81: =SUM(COSTOS!$B$54:E54) -> 1166666.7 | F81: =SUM(COSTOS!$B$54:F54) -> 1458333.3 | G81: =SUM(COSTOS!$B$54:G54) -> 1750000 | H81: =SUM(COSTOS!$B$54:H54) -> 2041666.7 | I81: =SUM(COSTOS!$B$54:I54) -> 2333333.3 | ... M81: =SUM(COSTOS!$B$54:M54) -> 3500000 | N81: =SUM(COSTOS!$N$54:N54) -> 616666.67 | O81: =SUM(COSTOS!$N$54:O54) -> 1233333.3 | P81: =SUM(COSTOS!$N$54:P54) -> 1850000 | Q81: =SUM(COSTOS!$N$54:Q54) -> 2466666.7 | R81: =SUM(COSTOS!$N$54:R54) -> 3083333.3 | S81: =SUM(COSTOS!$N$54:S54) -> 3700000 | T81: =SUM(COSTOS!$N$54:T54) -> 4316666.7 | U81: =SUM(COSTOS!$N$54:U54) -> 4933333.3 | ... Y81: =SUM(COSTOS!$N$54:Y54) -> 7400000 | Z81: =SUM(COSTOS!$Z$54:Z54) -> 1108333.3 | AA81: =SUM(COSTOS!$Z$54:AA54) -> 2216666.7 | AB81: =SUM(COSTOS!$Z$54:AB54) -> 3325000 | AC81: =SUM(COSTOS!$Z$54:AC54) -> 4433333.3 | AD81: =SUM(COSTOS!$Z$54:AD54) -> 5541666.7 | AE81: =SUM(COSTOS!$Z$54:AE54) -> 6650000 | AF81: =SUM(COSTOS!$Z$54:AF54) -> 7758333.3 | AG81: =SUM(COSTOS!$Z$54:AG54) -> 8866666.7 | ... AK81: =SUM(COSTOS!$Z$54:AK54) -> 13300000 | AL81: =SUM(COSTOS!$AL$54:AL54) -> 1791666.7 | AM81: =SUM(COSTOS!$AL$54:AM54) -> 3583333.3 | AN81: =SUM(COSTOS!$AL$54:AN54) -> 5375000 | AO81: =SUM(COSTOS!$AL$54:AO54) -> 7166666.7 | AP81: =SUM(COSTOS!$AL$54:AP54) -> 8958333.3 | AQ81: =SUM(COSTOS!$AL$54:AQ54) -> 10750000 | AR81: =SUM(COSTOS!$AL$54:AR54) -> 12541667 | AS81: =SUM(COSTOS!$AL$54:AS54) -> 14333333 | ... AW81: =SUM(COSTOS!$AL$54:AW54) -> 21500000 | AX81: =SUM(COSTOS!$AX$54:AX54) -> 1791666.7 | AY81: =SUM(COSTOS!$AX$54:AY54) -> 1791666.7 | AZ81: =SUM(COSTOS!$AX$54:AZ54) -> 1791666.7 | BA81: =SUM(COSTOS!$AX$54:BA54) -> 1791666.7 | BB81: =SUM(COSTOS!$AX$54:BB54) -> 1791666.7 | BC81: =SUM(COSTOS!$AX$54:BC54) -> 1791666.7 | BD81: =SUM(COSTOS!$AX$54:BD54) -> 1791666.7 | BE81: =SUM(COSTOS!$AX$54:BE54) -> 1791666.7 | ... BI81: =SUM(COSTOS!$AX$54:BI54) -> 1791666.7
A82: Intereses a las Cesantias MO Operativa | B82: =SUM(COSTOS!$B$55:B55) -> 2916.6667 | C82: =SUM(COSTOS!$B$55:C55) -> 5833.3333 | D82: =SUM(COSTOS!$B$55:D55) -> 8750 | E82: =SUM(COSTOS!$B$55:E55) -> 11666.667 | F82: =SUM(COSTOS!$B$55:F55) -> 14583.333 | G82: =SUM(COSTOS!$B$55:G55) -> 17500 | H82: =SUM(COSTOS!$B$55:H55) -> 20416.667 | I82: =SUM(COSTOS!$B$55:I55) -> 23333.333 | ... M82: =SUM(COSTOS!$B$55:M55) -> 35000 | N82: =SUM(COSTOS!$N$55:N55) -> 6166.6667 | O82: =SUM(COSTOS!$N$55:O55) -> 12333.333 | P82: =SUM(COSTOS!$N$55:P55) -> 18500 | Q82: =SUM(COSTOS!$N$55:Q55) -> 24666.667 | R82: =SUM(COSTOS!$N$55:R55) -> 30833.333 | S82: =SUM(COSTOS!$N$55:S55) -> 37000 | T82: =SUM(COSTOS!$N$55:T55) -> 43166.667 | U82: =SUM(COSTOS!$N$55:U55) -> 49333.333 | ... Y82: =SUM(COSTOS!$N$55:Y55) -> 74000 | Z82: =SUM(COSTOS!$Z$55:Z55) -> 11083.333 | AA82: =SUM(COSTOS!$Z$55:AA55) -> 22166.667 | AB82: =SUM(COSTOS!$Z$55:AB55) -> 33250 | AC82: =SUM(COSTOS!$Z$55:AC55) -> 44333.333 | AD82: =SUM(COSTOS!$Z$55:AD55) -> 55416.667 | AE82: =SUM(COSTOS!$Z$55:AE55) -> 66500 | AF82: =SUM(COSTOS!$Z$55:AF55) -> 77583.333 | AG82: =SUM(COSTOS!$Z$55:AG55) -> 88666.667 | ... AK82: =SUM(COSTOS!$Z$55:AK55) -> 133000 | AL82: =SUM(COSTOS!$AL$55:AL55) -> 17916.667 | AM82: =SUM(COSTOS!$AL$55:AM55) -> 35833.333 | AN82: =SUM(COSTOS!$AL$55:AN55) -> 53750 | AO82: =SUM(COSTOS!$AL$55:AO55) -> 71666.667 | AP82: =SUM(COSTOS!$AL$55:AP55) -> 89583.333 | AQ82: =SUM(COSTOS!$AL$55:AQ55) -> 107500 | AR82: =SUM(COSTOS!$AL$55:AR55) -> 125416.67 | AS82: =SUM(COSTOS!$AL$55:AS55) -> 143333.33 | ... AW82: =SUM(COSTOS!$AL$55:AW55) -> 215000 | AX82: =SUM(COSTOS!$AX$55:AX55) -> 17916.667 | AY82: =SUM(COSTOS!$AX$55:AY55) -> 17916.667 | AZ82: =SUM(COSTOS!$AX$55:AZ55) -> 17916.667 | BA82: =SUM(COSTOS!$AX$55:BA55) -> 17916.667 | BB82: =SUM(COSTOS!$AX$55:BB55) -> 17916.667 | BC82: =SUM(COSTOS!$AX$55:BC55) -> 17916.667 | BD82: =SUM(COSTOS!$AX$55:BD55) -> 17916.667 | BE82: =SUM(COSTOS!$AX$55:BE55) -> 17916.667 | ... BI82: =SUM(COSTOS!$AX$55:BI55) -> 17916.667
A83: Cesantias Mano de Obra Administrativa | B83: =SUM($B$66:B66) -> 0 | C83: =SUM($B$66:C66) -> 0 | D83: =SUM($B$66:D66) -> 0 | E83: =SUM($B$66:E66) -> 0 | F83: =SUM($B$66:F66) -> 0 | G83: =SUM($B$66:G66) -> 0 | H83: =SUM($B$66:H66) -> 0 | I83: =SUM($B$66:I66) -> 0 | ... M83: =SUM($B$66:M66) -> 0 | N83: =SUM($N$66:N66) -> 208333.33 | O83: =SUM($N$66:O66) -> 416666.67 | P83: =SUM($N$66:P66) -> 625000 | Q83: =SUM($N$66:Q66) -> 833333.33 | R83: =SUM($N$66:R66) -> 1041666.7 | S83: =SUM($N$66:S66) -> 1250000 | T83: =SUM($N$66:T66) -> 1458333.3 | U83: =SUM($N$66:U66) -> 1666666.7 | ... Y83: =SUM($N$66:Y66) -> 2500000 | Z83: =SUM($Z$66:Z66) -> 400000 | AA83: =SUM($Z$66:AA66) -> 800000 | AB83: =SUM($Z$66:AB66) -> 1200000 | AC83: =SUM($Z$66:AC66) -> 1600000 | AD83: =SUM($Z$66:AD66) -> 2000000 | AE83: =SUM($Z$66:AE66) -> 2400000 | AF83: =SUM($Z$66:AF66) -> 2800000 | AG83: =SUM($Z$66:AG66) -> 3200000 | ... AK83: =SUM($Z$66:AK66) -> 4800000 | AL83: =SUM($AL$66:AL66) -> 416666.67 | AM83: =SUM($AL$66:AM66) -> 833333.33 | AN83: =SUM($AL$66:AN66) -> 1250000 | AO83: =SUM($AL$66:AO66) -> 1666666.7 | AP83: =SUM($AL$66:AP66) -> 2083333.3 | AQ83: =SUM($AL$66:AQ66) -> 2500000 | AR83: =SUM($AL$66:AR66) -> 2916666.7 | AS83: =SUM($AL$66:AS66) -> 3333333.3 | ... AW83: =SUM($AL$66:AW66) -> 5000000 | AX83: =SUM($AX$66:AX66) -> 416666.67 | AY83: =SUM($AX$66:AY66) -> 416666.67 | AZ83: =SUM($AX$66:AZ66) -> 416666.67 | BA83: =SUM($AX$66:BA66) -> 416666.67 | BB83: =SUM($AX$66:BB66) -> 416666.67 | BC83: =SUM($AX$66:BC66) -> 416666.67 | BD83: =SUM($AX$66:BD66) -> 416666.67 | BE83: =SUM($AX$66:BE66) -> 416666.67 | ... BI83: =SUM($AX$66:BI66) -> 416666.67
A84: Intereses a las Cesantias MO Administrativa | B84: =SUM($B$67:B67) -> 0 | C84: =SUM($B$67:C67) -> 0 | D84: =SUM($B$67:D67) -> 0 | E84: =SUM($B$67:E67) -> 0 | F84: =SUM($B$67:F67) -> 0 | G84: =SUM($B$67:G67) -> 0 | H84: =SUM($B$67:H67) -> 0 | I84: =SUM($B$67:I67) -> 0 | ... M84: =SUM($B$67:M67) -> 0 | N84: =SUM($N$67:N67) -> 2083.3333 | O84: =SUM($N$67:O67) -> 4166.6667 | P84: =SUM($N$67:P67) -> 6250 | Q84: =SUM($N$67:Q67) -> 8333.3333 | R84: =SUM($N$67:R67) -> 10416.667 | S84: =SUM($N$67:S67) -> 12500 | T84: =SUM($N$67:T67) -> 14583.333 | U84: =SUM($N$67:U67) -> 16666.667 | ... Y84: =SUM($N$67:Y67) -> 25000 | Z84: =SUM($Z$67:Z67) -> 4000 | AA84: =SUM($Z$67:AA67) -> 8000 | AB84: =SUM($Z$67:AB67) -> 12000 | AC84: =SUM($Z$67:AC67) -> 16000 | AD84: =SUM($Z$67:AD67) -> 20000 | AE84: =SUM($Z$67:AE67) -> 24000 | AF84: =SUM($Z$67:AF67) -> 28000 | AG84: =SUM($Z$67:AG67) -> 32000 | ... AK84: =SUM($Z$67:AK67) -> 48000 | AL84: =SUM($AL$67:AL67) -> 4166.6667 | AM84: =SUM($AL$67:AM67) -> 8333.3333 | AN84: =SUM($AL$67:AN67) -> 12500 | AO84: =SUM($AL$67:AO67) -> 16666.667 | AP84: =SUM($AL$67:AP67) -> 20833.333 | AQ84: =SUM($AL$67:AQ67) -> 25000 | AR84: =SUM($AL$67:AR67) -> 29166.667 | AS84: =SUM($AL$67:AS67) -> 33333.333 | ... AW84: =SUM($AL$67:AW67) -> 50000 | AX84: =SUM($AX$67:AX67) -> 4166.6667 | AY84: =SUM($AX$67:AY67) -> 4166.6667 | AZ84: =SUM($AX$67:AZ67) -> 4166.6667 | BA84: =SUM($AX$67:BA67) -> 4166.6667 | BB84: =SUM($AX$67:BB67) -> 4166.6667 | BC84: =SUM($AX$67:BC67) -> 4166.6667 | BD84: =SUM($AX$67:BD67) -> 4166.6667 | BE84: =SUM($AX$67:BE67) -> 4166.6667 | ... BI84: =SUM($AX$67:BI67) -> 4166.6667
A85: Prima de Servicios MO Operativa | B85: =SUM(COSTOS!$B$53:B53) -> 291666.67 | C85: =SUM(COSTOS!$B$53:C53) -> 583333.33 | D85: =SUM(COSTOS!$B$53:D53) -> 875000 | E85: =SUM(COSTOS!$B$53:E53) -> 1166666.7 | F85: =SUM(COSTOS!$B$53:F53) -> 1458333.3 | G85: =SUM(COSTOS!$B$53:G53) -> 1750000 | H85: =SUM(COSTOS!$H$53:H53) -> 291666.67 | I85: =SUM(COSTOS!$H$53:I53) -> 583333.33 | J85: =SUM(COSTOS!$H$53:J53) -> 875000 | K85: =SUM(COSTOS!$H$53:K53) -> 1166666.7 | L85: =SUM(COSTOS!$H$53:L53) -> 1458333.3 | M85: =SUM(COSTOS!$H$53:M53) -> 1750000 | N85: =SUM(COSTOS!$N$53:N53) -> 616666.67 | O85: =SUM(COSTOS!$N$53:O53) -> 1233333.3 | P85: =SUM(COSTOS!$N$53:P53) -> 1850000 | Q85: =SUM(COSTOS!$N$53:Q53) -> 2466666.7 | R85: =SUM(COSTOS!$N$53:R53) -> 3083333.3 | S85: =SUM(COSTOS!$N$53:S53) -> 3700000 | T85: =SUM(COSTOS!$T$53:T53) -> 616666.67 | U85: =SUM(COSTOS!$T$53:U53) -> 1233333.3 | V85: =SUM(COSTOS!$T$53:V53) -> 1850000 | W85: =SUM(COSTOS!$T$53:W53) -> 2466666.7 | X85: =SUM(COSTOS!$T$53:X53) -> 3083333.3 | Y85: =SUM(COSTOS!$T$53:Y53) -> 3700000 | Z85: =SUM(COSTOS!$Z$53:Z53) -> 1108333.3 | AA85: =SUM(COSTOS!$Z$53:AA53) -> 2216666.7 | AB85: =SUM(COSTOS!$Z$53:AB53) -> 3325000 | AC85: =SUM(COSTOS!$Z$53:AC53) -> 4433333.3 | AD85: =SUM(COSTOS!$Z$53:AD53) -> 5541666.7 | AE85: =SUM(COSTOS!$Z$53:AE53) -> 6650000 | AF85: =SUM(COSTOS!$AF$53:AF53) -> 1108333.3 | AG85: =SUM(COSTOS!$AF$53:AG53) -> 2216666.7 | AH85: =SUM(COSTOS!$AF$53:AH53) -> 3325000 | AI85: =SUM(COSTOS!$AF$53:AI53) -> 4433333.3 | AJ85: =SUM(COSTOS!$AF$53:AJ53) -> 5541666.7 | AK85: =SUM(COSTOS!$AF$53:AK53) -> 6650000 | AL85: =SUM(COSTOS!$AL$53:AL53) -> 1791666.7 | AM85: =SUM(COSTOS!$AL$53:AM53) -> 3583333.3 | AN85: =SUM(COSTOS!$AL$53:AN53) -> 5375000 | AO85: =SUM(COSTOS!$AL$53:AO53) -> 7166666.7 | AP85: =SUM(COSTOS!$AL$53:AP53) -> 8958333.3 | AQ85: =SUM(COSTOS!$AL$53:AQ53) -> 10750000 | AR85: =SUM(COSTOS!$AR$53:AR53) -> 1791666.7 | AS85: =SUM(COSTOS!$AR$53:AS53) -> 3583333.3 | AT85: =SUM(COSTOS!$AR$53:AT53) -> 5375000 | AU85: =SUM(COSTOS!$AR$53:AU53) -> 7166666.7 | AV85: =SUM(COSTOS!$AR$53:AV53) -> 8958333.3 | AW85: =SUM(COSTOS!$AR$53:AW53) -> 10750000 | AX85: =SUM(COSTOS!$AX$53:AX53) -> 1791666.7 | AY85: =SUM(COSTOS!$AX$53:AY53) -> 1791666.7 | AZ85: =SUM(COSTOS!$AX$53:AZ53) -> 1791666.7 | BA85: =SUM(COSTOS!$AX$53:BA53) -> 1791666.7 | BB85: =SUM(COSTOS!$AX$53:BB53) -> 1791666.7 | BC85: =SUM(COSTOS!$AX$53:BC53) -> 1791666.7 | BD85: =SUM(COSTOS!$BD$53:BD53) -> 0 | BE85: =SUM(COSTOS!$BD$53:BE53) -> 0 | BF85: =SUM(COSTOS!$BD$53:BF53) -> 0 | BG85: =SUM(COSTOS!$BD$53:BG53) -> 0 | BH85: =SUM(COSTOS!$BD$53:BH53) -> 0 | BI85: =SUM(COSTOS!$BD$53:BI53) -> 0
A86: Prima de Servicios MO Administrativa | B86: =SUM($B$65:B65) -> 0 | C86: =SUM($B$65:C65) -> 0 | D86: =SUM($B$65:D65) -> 0 | E86: =SUM($B$65:E65) -> 0 | F86: =SUM($B$65:F65) -> 0 | G86: =SUM($B$65:G65) -> 0 | H86: =SUM($H$65:H65) -> 0 | I86: =SUM($H$65:I65) -> 0 | J86: =SUM($H$65:J65) -> 0 | K86: =SUM($H$65:K65) -> 0 | L86: =SUM($H$65:L65) -> 0 | M86: =SUM($H$65:M65) -> 0 | N86: =SUM($N$65:N65) -> 208333.33 | O86: =SUM($N$65:O65) -> 416666.67 | P86: =SUM($N$65:P65) -> 625000 | Q86: =SUM($N$65:Q65) -> 833333.33 | R86: =SUM($N$65:R65) -> 1041666.7 | S86: =SUM($N$65:S65) -> 1250000 | T86: =SUM($T$65:T65) -> 208333.33 | U86: =SUM($T$65:U65) -> 416666.67 | V86: =SUM($T$65:V65) -> 625000 | W86: =SUM($T$65:W65) -> 833333.33 | X86: =SUM($T$65:X65) -> 1041666.7 | Y86: =SUM($T$65:Y65) -> 1250000 | Z86: =SUM($Z$65:Z65) -> 400000 | AA86: =SUM($Z$65:AA65) -> 800000 | AB86: =SUM($Z$65:AB65) -> 1200000 | AC86: =SUM($Z$65:AC65) -> 1600000 | AD86: =SUM($Z$65:AD65) -> 2000000 | AE86: =SUM($Z$65:AE65) -> 2400000 | AF86: =SUM($AF$65:AF65) -> 400000 | AG86: =SUM($AF$65:AG65) -> 800000 | AH86: =SUM($AF$65:AH65) -> 1200000 | AI86: =SUM($AF$65:AI65) -> 1600000 | AJ86: =SUM($AF$65:AJ65) -> 2000000 | AK86: =SUM($AF$65:AK65) -> 2400000 | AL86: =SUM($AL$65:AL65) -> 416666.67 | AM86: =SUM($AL$65:AM65) -> 833333.33 | AN86: =SUM($AL$65:AN65) -> 1250000 | AO86: =SUM($AL$65:AO65) -> 1666666.7 | AP86: =SUM($AL$65:AP65) -> 2083333.3 | AQ86: =SUM($AL$65:AQ65) -> 2500000 | AR86: =SUM($AR$65:AR65) -> 416666.67 | AS86: =SUM($AR$65:AS65) -> 833333.33 | AT86: =SUM($AR$65:AT65) -> 1250000 | AU86: =SUM($AR$65:AU65) -> 1666666.7 | AV86: =SUM($AR$65:AV65) -> 2083333.3 | AW86: =SUM($AR$65:AW65) -> 2500000 | AX86: =SUM($AX$65:AX65) -> 416666.67 | AY86: =SUM($AX$65:AY65) -> 416666.67 | AZ86: =SUM($AX$65:AZ65) -> 416666.67 | BA86: =SUM($AX$65:BA65) -> 416666.67 | BB86: =SUM($AX$65:BB65) -> 416666.67 | BC86: =SUM($AX$65:BC65) -> 416666.67 | BD86: =SUM($BD$65:BD65) -> 0 | BE86: =SUM($BD$65:BE65) -> 0 | BF86: =SUM($BD$65:BF65) -> 0 | BG86: =SUM($BD$65:BG65) -> 0 | BH86: =SUM($BD$65:BH65) -> 0 | BI86: =SUM($BD$65:BI65) -> 0
A87: TOTAL CUENTA POR PAGAR PRESTACIONES | B87: =SUM(B81:B86) -> 586250 | C87: =SUM(C81:C86) -> 1172500 | D87: =SUM(D81:D86) -> 1758750 | E87: =SUM(E81:E86) -> 2345000 | F87: =SUM(F81:F86) -> 2931250 | G87: =SUM(G81:G86) -> 3517500 | H87: =SUM(H81:H86) -> 2353750 | I87: =SUM(I81:I86) -> 2940000 | ... BI87: =SUM(BI81:BI86) -> 2230416.7
A90: Plantilla Realizada por María Teresa Macías Joven
A91: Universidad de La Sabana
A92: Versión 2021
A93: ®Todos los derechos reservados
A94: Si desea utilizar esta plantilla por fuera del programa Expo-Empresarial, clase de proyecto empresarial de la Universidad de La Sabana, asegúrese de poseer los derechos de uso por parte de la autora de la plantilla, con una autorización clara, expresa y por escrito.

Sheet INVERSIONES
C1: =CONCATENATE(INICIO!$B$10," ",INICIO!$B$11) -> TIZA S.A.S
C5: PRESUPUESTO DE INVERSIONES
A8: COMPRA DE PROPIEDAD, PLANTA Y EQUIPO E INVERSIONES EN INTANGIBLES | D8: =Año1 -> 2027 | P8: =Año2 -> 2028 | AB8: =Año3 -> 2029 | AN8: =Año4 -> 2030 | AZ8: =Año5 -> 2031
B9: Vida Útil del Activo | C9: Mes 0 | D9: Mes 1 | E9: Mes 2 | F9: Mes 3 | G9: Mes 4 | H9: Mes 5 | I9: Mes 6 | J9: Mes 7 | K9: Mes 8 | L9: Mes 9 | M9: Mes 10 | N9: Mes 11 | O9: Mes 12 | P9: Mes 13 | Q9: Mes 14 | R9: Mes 15 | S9: Mes 16 | T9: Mes 17 | U9: Mes 18 | V9: Mes 19 | W9: Mes 20 | X9: Mes 21 | Y9: Mes 22 | Z9: Mes 23 | AA9: Mes 24 | AB9: Mes 25 | AC9: Mes 26 | AD9: Mes 27 | AE9: Mes 28 | AF9: Mes 29 | AG9: Mes 30 | AH9: Mes 31 | AI9: Mes 32 | AJ9: Mes 33 | AK9: Mes 34 | AL9: Mes 35 | AM9: Mes 36 | AN9: Mes 37 | AO9: Mes 38 | AP9: Mes 39 | AQ9: Mes 40 | AR9: Mes 41 | AS9: Mes 42 | AT9: Mes 43 | AU9: Mes 44 | AV9: Mes 45 | AW9: Mes 46 | AX9: Mes 47 | AY9: Mes 48 | AZ9: Mes 49 | BA9: Mes 50 | BB9: Mes 51 | BC9: Mes 52 | BD9: Mes 53 | BE9: Mes 54 | BF9: Mes 55 | BG9: Mes 56 | BH9: Mes 57 | BI9: Mes 58 | BJ9: Mes 59 | BK9: Mes 60
A10: Laptop Desarrollador 1 | B10: 60
A11: Laptop Desarrollador 2 | B11: 60
A12: Laptop Desarrollador 3 | B12: 60
A13: Monitor Externo (x2) | B13: 60
A14: Laptop Desarrollador 4 | B14: 60
A36: TOTAL INVERSIONES EN PROPIEDAD, PLANTA Y EQUIPO | C36: =SUM(C10:C35) -> 0 | D36: =SUM(D10:D30) -> 0 | E36: =SUM(E10:E30) -> 0 | F36: =SUM(F10:F30) -> 0 | G36: =SUM(G10:G30) -> 0 | H36: =SUM(H10:H30) -> 0 | I36: =SUM(I10:I30) -> 0 | J36: =SUM(J10:J30) -> 0 | K36: =SUM(K10:K30) -> 0 | ... BK36: =SUM(BK10:BK30) -> 0
A39: DEPRECIACIÓN DE LA PROPIEDAD, PLANTA Y EQUIPO Y AMORTIZACIÓN DEL INTANGIBLE | C39: =Año1 -> 2027 | O39: =Año2 -> 2028 | AA39: =Año3 -> 2029 | AM39: =Año4 -> 2030 | AY39: =Año5 -> 2031
C40: Mes 1 | D40: Mes 2 | E40: Mes 3 | F40: Mes 4 | G40: Mes 5 | H40: Mes 6 | I40: Mes 7 | J40: Mes 8 | K40: Mes 9 | L40: Mes 10 | M40: Mes 11 | N40: Mes 12 | O40: Mes 13 | P40: Mes 14 | Q40: Mes 15 | R40: Mes 16 | S40: Mes 17 | T40: Mes 18 | U40: Mes 19 | V40: Mes 20 | W40: Mes 21 | X40: Mes 22 | Y40: Mes 23 | Z40: Mes 24 | AA40: Mes 25 | AB40: Mes 26 | AC40: Mes 27 | AD40: Mes 28 | AE40: Mes 29 | AF40: Mes 30 | AG40: Mes 31 | AH40: Mes 32 | AI40: Mes 33 | AJ40: Mes 34 | AK40: Mes 35 | AL40: Mes 36 | AM40: Mes 37 | AN40: Mes 38 | AO40: Mes 39 | AP40: Mes 40 | AQ40: Mes 41 | AR40: Mes 42 | AS40: Mes 43 | AT40: Mes 44 | AU40: Mes 45 | AV40: Mes 46 | AW40: Mes 47 | AX40: Mes 48 | AY40: Mes 49 | AZ40: Mes 50 | BA40: Mes 51 | BB40: Mes 52 | BC40: Mes 53 | BD40: Mes 54 | BE40: Mes 55 | BF40: Mes 56 | BG40: Mes 57 | BH40: Mes 58 | BI40: Mes 59 | BJ40: Mes 60
A41: =CONCATENATE("Depreciación del activo"," ",A10) -> Depreciación del activo Laptop Desarrollador 1 | C41: =IF($B$10>0,SUM($C$10:C10)/$B$10,0) -> 0 | D41: =IF($B$10>0,SUM($C$10:D10)/$B$10,0) -> 0 | E41: =IF($B$10>0,SUM($C$10:E10)/$B$10,0) -> 0 | F41: =IF($B$10>0,SUM($C$10:F10)/$B$10,0) -> 0 | G41: =IF($B$10>0,SUM($C$10:G10)/$B$10,0) -> 0 | H41: =IF($B$10>0,SUM($C$10:H10)/$B$10,0) -> 0 | I41: =IF($B$10>0,SUM($C$10:I10)/$B$10,0) -> 0 | J41: =IF($B$10>0,SUM($C$10:J10)/$B$10,0) -> 0 | ... BJ41: =IF($B$10>0,SUM($C$10:BJ10)/$B$10,0) -> 0
A42: =CONCATENATE("Depreciación del activo"," ",A11) -> Depreciación del activo Laptop Desarrollador 2 | C42: =IF($B$11>0,SUM($C$11:C11)/$B$11,0) -> 0 | D42: =IF($B$11>0,SUM($C$11:D11)/$B$11,0) -> 0 | E42: =IF($B$11>0,SUM($C$11:E11)/$B$11,0) -> 0 | F42: =IF($B$11>0,SUM($C$11:F11)/$B$11,0) -> 0 | G42: =IF($B$11>0,SUM($C$11:G11)/$B$11,0) -> 0 | H42: =IF($B$11>0,SUM($C$11:H11)/$B$11,0) -> 0 | I42: =IF($B$11>0,SUM($C$11:I11)/$B$11,0) -> 0 | J42: =IF($B$11>0,SUM($C$11:J11)/$B$11,0) -> 0 | ... BJ42: =IF($B$11>0,SUM($C$11:BJ11)/$B$11,0) -> 0
A43: =CONCATENATE("Depreciación del activo"," ",A12) -> Depreciación del activo Laptop Desarrollador 3 | C43: =IF($B$12>0,SUM($C$12:C12)/$B$12,0) -> 0 | D43: =IF($B$12>0,SUM($C$12:D12)/$B$12,0) -> 0 | E43: =IF($B$12>0,SUM($C$12:E12)/$B$12,0) -> 0 | F43: =IF($B$12>0,SUM($C$12:F12)/$B$12,0) -> 0 | G43: =IF($B$12>0,SUM($C$12:G12)/$B$12,0) -> 0 | H43: =IF($B$12>0,SUM($C$12:H12)/$B$12,0) -> 0 | I43: =IF($B$12>0,SUM($C$12:I12)/$B$12,0) -> 0 | J43: =IF($B$12>0,SUM($C$12:J12)/$B$12,0) -> 0 | ... BJ43: =IF($B$12>0,SUM($C$12:BJ12)/$B$12,0) -> 0
A44: =CONCATENATE("Depreciación del activo"," ",A13) -> Depreciación del activo Monitor Externo (x2) | C44: =IF($B$13>0,SUM($C$13:C13)/$B$13,0) -> 0 | D44: =IF($B$13>0,SUM($C$13:D13)/$B$13,0) -> 0 | E44: =IF($B$13>0,SUM($C$13:E13)/$B$13,0) -> 0 | F44: =IF($B$13>0,SUM($C$13:F13)/$B$13,0) -> 0 | G44: =IF($B$13>0,SUM($C$13:G13)/$B$13,0) -> 0 | H44: =IF($B$13>0,SUM($C$13:H13)/$B$13,0) -> 0 | I44: =IF($B$13>0,SUM($C$13:I13)/$B$13,0) -> 0 | J44: =IF($B$13>0,SUM($C$13:J13)/$B$13,0) -> 0 | ... BJ44: =IF($B$13>0,SUM($C$13:BJ13)/$B$13,0) -> 0
A45: =CONCATENATE("Depreciación del activo"," ",A14) -> Depreciación del activo Laptop Desarrollador 4 | C45: =IF($B$14>0,SUM($C$14:C14)/$B$14,0) -> 0 | D45: =IF($B$14>0,SUM($C$14:D14)/$B$14,0) -> 0 | E45: =IF($B$14>0,SUM($C$14:E14)/$B$14,0) -> 0 | F45: =IF($B$14>0,SUM($C$14:F14)/$B$14,0) -> 0 | G45: =IF($B$14>0,SUM($C$14:G14)/$B$14,0) -> 0 | H45: =IF($B$14>0,SUM($C$14:H14)/$B$14,0) -> 0 | I45: =IF($B$14>0,SUM($C$14:I14)/$B$14,0) -> 0 | J45: =IF($B$14>0,SUM($C$14:J14)/$B$14,0) -> 0 | ... BJ45: =IF($B$14>0,SUM($C$14:BJ14)/$B$14,0) -> 0
A46: =CONCATENATE("Depreciación del activo"," ",A15) -> Depreciación del activo | C46: =IF($B$15>0,SUM($C$15:C15)/$B$15,0) -> 0 | D46: =IF($B$15>0,SUM($C$15:D15)/$B$15,0) -> 0 | E46: =IF($B$15>0,SUM($C$15:E15)/$B$15,0) -> 0 | F46: =IF($B$15>0,SUM($C$15:F15)/$B$15,0) -> 0 | G46: =IF($B$15>0,SUM($C$15:G15)/$B$15,0) -> 0 | H46: =IF($B$15>0,SUM($C$15:H15)/$B$15,0) -> 0 | I46: =IF($B$15>0,SUM($C$15:I15)/$B$15,0) -> 0 | J46: =IF($B$15>0,SUM($C$15:J15)/$B$15,0) -> 0 | ... BJ46: =IF($B$15>0,SUM($C$15:BJ15)/$B$15,0) -> 0
A47: =CONCATENATE("Depreciación del activo"," ",A16) -> Depreciación del activo | C47: =IF($B$16>0,SUM($C$16:C16)/$B$16,0) -> 0 | D47: =IF($B$16>0,SUM($C$16:D16)/$B$16,0) -> 0 | E47: =IF($B$16>0,SUM($C$16:E16)/$B$16,0) -> 0 | F47: =IF($B$16>0,SUM($C$16:F16)/$B$16,0) -> 0 | G47: =IF($B$16>0,SUM($C$16:G16)/$B$16,0) -> 0 | H47: =IF($B$16>0,SUM($C$16:H16)/$B$16,0) -> 0 | I47: =IF($B$16>0,SUM($C$16:I16)/$B$16,0) -> 0 | J47: =IF($B$16>0,SUM($C$16:J16)/$B$16,0) -> 0 | ... BJ47: =IF($B$16>0,SUM($C$16:BJ16)/$B$16,0) -> 0
A48: =CONCATENATE("Depreciación del activo"," ",A17) -> Depreciación del activo | C48: =IF($B$17>0,SUM($C$17:C17)/$B$17,0) -> 0 | D48: =IF($B$17>0,SUM($C$17:D17)/$B$17,0) -> 0 | E48: =IF($B$17>0,SUM($C$17:E17)/$B$17,0) -> 0 | F48: =IF($B$17>0,SUM($C$17:F17)/$B$17,0) -> 0 | G48: =IF($B$17>0,SUM($C$17:G17)/$B$17,0) -> 0 | H48: =IF($B$17>0,SUM($C$17:H17)/$B$17,0) -> 0 | I48: =IF($B$17>0,SUM($C$17:I17)/$B$17,0) -> 0 | J48: =IF($B$17>0,SUM($C$17:J17)/$B$17,0) -> 0 | ... BJ48: =IF($B$17>0,SUM($C$17:BJ17)/$B$17,0) -> 0
A49: =CONCATENATE("Depreciación del activo"," ",A18) -> Depreciación del activo | C49: =IF($B$18>0,SUM($C$18:C18)/$B$18,0) -> 0 | D49: =IF($B$18>0,SUM($C$18:D18)/$B$18,0) -> 0 | E49: =IF($B$18>0,SUM($C$18:E18)/$B$18,0) -> 0 | F49: =IF($B$18>0,SUM($C$18:F18)/$B$18,0) -> 0 | G49: =IF($B$18>0,SUM($C$18:G18)/$B$18,0) -> 0 | H49: =IF($B$18>0,SUM($C$18:H18)/$B$18,0) -> 0 | I49: =IF($B$18>0,SUM($C$18:I18)/$B$18,0) -> 0 | J49: =IF($B$18>0,SUM($C$18:J18)/$B$18,0) -> 0 | ... BJ49: =IF($B$18>0,SUM($C$18:BJ18)/$B$18,0) -> 0
A50: =CONCATENATE("Depreciación del activo"," ",A19) -> Depreciación del activo | C50: =IF($B$19>0,SUM($C$19:C19)/$B$19,0) -> 0 | D50: =IF($B$19>0,SUM($C$19:D19)/$B$19,0) -> 0 | E50: =IF($B$19>0,SUM($C$19:E19)/$B$19,0) -> 0 | F50: =IF($B$19>0,SUM($C$19:F19)/$B$19,0) -> 0 | G50: =IF($B$19>0,SUM($C$19:G19)/$B$19,0) -> 0 | H50: =IF($B$19>0,SUM($C$19:H19)/$B$19,0) -> 0 | I50: =IF($B$19>0,SUM($C$19:I19)/$B$19,0) -> 0 | J50: =IF($B$19>0,SUM($C$19:J19)/$B$19,0) -> 0 | ... BJ50: =IF($B$19>0,SUM($C$19:BJ19)/$B$19,0) -> 0
A51: =CONCATENATE("Depreciación del activo"," ",A20) -> Depreciación del activo | C51: =IF($B$20>0,SUM($C$20:C20)/$B$20,0) -> 0 | D51: =IF($B$20>0,SUM($C$20:D20)/$B$20,0) -> 0 | E51: =IF($B$20>0,SUM($C$20:E20)/$B$20,0) -> 0 | F51: =IF($B$20>0,SUM($C$20:F20)/$B$20,0) -> 0 | G51: =IF($B$20>0,SUM($C$20:G20)/$B$20,0) -> 0 | H51: =IF($B$20>0,SUM($C$20:H20)/$B$20,0) -> 0 | I51: =IF($B$20>0,SUM($C$20:I20)/$B$20,0) -> 0 | J51: =IF($B$20>0,SUM($C$20:J20)/$B$20,0) -> 0 | ... BJ51: =IF($B$20>0,SUM($C$20:BJ20)/$B$20,0) -> 0
A52: =CONCATENATE("Depreciación del activo"," ",A21) -> Depreciación del activo | C52: =IF($B$21>0,SUM($C$21:C21)/$B$21,0) -> 0 | D52: =IF($B$21>0,SUM($C$21:D21)/$B$21,0) -> 0 | E52: =IF($B$21>0,SUM($C$21:E21)/$B$21,0) -> 0 | F52: =IF($B$21>0,SUM($C$21:F21)/$B$21,0) -> 0 | G52: =IF($B$21>0,SUM($C$21:G21)/$B$21,0) -> 0 | H52: =IF($B$21>0,SUM($C$21:H21)/$B$21,0) -> 0 | I52: =IF($B$21>0,SUM($C$21:I21)/$B$21,0) -> 0 | J52: =IF($B$21>0,SUM($C$21:J21)/$B$21,0) -> 0 | ... BJ52: =IF($B$21>0,SUM($C$21:BJ21)/$B$21,0) -> 0
A53: =CONCATENATE("Depreciación del activo"," ",A22) -> Depreciación del activo | C53: =IF($B$22>0,SUM($C$22:C22)/$B$22,0) -> 0 | D53: =IF($B$22>0,SUM($C$22:D22)/$B$22,0) -> 0 | E53: =IF($B$22>0,SUM($C$22:E22)/$B$22,0) -> 0 | F53: =IF($B$22>0,SUM($C$22:F22)/$B$22,0) -> 0 | G53: =IF($B$22>0,SUM($C$22:G22)/$B$22,0) -> 0 | H53: =IF($B$22>0,SUM($C$22:H22)/$B$22,0) -> 0 | I53: =IF($B$22>0,SUM($C$22:I22)/$B$22,0) -> 0 | J53: =IF($B$22>0,SUM($C$22:J22)/$B$22,0) -> 0 | ... BJ53: =IF($B$22>0,SUM($C$22:BJ22)/$B$22,0) -> 0
A54: =CONCATENATE("Depreciación del activo"," ",A23) -> Depreciación del activo | C54: =IF($B$23>0,SUM($C$23:C23)/$B$23,0) -> 0 | D54: =IF($B$23>0,SUM($C$23:D23)/$B$23,0) -> 0 | E54: =IF($B$23>0,SUM($C$23:E23)/$B$23,0) -> 0 | F54: =IF($B$23>0,SUM($C$23:F23)/$B$23,0) -> 0 | G54: =IF($B$23>0,SUM($C$23:G23)/$B$23,0) -> 0 | H54: =IF($B$23>0,SUM($C$23:H23)/$B$23,0) -> 0 | I54: =IF($B$23>0,SUM($C$23:I23)/$B$23,0) -> 0 | J54: =IF($B$23>0,SUM($C$23:J23)/$B$23,0) -> 0 | ... BJ54: =IF($B$23>0,SUM($C$23:BJ23)/$B$23,0) -> 0
A55: =CONCATENATE("Depreciación del activo"," ",A24) -> Depreciación del activo | C55: =IF($B$24>0,SUM($C$24:C24)/$B$24,0) -> 0 | D55: =IF($B$24>0,SUM($C$24:D24)/$B$24,0) -> 0 | E55: =IF($B$24>0,SUM($C$24:E24)/$B$24,0) -> 0 | F55: =IF($B$24>0,SUM($C$24:F24)/$B$24,0) -> 0 | G55: =IF($B$24>0,SUM($C$24:G24)/$B$24,0) -> 0 | H55: =IF($B$24>0,SUM($C$24:H24)/$B$24,0) -> 0 | I55: =IF($B$24>0,SUM($C$24:I24)/$B$24,0) -> 0 | J55: =IF($B$24>0,SUM($C$24:J24)/$B$24,0) -> 0 | ... BJ55: =IF($B$24>0,SUM($C$24:BJ24)/$B$24,0) -> 0
A56: =CONCATENATE("Depreciación del activo"," ",A25) -> Depreciación del activo | C56: =IF($B$25>0,SUM($C$25:C25)/$B$25,0) -> 0 | D56: =IF($B$25>0,SUM($C$25:D25)/$B$25,0) -> 0 | E56: =IF($B$25>0,SUM($C$25:E25)/$B$25,0) -> 0 | F56: =IF($B$25>0,SUM($C$25:F25)/$B$25,0) -> 0 | G56: =IF($B$25>0,SUM($C$25:G25)/$B$25,0) -> 0 | H56: =IF($B$25>0,SUM($C$25:H25)/$B$25,0) -> 0 | I56: =IF($B$25>0,SUM($C$25:I25)/$B$25,0) -> 0 | J56: =IF($B$25>0,SUM($C$25:J25)/$B$25,0) -> 0 | ... BJ56: =IF($B$25>0,SUM($C$25:BJ25)/$B$25,0) -> 0
A57: =CONCATENATE("Depreciación del activo"," ",A26) -> Depreciación del activo | C57: =IF($B$26>0,SUM($C$26:C26)/$B$26,0) -> 0 | D57: =IF($B$26>0,SUM($C$26:D26)/$B$26,0) -> 0 | E57: =IF($B$26>0,SUM($C$26:E26)/$B$26,0) -> 0 | F57: =IF($B$26>0,SUM($C$26:F26)/$B$26,0) -> 0 | G57: =IF($B$26>0,SUM($C$26:G26)/$B$26,0) -> 0 | H57: =IF($B$26>0,SUM($C$26:H26)/$B$26,0) -> 0 | I57: =IF($B$26>0,SUM($C$26:I26)/$B$26,0) -> 0 | J57: =IF($B$26>0,SUM($C$26:J26)/$B$26,0) -> 0 | ... BJ57: =IF($B$26>0,SUM($C$26:BJ26)/$B$26,0) -> 0
A58: =CONCATENATE("Depreciación del activo"," ",A27) -> Depreciación del activo | C58: =IF($B$27>0,SUM($C$27:C27)/$B$27,0) -> 0 | D58: =IF($B$27>0,SUM($C$27:D27)/$B$27,0) -> 0 | E58: =IF($B$27>0,SUM($C$27:E27)/$B$27,0) -> 0 | F58: =IF($B$27>0,SUM($C$27:F27)/$B$27,0) -> 0 | G58: =IF($B$27>0,SUM($C$27:G27)/$B$27,0) -> 0 | H58: =IF($B$27>0,SUM($C$27:H27)/$B$27,0) -> 0 | I58: =IF($B$27>0,SUM($C$27:I27)/$B$27,0) -> 0 | J58: =IF($B$27>0,SUM($C$27:J27)/$B$27,0) -> 0 | ... BJ58: =IF($B$27>0,SUM($C$27:BJ27)/$B$27,0) -> 0
A59: =CONCATENATE("Depreciación del activo"," ",A28) -> Depreciación del activo | C59: =IF($B$28>0,SUM($C$28:C28)/$B$28,0) -> 0 | D59: =IF($B$28>0,SUM($C$28:D28)/$B$28,0) -> 0 | E59: =IF($B$28>0,SUM($C$28:E28)/$B$28,0) -> 0 | F59: =IF($B$28>0,SUM($C$28:F28)/$B$28,0) -> 0 | G59: =IF($B$28>0,SUM($C$28:G28)/$B$28,0) -> 0 | H59: =IF($B$28>0,SUM($C$28:H28)/$B$28,0) -> 0 | I59: =IF($B$28>0,SUM($C$28:I28)/$B$28,0) -> 0 | J59: =IF($B$28>0,SUM($C$28:J28)/$B$28,0) -> 0 | ... BJ59: =IF($B$28>0,SUM($C$28:BJ28)/$B$28,0) -> 0
A60: =CONCATENATE("Depreciación del activo"," ",A29) -> Depreciación del activo | C60: =IF($B$29>0,SUM($C$29:C29)/$B$29,0) -> 0 | D60: =IF($B$29>0,SUM($C$29:D29)/$B$29,0) -> 0 | E60: =IF($B$29>0,SUM($C$29:E29)/$B$29,0) -> 0 | F60: =IF($B$29>0,SUM($C$29:F29)/$B$29,0) -> 0 | G60: =IF($B$29>0,SUM($C$29:G29)/$B$29,0) -> 0 | H60: =IF($B$29>0,SUM($C$29:H29)/$B$29,0) -> 0 | I60: =IF($B$29>0,SUM($C$29:I29)/$B$29,0) -> 0 | J60: =IF($B$29>0,SUM($C$29:J29)/$B$29,0) -> 0 | ... BJ60: =IF($B$29>0,SUM($C$29:BJ29)/$B$29,0) -> 0
A61: =CONCATENATE("Depreciación del activo"," ",A30) -> Depreciación del activo | C61: =IF($B$30>0,SUM($C$30:C30)/$B$30,0) -> 0 | D61: =IF($B$30>0,SUM($C$30:D30)/$B$30,0) -> 0 | E61: =IF($B$30>0,SUM($C$30:E30)/$B$30,0) -> 0 | F61: =IF($B$30>0,SUM($C$30:F30)/$B$30,0) -> 0 | G61: =IF($B$30>0,SUM($C$30:G30)/$B$30,0) -> 0 | H61: =IF($B$30>0,SUM($C$30:H30)/$B$30,0) -> 0 | I61: =IF($B$30>0,SUM($C$30:I30)/$B$30,0) -> 0 | J61: =IF($B$30>0,SUM($C$30:J30)/$B$30,0) -> 0 | ... BJ61: =IF($B$30>0,SUM($C$30:BJ30)/$B$30,0) -> 0
A62: =CONCATENATE("Depreciación del activo"," ",A31) -> Depreciación del activo | C62: =IF($B$31>0,SUM($C$31:C31)/$B$31,0) -> 0 | D62: =IF($B$31>0,SUM($C$31:D31)/$B$31,0) -> 0 | E62: =IF($B$31>0,SUM($C$31:E31)/$B$31,0) -> 0 | F62: =IF($B$31>0,SUM($C$31:F31)/$B$31,0) -> 0 | G62: =IF($B$31>0,SUM($C$31:G31)/$B$31,0) -> 0 | H62: =IF($B$31>0,SUM($C$31:H31)/$B$31,0) -> 0 | I62: =IF($B$31>0,SUM($C$31:I31)/$B$31,0) -> 0 | J62: =IF($B$31>0,SUM($C$31:J31)/$B$31,0) -> 0 | ... BJ62: =IF($B$31>0,SUM($C$31:BJ31)/$B$31,0) -> 0
A63: =CONCATENATE("Depreciación del activo"," ",A32) -> Depreciación del activo | C63: =IF($B$32>0,SUM($C$32:C32)/$B$32,0) -> 0 | D63: =IF($B$32>0,SUM($C$32:D32)/$B$32,0) -> 0 | E63: =IF($B$32>0,SUM($C$32:E32)/$B$32,0) -> 0 | F63: =IF($B$32>0,SUM($C$32:F32)/$B$32,0) -> 0 | G63: =IF($B$32>0,SUM($C$32:G32)/$B$32,0) -> 0 | H63: =IF($B$32>0,SUM($C$32:H32)/$B$32,0) -> 0 | I63: =IF($B$32>0,SUM($C$32:I32)/$B$32,0) -> 0 | J63: =IF($B$32>0,SUM($C$32:J32)/$B$32,0) -> 0 | ... BJ63: =IF($B$32>0,SUM($C$32:BJ32)/$B$32,0) -> 0
A64: =CONCATENATE("Depreciación del activo"," ",A33) -> Depreciación del activo | C64: =IF($B$33>0,SUM($C$33:C33)/$B$33,0) -> 0 | D64: =IF($B$33>0,SUM($C$33:D33)/$B$33,0) -> 0 | E64: =IF($B$33>0,SUM($C$33:E33)/$B$33,0) -> 0 | F64: =IF($B$33>0,SUM($C$33:F33)/$B$33,0) -> 0 | G64: =IF($B$33>0,SUM($C$33:G33)/$B$33,0) -> 0 | H64: =IF($B$33>0,SUM($C$33:H33)/$B$33,0) -> 0 | I64: =IF($B$33>0,SUM($C$33:I33)/$B$33,0) -> 0 | J64: =IF($B$33>0,SUM($C$33:J33)/$B$33,0) -> 0 | ... BJ64: =IF($B$33>0,SUM($C$33:BJ33)/$B$33,0) -> 0
A65: =CONCATENATE("Depreciación del activo"," ",A34) -> Depreciación del activo | C65: =IF($B$34>0,SUM($C$34:C34)/$B$34,0) -> 0 | D65: =IF($B$34>0,SUM($C$34:D34)/$B$34,0) -> 0 | E65: =IF($B$34>0,SUM($C$34:E34)/$B$34,0) -> 0 | F65: =IF($B$34>0,SUM($C$34:F34)/$B$34,0) -> 0 | G65: =IF($B$34>0,SUM($C$34:G34)/$B$34,0) -> 0 | H65: =IF($B$34>0,SUM($C$34:H34)/$B$34,0) -> 0 | I65: =IF($B$34>0,SUM($C$34:I34)/$B$34,0) -> 0 | J65: =IF($B$34>0,SUM($C$34:J34)/$B$34,0) -> 0 | ... BJ65: =IF($B$34>0,SUM($C$34:BJ34)/$B$34,0) -> 0
A66: =CONCATENATE("Depreciación del activo"," ",A35) -> Depreciación del activo | C66: =IF($B$35>0,SUM($C$35:C35)/$B$35,0) -> 0 | D66: =IF($B$35>0,SUM($C$35:D35)/$B$35,0) -> 0 | E66: =IF($B$35>0,SUM($C$35:E35)/$B$35,0) -> 0 | F66: =IF($B$35>0,SUM($C$35:F35)/$B$35,0) -> 0 | G66: =IF($B$35>0,SUM($C$35:G35)/$B$35,0) -> 0 | H66: =IF($B$35>0,SUM($C$35:H35)/$B$35,0) -> 0 | I66: =IF($B$35>0,SUM($C$35:I35)/$B$35,0) -> 0 | J66: =IF($B$35>0,SUM($C$35:J35)/$B$35,0) -> 0 | ... BJ66: =IF($B$35>0,SUM($C$35:BJ35)/$B$35,0) -> 0
A67: TOTAL DEPRECIACIONES DE LA PROPIEDAD, PLANTA Y EQUIPO | C67: =SUM(C41:C66) -> 0 | D67: =SUM(D41:D66) -> 0 | E67: =SUM(E41:E66) -> 0 | F67: =SUM(F41:F66) -> 0 | G67: =SUM(G41:G66) -> 0 | H67: =SUM(H41:H66) -> 0 | I67: =SUM(I41:I66) -> 0 | J67: =SUM(J41:J66) -> 0 | ... BJ67: =SUM(BJ41:BJ66) -> 0
A68: Según la Lay 1819 de 2016, estas son las tasas de depreciación a aplicar en Colombia:
A99: Plantilla Realizada por María Teresa Macías Joven
A100: Universidad de La Sabana
A101: Versión 2021
A102: ®Todos los derechos reservados
A103: Si desea utilizar esta plantilla por fuera del programa Expo-Empresarial, clase de proyecto empresarial de la Universidad de La Sabana, asegúrese de poseer los derechos de uso por parte de la autora de la plantilla, con una autorización clara, expresa y por escrito.

Sheet FINANCIACIÓN
B1: =CONCATENATE(INICIO!$B$10," ",INICIO!$B$11) -> TIZA S.A.S
B5: PRESUPUESTO DE FINANCIACIÓN
A6: Aportar modelos de socios y formas para levantar el capital.
A7: FINANCIACIÓN MEDIANTE CAPITAL DE RIESGO | D7: =Año1 -> 2027 | P7: =Año2 -> 2028 | AB7: =Año3 -> 2029 | AN7: =Año4 -> 2030 | AZ7: =Año5 -> 2031
C8: Mes 0 | D8: Mes 1 | E8: Mes 2 | F8: Mes 3 | G8: Mes 4 | H8: Mes 5 | I8: Mes 6 | J8: Mes 7 | K8: Mes 8 | L8: Mes 9 | M8: Mes 10 | N8: Mes 11 | O8: Mes 12 | P8: Mes 13 | Q8: Mes 14 | R8: Mes 15 | S8: Mes 16 | T8: Mes 17 | U8: Mes 18 | V8: Mes 19 | W8: Mes 20 | X8: Mes 21 | Y8: Mes 22 | Z8: Mes 23 | AA8: Mes 24 | AB8: Mes 25 | AC8: Mes 26 | AD8: Mes 27 | AE8: Mes 28 | AF8: Mes 29 | AG8: Mes 30 | AH8: Mes 31 | AI8: Mes 32 | AJ8: Mes 33 | AK8: Mes 34 | AL8: Mes 35 | AM8: Mes 36 | AN8: Mes 37 | AO8: Mes 38 | AP8: Mes 39 | AQ8: Mes 40 | AR8: Mes 41 | AS8: Mes 42 | AT8: Mes 43 | AU8: Mes 44 | AV8: Mes 45 | AW8: Mes 46 | AX8: Mes 47 | AY8: Mes 48 | AZ8: Mes 49 | BA8: Mes 50 | BB8: Mes 51 | BC8: Mes 52 | BD8: Mes 53 | BE8: Mes 54 | BF8: Mes 55 | BG8: Mes 56 | BH8: Mes 57 | BI8: Mes 58 | BJ8: Mes 59 | BK8: Mes 60
A9: =CONCATENATE("Aportes de Capital del socio"," ",INICIO!A19) -> Aportes de Capital del socio Danna Sanchez | C9: 2000000 | BL9: =SUM(C9:BK9) -> 2000000
A10: =CONCATENATE("Aportes de Capital del socio"," ",INICIO!A20) -> Aportes de Capital del socio Sergio Nieto | C10: 2000000 | BL10: =SUM(C10:BK10) -> 2000000
A11: =CONCATENATE("Aportes de Capital del socio"," ",INICIO!A21) -> Aportes de Capital del socio Daniel Martin | C11: 2000000 | BL11: =SUM(C11:BK11) -> 2000000
A12: =CONCATENATE("Aportes de Capital del socio"," ",INICIO!A22) -> Aportes de Capital del socio Christian Morales | C12: 2000000 | BL12: =SUM(C12:BK12) -> 2000000
A13: =CONCATENATE("Aportes de Capital del socio"," ",INICIO!A23) -> Aportes de Capital del socio INVERSOR 5 | BL13: =SUM(C13:BK13) -> 0
A14: =CONCATENATE("Aportes de Capital del socio"," ",INICIO!A24) -> Aportes de Capital del socio INVERSOR 6 | BL14: =SUM(C14:BK14) -> 0
BL15: =SUM(C15:BK15) -> 0
BL16: =SUM(C16:BK16) -> 0
BL17: =SUM(C17:BK17) -> 0
BL18: =SUM(C18:BK18) -> 0
BL19: =SUM(C19:BK19) -> 0
BL20: =SUM(C20:BK20) -> 0
BL21: =SUM(C21:BK21) -> 0
BL22: =SUM(C22:BK22) -> 0
BL23: =SUM(C23:BK23) -> 0
A24: TOTAL APORTES DE CAPITAL SOCIAL | C24: =SUM(C9:C23) -> 8000000 | D24: =SUM(D9:D23) -> 0 | E24: =SUM(E9:E23) -> 0 | F24: =SUM(F9:F23) -> 0 | G24: =SUM(G9:G23) -> 0 | H24: =SUM(H9:H23) -> 0 | I24: =SUM(I9:I23) -> 0 | J24: =SUM(J9:J23) -> 0 | ... BL24: =SUM(BL9:BL23) -> 8000000
A26: AUTOFINANCIACIÓN: RETENCIÓN DE UTILIDADES | D26: =Año1 -> 2027 | P26: =Año2 -> 2028 | AB26: =Año3 -> 2029 | AN26: =Año4 -> 2030 | AZ26: =Año5 -> 2031
C27: Mes 0 | D27: Mes 1 | E27: Mes 2 | F27: Mes 3 | G27: Mes 4 | H27: Mes 5 | I27: Mes 6 | J27: Mes 7 | K27: Mes 8 | L27: Mes 9 | M27: Mes 10 | N27: Mes 11 | O27: Mes 12 | P27: Mes 13 | Q27: Mes 14 | R27: Mes 15 | S27: Mes 16 | T27: Mes 17 | U27: Mes 18 | V27: Mes 19 | W27: Mes 20 | X27: Mes 21 | Y27: Mes 22 | Z27: Mes 23 | AA27: Mes 24 | AB27: Mes 25 | AC27: Mes 26 | AD27: Mes 27 | AE27: Mes 28 | AF27: Mes 29 | AG27: Mes 30 | AH27: Mes 31 | AI27: Mes 32 | AJ27: Mes 33 | AK27: Mes 34 | AL27: Mes 35 | AM27: Mes 36 | AN27: Mes 37 | AO27: Mes 38 | AP27: Mes 39 | AQ27: Mes 40 | AR27: Mes 41 | AS27: Mes 42 | AT27: Mes 43 | AU27: Mes 44 | AV27: Mes 45 | AW27: Mes 46 | AX27: Mes 47 | AY27: Mes 48 | AZ27: Mes 49 | BA27: Mes 50 | BB27: Mes 51 | BC27: Mes 52 | BD27: Mes 53 | BE27: Mes 54 | BF27: Mes 55 | BG27: Mes 56 | BH27: Mes 57 | BI27: Mes 58 | BJ27: Mes 59 | BK27: Mes 60
A28: Tasa de Retención | C28: =#REF! -> #REF! | D28: =#REF! -> #REF! | E28: =#REF! -> #REF! | F28: =#REF! -> #REF! | G28: =#REF! -> #REF! | H28: =#REF! -> #REF! | I28: =#REF! -> #REF! | J28: =#REF! -> #REF! | ... BK28: =#REF! -> #REF!
A30: FINANCIACIÓN MEDIANTE ENTIDADES FINANCIERAS | B30: Tasa de Interés Mensual | D30: =Año1 -> 2027 | P30: =Año2 -> 2028 | AB30: =Año3 -> 2029 | AN30: =Año4 -> 2030 | AZ30: =Año5 -> 2031
C31: Mes 0 | D31: Mes 1 | E31: Mes 2 | F31: Mes 3 | G31: Mes 4 | H31: Mes 5 | I31: Mes 6 | J31: Mes 7 | K31: Mes 8 | L31: Mes 9 | M31: Mes 10 | N31: Mes 11 | O31: Mes 12 | P31: Mes 13 | Q31: Mes 14 | R31: Mes 15 | S31: Mes 16 | T31: Mes 17 | U31: Mes 18 | V31: Mes 19 | W31: Mes 20 | X31: Mes 21 | Y31: Mes 22 | Z31: Mes 23 | AA31: Mes 24 | AB31: Mes 25 | AC31: Mes 26 | AD31: Mes 27 | AE31: Mes 28 | AF31: Mes 29 | AG31: Mes 30 | AH31: Mes 31 | AI31: Mes 32 | AJ31: Mes 33 | AK31: Mes 34 | AL31: Mes 35 | AM31: Mes 36 | AN31: Mes 37 | AO31: Mes 38 | AP31: Mes 39 | AQ31: Mes 40 | AR31: Mes 41 | AS31: Mes 42 | AT31: Mes 43 | AU31: Mes 44 | AV31: Mes 45 | AW31: Mes 46 | AX31: Mes 47 | AY31: Mes 48 | AZ31: Mes 49 | BA31: Mes 50 | BB31: Mes 51 | BC31: Mes 52 | BD31: Mes 53 | BE31: Mes 54 | BF31: Mes 55 | BG31: Mes 56 | BH31: Mes 57 | BI31: Mes 58 | BJ31: Mes 59 | BK31: Mes 60 | BM31: W | BN31: i | BO31: W x i
BL32: =SUM(C32:BK32) -> 0 | BM32: =BL32/$BL$47 -> #DIV/0! | BN32: =(1+B32)^(12/1)-1 -> 0 | BO32: =IF(BL32<=0,0,BM32*BN32) -> 0
BL33: =SUM(C33:BK33) -> 0 | BM33: =BL33/$BL$47 -> #DIV/0! | BN33: =(1+B33)^(12/1)-1 -> 0 | BO33: =IF(BL33<=0,0,BM33*BN33) -> 0
BL34: =SUM(C34:BK34) -> 0 | BM34: =BL34/$BL$47 -> #DIV/0! | BN34: =(1+B34)^(12/1)-1 -> 0 | BO34: =IF(BL34<=0,0,BM34*BN34) -> 0
BL35: =SUM(C35:BK35) -> 0 | BM35: =BL35/$BL$47 -> #DIV/0! | BN35: =(1+B35)^(12/1)-1 -> 0 | BO35: =IF(BL35<=0,0,BM35*BN35) -> 0
BL36: =SUM(C36:BK36) -> 0 | BM36: =BL36/$BL$47 -> #DIV/0! | BN36: =(1+B36)^(12/1)-1 -> 0 | BO36: =IF(BL36<=0,0,BM36*BN36) -> 0
BL37: =SUM(C37:BK37) -> 0 | BM37: =BL37/$BL$47 -> #DIV/0! | BN37: =(1+B37)^(12/1)-1 -> 0 | BO37: =IF(BL37<=0,0,BM37*BN37) -> 0
BL38: =SUM(C38:BK38) -> 0 | BM38: =BL38/$BL$47 -> #DIV/0! | BN38: =(1+B38)^(12/1)-1 -> 0 | BO38: =IF(BL38<=0,0,BM38*BN38) -> 0
BL39: =SUM(C39:BK39) -> 0 | BM39: =BL39/$BL$47 -> #DIV/0! | BN39: =(1+B39)^(12/1)-1 -> 0 | BO39: =IF(BL39<=0,0,BM39*BN39) -> 0
BL40: =SUM(C40:BK40) -> 0 | BM40: =BL40/$BL$47 -> #DIV/0! | BN40: =(1+B40)^(12/1)-1 -> 0 | BO40: =IF(BL40<=0,0,BM40*BN40) -> 0
BL41: =SUM(C41:BK41) -> 0 | BM41: =BL41/$BL$47 -> #DIV/0! | BN41: =(1+B41)^(12/1)-1 -> 0 | BO41: =IF(BL41<=0,0,BM41*BN41) -> 0
BL42: =SUM(C42:BK42) -> 0 | BM42: =BL42/$BL$47 -> #DIV/0! | BN42: =(1+B42)^(12/1)-1 -> 0 | BO42: =IF(BL42<=0,0,BM42*BN42) -> 0
BL43: =SUM(C43:BK43) -> 0 | BM43: =BL43/$BL$47 -> #DIV/0! | BN43: =(1+B43)^(12/1)-1 -> 0 | BO43: =IF(BL43<=0,0,BM43*BN43) -> 0
... BL46: =SUM(C46:BK46) -> 0 | BM46: =BL46/$BL$47 -> #DIV/0! | BN46: =(1+B46)^(12/1)-1 -> 0 | BO46: =IF(BL46<=0,0,BM46*BN46) -> 0
A47: TOTAL DESEMBOLSOS POR FINANCIACIÓN | C47: =SUM(C32:C46) -> 0 | D47: =SUM(D32:D46) -> 0 | E47: =SUM(E32:E46) -> 0 | F47: =SUM(F32:F46) -> 0 | G47: =SUM(G32:G46) -> 0 | H47: =SUM(H32:H46) -> 0 | I47: =SUM(I32:I46) -> 0 | J47: =SUM(J32:J46) -> 0 | ... BL47: =SUM(BL32:BL46) -> 0 | BN47: RD | BO47: =SUM(BO32:BO46) -> 0
A49: ABONOS A CAPITAL | D49: =Año1 -> 2027 | P49: =Año2 -> 2028 | AB49: =Año3 -> 2029 | AN49: =Año4 -> 2030 | AZ49: =Año5 -> 2031 | BL49: =AZ49+1 -> 2032
C50: Mes 0 | D50: Mes 1 | E50: Mes 2 | F50: Mes 3 | G50: Mes 4 | H50: Mes 5 | I50: Mes 6 | J50: Mes 7 | K50: Mes 8 | L50: Mes 9 | M50: Mes 10 | N50: Mes 11 | O50: Mes 12 | P50: Mes 13 | Q50: Mes 14 | R50: Mes 15 | S50: Mes 16 | T50: Mes 17 | U50: Mes 18 | V50: Mes 19 | W50: Mes 20 | X50: Mes 21 | Y50: Mes 22 | Z50: Mes 23 | AA50: Mes 24 | AB50: Mes 25 | AC50: Mes 26 | AD50: Mes 27 | AE50: Mes 28 | AF50: Mes 29 | AG50: Mes 30 | AH50: Mes 31 | AI50: Mes 32 | AJ50: Mes 33 | AK50: Mes 34 | AL50: Mes 35 | AM50: Mes 36 | AN50: Mes 37 | AO50: Mes 38 | AP50: Mes 39 | AQ50: Mes 40 | AR50: Mes 41 | AS50: Mes 42 | AT50: Mes 43 | AU50: Mes 44 | AV50: Mes 45 | AW50: Mes 46 | AX50: Mes 47 | AY50: Mes 48 | AZ50: Mes 49 | BA50: Mes 50 | BB50: Mes 51 | BC50: Mes 52 | BD50: Mes 53 | BE50: Mes 54 | BF50: Mes 55 | BG50: Mes 56 | BH50: Mes 57 | BI50: Mes 58 | BJ50: Mes 59 | BK50: Mes 60 | BL50: Mes 61 | BM50: Mes 62 | BN50: Mes 63 | BO50: Mes 64 | BP50: Mes 65 | BQ50: Mes 66 | BR50: Mes 67 | BS50: Mes 68 | BT50: Mes 69 | BU50: Mes 70 | BV50: Mes 71 | BW50: Mes 72
A51: =CONCATENATE("Abonos a capital del crédito"," ",A32) -> Abonos a capital del crédito | D51: =IF(C89>0,SUM($C$32:C32)/60,0) -> 0 | E51: =IF(D89>0,SUM($C$32:D32)/60,0) -> 0 | F51: =IF(E89>0,SUM($C$32:E32)/60,0) -> 0 | G51: =IF(F89>0,SUM($C$32:F32)/60,0) -> 0 | H51: =IF(G89>0,SUM($C$32:G32)/60,0) -> 0 | I51: =IF(H89>0,SUM($C$32:H32)/60,0) -> 0 | J51: =IF(I89>0,SUM($C$32:I32)/60,0) -> 0 | K51: =IF(J89>0,SUM($C$32:J32)/60,0) -> 0 | ... BW51: =IF(BV89>0,SUM($C$32:BV32)/60,0) -> #DIV/0!
A52: =CONCATENATE("Abonos a capital del crédito"," ",A33) -> Abonos a capital del crédito | D52: =IF(C90>0,SUM($C$33:C33)/60,0) -> 0 | E52: =IF(D90>0,SUM($C$33:D33)/60,0) -> 0 | F52: =IF(E90>0,SUM($C$33:E33)/60,0) -> 0 | G52: =IF(F90>0,SUM($C$33:F33)/60,0) -> 0 | H52: =IF(G90>0,SUM($C$33:G33)/60,0) -> 0 | I52: =IF(H90>0,SUM($C$33:H33)/60,0) -> 0 | J52: =IF(I90>0,SUM($C$33:I33)/60,0) -> 0 | K52: =IF(J90>0,SUM($C$33:J33)/60,0) -> 0 | ... BW52: =IF(BV90>0,SUM($C$33:BV33)/60,0) -> #DIV/0!
A53: =CONCATENATE("Abonos a capital del crédito"," ",A34) -> Abonos a capital del crédito | D53: =IF(C91>0,SUM($C$34:C34)/60,0) -> 0 | E53: =IF(D91>0,SUM($C$34:D34)/60,0) -> 0 | F53: =IF(E91>0,SUM($C$34:E34)/60,0) -> 0 | G53: =IF(F91>0,SUM($C$34:F34)/60,0) -> 0 | H53: =IF(G91>0,SUM($C$34:G34)/60,0) -> 0 | I53: =IF(H91>0,SUM($C$34:H34)/60,0) -> 0 | J53: =IF(I91>0,SUM($C$34:I34)/60,0) -> 0 | K53: =IF(J91>0,SUM($C$34:J34)/60,0) -> 0 | ... BW53: =IF(BV91>0,SUM($C$34:BV34)/60,0) -> #DIV/0!
A54: =CONCATENATE("Abonos a capital del crédito"," ",A35) -> Abonos a capital del crédito | D54: =IF(C92>0,SUM($C$35:C35)/60,0) -> 0 | E54: =IF(D92>0,SUM($C$35:D35)/60,0) -> 0 | F54: =IF(E92>0,SUM($C$35:E35)/60,0) -> 0 | G54: =IF(F92>0,SUM($C$35:F35)/60,0) -> 0 | H54: =IF(G92>0,SUM($C$35:G35)/60,0) -> 0 | I54: =IF(H92>0,SUM($C$35:H35)/60,0) -> 0 | J54: =IF(I92>0,SUM($C$35:I35)/60,0) -> 0 | K54: =IF(J92>0,SUM($C$35:J35)/60,0) -> 0 | ... BW54: =IF(BV92>0,SUM($C$35:BV35)/60,0) -> #DIV/0!
A55: =CONCATENATE("Abonos a capital del crédito"," ",A36) -> Abonos a capital del crédito | D55: =IF(C93>0,SUM($C$36:C36)/60,0) -> 0 | E55: =IF(D93>0,SUM($C$36:D36)/60,0) -> 0 | F55: =IF(E93>0,SUM($C$36:E36)/60,0) -> 0 | G55: =IF(F93>0,SUM($C$36:F36)/60,0) -> 0 | H55: =IF(G93>0,SUM($C$36:G36)/60,0) -> 0 | I55: =IF(H93>0,SUM($C$36:H36)/60,0) -> 0 | J55: =IF(I93>0,SUM($C$36:I36)/60,0) -> 0 | K55: =IF(J93>0,SUM($C$36:J36)/60,0) -> 0 | ... BW55: =IF(BV93>0,SUM($C$36:BV36)/60,0) -> #DIV/0!
A56: =CONCATENATE("Abonos a capital del crédito"," ",A37) -> Abonos a capital del crédito | D56: =IF(C94>0,SUM($C$37:C37)/60,0) -> 0 | E56: =IF(D94>0,SUM($C$37:D37)/60,0) -> 0 | F56: =IF(E94>0,SUM($C$37:E37)/60,0) -> 0 | G56: =IF(F94>0,SUM($C$37:F37)/60,0) -> 0 | H56: =IF(G94>0,SUM($C$37:G37)/60,0) -> 0 | I56: =IF(H94>0,SUM($C$37:H37)/60,0) -> 0 | J56: =IF(I94>0,SUM($C$37:I37)/60,0) -> 0 | K56: =IF(J94>0,SUM($C$37:J37)/60,0) -> 0 | ... BW56: =IF(BV94>0,SUM($C$37:BV37)/60,0) -> #DIV/0!
A57: =CONCATENATE("Abonos a capital del crédito"," ",A38) -> Abonos a capital del crédito | D57: =IF(C95>0,SUM($C$38:C38)/60,0) -> 0 | E57: =IF(D95>0,SUM($C$38:D38)/60,0) -> 0 | F57: =IF(E95>0,SUM($C$38:E38)/60,0) -> 0 | G57: =IF(F95>0,SUM($C$38:F38)/60,0) -> 0 | H57: =IF(G95>0,SUM($C$38:G38)/60,0) -> 0 | I57: =IF(H95>0,SUM($C$38:H38)/60,0) -> 0 | J57: =IF(I95>0,SUM($C$38:I38)/60,0) -> 0 | K57: =IF(J95>0,SUM($C$38:J38)/60,0) -> 0 | ... BW57: =IF(BV95>0,SUM($C$38:BV38)/60,0) -> #DIV/0!
A58: =CONCATENATE("Abonos a capital del crédito"," ",A39) -> Abonos a capital del crédito | D58: =IF(C96>0,SUM($C$39:C39)/60,0) -> 0 | E58: =IF(D96>0,SUM($C$39:D39)/60,0) -> 0 | F58: =IF(E96>0,SUM($C$39:E39)/60,0) -> 0 | G58: =IF(F96>0,SUM($C$39:F39)/60,0) -> 0 | H58: =IF(G96>0,SUM($C$39:G39)/60,0) -> 0 | I58: =IF(H96>0,SUM($C$39:H39)/60,0) -> 0 | J58: =IF(I96>0,SUM($C$39:I39)/60,0) -> 0 | K58: =IF(J96>0,SUM($C$39:J39)/60,0) -> 0 | ... BW58: =IF(BV96>0,SUM($C$39:BV39)/60,0) -> #DIV/0!
A59: =CONCATENATE("Abonos a capital del crédito"," ",A40) -> Abonos a capital del crédito | D59: =IF(C97>0,SUM($C$40:C40)/60,0) -> 0 | E59: =IF(D97>0,SUM($C$40:D40)/60,0) -> 0 | F59: =IF(E97>0,SUM($C$40:E40)/60,0) -> 0 | G59: =IF(F97>0,SUM($C$40:F40)/60,0) -> 0 | H59: =IF(G97>0,SUM($C$40:G40)/60,0) -> 0 | I59: =IF(H97>0,SUM($C$40:H40)/60,0) -> 0 | J59: =IF(I97>0,SUM($C$40:I40)/60,0) -> 0 | K59: =IF(J97>0,SUM($C$40:J40)/60,0) -> 0 | ... BW59: =IF(BV97>0,SUM($C$40:BV40)/60,0) -> #DIV/0!
A60: =CONCATENATE("Abonos a capital del crédito"," ",A41) -> Abonos a capital del crédito | D60: =IF(C98>0,SUM($C$41:C41)/60,0) -> 0 | E60: =IF(D98>0,SUM($C$41:D41)/60,0) -> 0 | F60: =IF(E98>0,SUM($C$41:E41)/60,0) -> 0 | G60: =IF(F98>0,SUM($C$41:F41)/60,0) -> 0 | H60: =IF(G98>0,SUM($C$41:G41)/60,0) -> 0 | I60: =IF(H98>0,SUM($C$41:H41)/60,0) -> 0 | J60: =IF(I98>0,SUM($C$41:I41)/60,0) -> 0 | K60: =IF(J98>0,SUM($C$41:J41)/60,0) -> 0 | ... BW60: =IF(BV98>0,SUM($C$41:BV41)/60,0) -> #DIV/0!
A61: =CONCATENATE("Abonos a capital del crédito"," ",A42) -> Abonos a capital del crédito | D61: =IF(C99>0,SUM($C$42:C42)/60,0) -> 0 | E61: =IF(D99>0,SUM($C$42:D42)/60,0) -> 0 | F61: =IF(E99>0,SUM($C$42:E42)/60,0) -> 0 | G61: =IF(F99>0,SUM($C$42:F42)/60,0) -> 0 | H61: =IF(G99>0,SUM($C$42:G42)/60,0) -> 0 | I61: =IF(H99>0,SUM($C$42:H42)/60,0) -> 0 | J61: =IF(I99>0,SUM($C$42:I42)/60,0) -> 0 | K61: =IF(J99>0,SUM($C$42:J42)/60,0) -> 0 | ... BW61: =IF(BV99>0,SUM($C$42:BV42)/60,0) -> #DIV/0!
A62: =CONCATENATE("Abonos a capital del crédito"," ",A43) -> Abonos a capital del crédito | D62: =IF(C100>0,SUM($C$43:C43)/60,0) -> 0 | E62: =IF(D100>0,SUM($C$43:D43)/60,0) -> 0 | F62: =IF(E100>0,SUM($C$43:E43)/60,0) -> 0 | G62: =IF(F100>0,SUM($C$43:F43)/60,0) -> 0 | H62: =IF(G100>0,SUM($C$43:G43)/60,0) -> 0 | I62: =IF(H100>0,SUM($C$43:H43)/60,0) -> 0 | J62: =IF(I100>0,SUM($C$43:I43)/60,0) -> 0 | K62: =IF(J100>0,SUM($C$43:J43)/60,0) -> 0 | ... BW62: =IF(BV100>0,SUM($C$43:BV43)/60,0) -> #DIV/0!
A63: =CONCATENATE("Abonos a capital del crédito"," ",A44) -> Abonos a capital del crédito | D63: =IF(C101>0,SUM($C$44:C44)/60,0) -> 0 | E63: =IF(D101>0,SUM($C$44:D44)/60,0) -> 0 | F63: =IF(E101>0,SUM($C$44:E44)/60,0) -> 0 | G63: =IF(F101>0,SUM($C$44:F44)/60,0) -> 0 | H63: =IF(G101>0,SUM($C$44:G44)/60,0) -> 0 | I63: =IF(H101>0,SUM($C$44:H44)/60,0) -> 0 | J63: =IF(I101>0,SUM($C$44:I44)/60,0) -> 0 | K63: =IF(J101>0,SUM($C$44:J44)/60,0) -> 0 | ... BW63: =IF(BV101>0,SUM($C$44:BV44)/60,0) -> #DIV/0!
A64: =CONCATENATE("Abonos a capital del crédito"," ",A45) -> Abonos a capital del crédito | D64: =IF(C102>0,SUM($C$45:C45)/60,0) -> 0 | E64: =IF(D102>0,SUM($C$45:D45)/60,0) -> 0 | F64: =IF(E102>0,SUM($C$45:E45)/60,0) -> 0 | G64: =IF(F102>0,SUM($C$45:F45)/60,0) -> 0 | H64: =IF(G102>0,SUM($C$45:G45)/60,0) -> 0 | I64: =IF(H102>0,SUM($C$45:H45)/60,0) -> 0 | J64: =IF(I102>0,SUM($C$45:I45)/60,0) -> 0 | K64: =IF(J102>0,SUM($C$45:J45)/60,0) -> 0 | ... BW64: =IF(BV102>0,SUM($C$45:BV45)/60,0) -> #DIV/0!
A65: =CONCATENATE("Abonos a capital del crédito"," ",A46) -> Abonos a capital del crédito | D65: =IF(C103>0,SUM($C$46:C46)/60,0) -> 0 | E65: =IF(D103>0,SUM($C$46:D46)/60,0) -> 0 | F65: =IF(E103>0,SUM($C$46:E46)/60,0) -> 0 | G65: =IF(F103>0,SUM($C$46:F46)/60,0) -> 0 | H65: =IF(G103>0,SUM($C$46:G46)/60,0) -> 0 | I65: =IF(H103>0,SUM($C$46:H46)/60,0) -> 0 | J65: =IF(I103>0,SUM($C$46:I46)/60,0) -> 0 | K65: =IF(J103>0,SUM($C$46:J46)/60,0) -> 0 | ... BW65: =IF(BV103>0,SUM($C$46:BV46)/60,0) -> #DIV/0!
A66: TOTAL ABONOS A CAPITAL | C66: =SUM(C51:C65) -> 0 | D66: =SUM(D51:D65) -> 0 | E66: =SUM(E51:E65) -> 0 | F66: =SUM(F51:F65) -> 0 | G66: =SUM(G51:G65) -> 0 | H66: =SUM(H51:H65) -> 0 | I66: =SUM(I51:I65) -> 0 | J66: =SUM(J51:J65) -> 0 | ... BW66: =SUM(BW51:BW65) -> #DIV/0!
A68: PAGO DE INTERESES Y OTROS GASTOS FINANCIEROS | D68: =Año1 -> 2027 | P68: =Año2 -> 2028 | AB68: =Año3 -> 2029 | AN68: =Año4 -> 2030 | AZ68: =Año5 -> 2031
C69: Mes 0 | D69: Mes 1 | E69: Mes 2 | F69: Mes 3 | G69: Mes 4 | H69: Mes 5 | I69: Mes 6 | J69: Mes 7 | K69: Mes 8 | L69: Mes 9 | M69: Mes 10 | N69: Mes 11 | O69: Mes 12 | P69: Mes 13 | Q69: Mes 14 | R69: Mes 15 | S69: Mes 16 | T69: Mes 17 | U69: Mes 18 | V69: Mes 19 | W69: Mes 20 | X69: Mes 21 | Y69: Mes 22 | Z69: Mes 23 | AA69: Mes 24 | AB69: Mes 25 | AC69: Mes 26 | AD69: Mes 27 | AE69: Mes 28 | AF69: Mes 29 | AG69: Mes 30 | AH69: Mes 31 | AI69: Mes 32 | AJ69: Mes 33 | AK69: Mes 34 | AL69: Mes 35 | AM69: Mes 36 | AN69: Mes 37 | AO69: Mes 38 | AP69: Mes 39 | AQ69: Mes 40 | AR69: Mes 41 | AS69: Mes 42 | AT69: Mes 43 | AU69: Mes 44 | AV69: Mes 45 | AW69: Mes 46 | AX69: Mes 47 | AY69: Mes 48 | AZ69: Mes 49 | BA69: Mes 50 | BB69: Mes 51 | BC69: Mes 52 | BD69: Mes 53 | BE69: Mes 54 | BF69: Mes 55 | BG69: Mes 56 | BH69: Mes 57 | BI69: Mes 58 | BJ69: Mes 59 | BK69: Mes 60
A70: =CONCATENATE("Pago de intereses por el crédito"," ",A32) -> Pago de intereses por el crédito | D70: =C89*$B$32 -> 0 | E70: =D89*$B$32 -> 0 | F70: =E89*$B$32 -> 0 | G70: =F89*$B$32 -> 0 | H70: =G89*$B$32 -> 0 | I70: =H89*$B$32 -> 0 | J70: =I89*$B$32 -> 0 | K70: =J89*$B$32 -> 0 | ... BK70: =BJ89*$B$32 -> 0
A71: =CONCATENATE("Pago de intereses por el crédito"," ",A33) -> Pago de intereses por el crédito | D71: =C90*$B$33 -> 0 | E71: =D90*$B$33 -> 0 | F71: =E90*$B$33 -> 0 | G71: =F90*$B$33 -> 0 | H71: =G90*$B$33 -> 0 | I71: =H90*$B$33 -> 0 | J71: =I90*$B$33 -> 0 | K71: =J90*$B$33 -> 0 | ... BK71: =BJ90*$B$33 -> 0
A72: =CONCATENATE("Pago de intereses por el crédito"," ",A34) -> Pago de intereses por el crédito | D72: =C91*$B$34 -> 0 | E72: =D91*$B$34 -> 0 | F72: =E91*$B$34 -> 0 | G72: =F91*$B$34 -> 0 | H72: =G91*$B$34 -> 0 | I72: =H91*$B$34 -> 0 | J72: =I91*$B$34 -> 0 | K72: =J91*$B$34 -> 0 | ... BK72: =BJ91*$B$34 -> 0
A73: =CONCATENATE("Pago de intereses por el crédito"," ",A35) -> Pago de intereses por el crédito | D73: =C92*$B$35 -> 0 | E73: =D92*$B$35 -> 0 | F73: =E92*$B$35 -> 0 | G73: =F92*$B$35 -> 0 | H73: =G92*$B$35 -> 0 | I73: =H92*$B$35 -> 0 | J73: =I92*$B$35 -> 0 | K73: =J92*$B$35 -> 0 | ... BK73: =BJ92*$B$35 -> 0
A74: =CONCATENATE("Pago de intereses por el crédito"," ",A36) -> Pago de intereses por el crédito | D74: =C93*$B$36 -> 0 | E74: =D93*$B$36 -> 0 | F74: =E93*$B$36 -> 0 | G74: =F93*$B$36 -> 0 | H74: =G93*$B$36 -> 0 | I74: =H93*$B$36 -> 0 | J74: =I93*$B$36 -> 0 | K74: =J93*$B$36 -> 0 | ... BK74: =BJ93*$B$36 -> 0
A75: =CONCATENATE("Pago de intereses por el crédito"," ",A37) -> Pago de intereses por el crédito | D75: =C94*$B$37 -> 0 | E75: =D94*$B$37 -> 0 | F75: =E94*$B$37 -> 0 | G75: =F94*$B$37 -> 0 | H75: =G94*$B$37 -> 0 | I75: =H94*$B$37 -> 0 | J75: =I94*$B$37 -> 0 | K75: =J94*$B$37 -> 0 | ... BK75: =BJ94*$B$37 -> 0
A76: =CONCATENATE("Pago de intereses por el crédito"," ",A38) -> Pago de intereses por el crédito | D76: =C95*$B$38 -> 0 | E76: =D95*$B$38 -> 0 | F76: =E95*$B$38 -> 0 | G76: =F95*$B$38 -> 0 | H76: =G95*$B$38 -> 0 | I76: =H95*$B$38 -> 0 | J76: =I95*$B$38 -> 0 | K76: =J95*$B$38 -> 0 | ... BK76: =BJ95*$B$38 -> 0
A77: =CONCATENATE("Pago de intereses por el crédito"," ",A39) -> Pago de intereses por el crédito | D77: =C96*$B$39 -> 0 | E77: =D96*$B$39 -> 0 | F77: =E96*$B$39 -> 0 | G77: =F96*$B$39 -> 0 | H77: =G96*$B$39 -> 0 | I77: =H96*$B$39 -> 0 | J77: =I96*$B$39 -> 0 | K77: =J96*$B$39 -> 0 | ... BK77: =BJ96*$B$39 -> 0
A78: =CONCATENATE("Pago de intereses por el crédito"," ",A40) -> Pago de intereses por el crédito | D78: =C97*$B$40 -> 0 | E78: =D97*$B$40 -> 0 | F78: =E97*$B$40 -> 0 | G78: =F97*$B$40 -> 0 | H78: =G97*$B$40 -> 0 | I78: =H97*$B$40 -> 0 | J78: =I97*$B$40 -> 0 | K78: =J97*$B$40 -> 0 | ... BK78: =BJ97*$B$40 -> 0
A79: =CONCATENATE("Pago de intereses por el crédito"," ",A41) -> Pago de intereses por el crédito | D79: =C98*$B$41 -> 0 | E79: =D98*$B$41 -> 0 | F79: =E98*$B$41 -> 0 | G79: =F98*$B$41 -> 0 | H79: =G98*$B$41 -> 0 | I79: =H98*$B$41 -> 0 | J79: =I98*$B$41 -> 0 | K79: =J98*$B$41 -> 0 | ... BK79: =BJ98*$B$41 -> 0
A80: =CONCATENATE("Pago de intereses por el crédito"," ",A42) -> Pago de intereses por el crédito | D80: =C99*$B$42 -> 0 | E80: =D99*$B$42 -> 0 | F80: =E99*$B$42 -> 0 | G80: =F99*$B$42 -> 0 | H80: =G99*$B$42 -> 0 | I80: =H99*$B$42 -> 0 | J80: =I99*$B$42 -> 0 | K80: =J99*$B$42 -> 0 | ... BK80: =BJ99*$B$42 -> 0
A81: =CONCATENATE("Pago de intereses por el crédito"," ",A43) -> Pago de intereses por el crédito | D81: =C100*$B$43 -> 0 | E81: =D100*$B$43 -> 0 | F81: =E100*$B$43 -> 0 | G81: =F100*$B$43 -> 0 | H81: =G100*$B$43 -> 0 | I81: =H100*$B$43 -> 0 | J81: =I100*$B$43 -> 0 | K81: =J100*$B$43 -> 0 | ... BK81: =BJ100*$B$43 -> 0
A82: =CONCATENATE("Pago de intereses por el crédito"," ",A44) -> Pago de intereses por el crédito | D82: =C101*$B$44 -> 0 | E82: =D101*$B$44 -> 0 | F82: =E101*$B$44 -> 0 | G82: =F101*$B$44 -> 0 | H82: =G101*$B$44 -> 0 | I82: =H101*$B$44 -> 0 | J82: =I101*$B$44 -> 0 | K82: =J101*$B$44 -> 0 | ... BK82: =BJ101*$B$44 -> 0
A83: =CONCATENATE("Pago de intereses por el crédito"," ",A45) -> Pago de intereses por el crédito | D83: =C102*$B$45 -> 0 | E83: =D102*$B$45 -> 0 | F83: =E102*$B$45 -> 0 | G83: =F102*$B$45 -> 0 | H83: =G102*$B$45 -> 0 | I83: =H102*$B$45 -> 0 | J83: =I102*$B$45 -> 0 | K83: =J102*$B$45 -> 0 | ... BK83: =BJ102*$B$45 -> 0
A84: =CONCATENATE("Pago de intereses por el crédito"," ",A46) -> Pago de intereses por el crédito | D84: =C103*$B$46 -> 0 | E84: =D103*$B$46 -> 0 | F84: =E103*$B$46 -> 0 | G84: =F103*$B$46 -> 0 | H84: =G103*$B$46 -> 0 | I84: =H103*$B$46 -> 0 | J84: =I103*$B$46 -> 0 | K84: =J103*$B$46 -> 0 | ... BK84: =BJ103*$B$46 -> 0
A85: TOTAL INTERESES Y OTROS GASTOS FINANCIEROS | C85: =SUM(C70:C84) -> 0 | D85: =SUM(D70:D84) -> 0 | E85: =SUM(E70:E84) -> 0 | F85: =SUM(F70:F84) -> 0 | G85: =SUM(G70:G84) -> 0 | H85: =SUM(H70:H84) -> 0 | I85: =SUM(I70:I84) -> 0 | J85: =SUM(J70:J84) -> 0 | ... BK85: =SUM(BK70:BK84) -> 0
A87: SALDOS DE LA DEUDA | D87: =Año1 -> 2027 | P87: =Año2 -> 2028 | AB87: =Año3 -> 2029 | AN87: =Año4 -> 2030 | AZ87: =Año5 -> 2031 | BL87: =Año5+1 -> 2032
C88: Mes 0 | D88: Mes 1 | E88: Mes 2 | F88: Mes 3 | G88: Mes 4 | H88: Mes 5 | I88: Mes 6 | J88: Mes 7 | K88: Mes 8 | L88: Mes 9 | M88: Mes 10 | N88: Mes 11 | O88: Mes 12 | P88: Mes 13 | Q88: Mes 14 | R88: Mes 15 | S88: Mes 16 | T88: Mes 17 | U88: Mes 18 | V88: Mes 19 | W88: Mes 20 | X88: Mes 21 | Y88: Mes 22 | Z88: Mes 23 | AA88: Mes 24 | AB88: Mes 25 | AC88: Mes 26 | AD88: Mes 27 | AE88: Mes 28 | AF88: Mes 29 | AG88: Mes 30 | AH88: Mes 31 | AI88: Mes 32 | AJ88: Mes 33 | AK88: Mes 34 | AL88: Mes 35 | AM88: Mes 36 | AN88: Mes 37 | AO88: Mes 38 | AP88: Mes 39 | AQ88: Mes 40 | AR88: Mes 41 | AS88: Mes 42 | AT88: Mes 43 | AU88: Mes 44 | AV88: Mes 45 | AW88: Mes 46 | AX88: Mes 47 | AY88: Mes 48 | AZ88: Mes 49 | BA88: Mes 50 | BB88: Mes 51 | BC88: Mes 52 | BD88: Mes 53 | BE88: Mes 54 | BF88: Mes 55 | BG88: Mes 56 | BH88: Mes 57 | BI88: Mes 58 | BJ88: Mes 59 | BK88: Mes 60 | BL88: Mes 61 | BM88: Mes 62 | BN88: Mes 63 | BO88: Mes 64 | BP88: Mes 65 | BQ88: Mes 66 | BR88: Mes 67 | BS88: Mes 68 | BT88: Mes 69 | BU88: Mes 70 | BV88: Mes 71 | BW88: Mes 72
A89: =CONCATENATE("Saldos del crédito"," ",A32) -> Saldos del crédito | C89: =IF(SUM($C$32:C32)-SUM($C$51:C51)>0,SUM($C$32:C32)-SUM($C$51:C51),0) -> 0 | D89: =IF(SUM($C$32:D32)-SUM($C$51:D51)>0,SUM($C$32:D32)-SUM($C$51:D51),0) -> 0 | E89: =IF(SUM($C$32:E32)-SUM($C$51:E51)>0,SUM($C$32:E32)-SUM($C$51:E51),0) -> 0 | F89: =IF(SUM($C$32:F32)-SUM($C$51:F51)>0,SUM($C$32:F32)-SUM($C$51:F51),0) -> 0 | G89: =IF(SUM($C$32:G32)-SUM($C$51:G51)>0,SUM($C$32:G32)-SUM($C$51:G51),0) -> 0 | H89: =IF(SUM($C$32:H32)-SUM($C$51:H51)>0,SUM($C$32:H32)-SUM($C$51:H51),0) -> 0 | I89: =IF(SUM($C$32:I32)-SUM($C$51:I51)>0,SUM($C$32:I32)-SUM($C$51:I51),0) -> 0 | J89: =IF(SUM($C$32:J32)-SUM($C$51:J51)>0,SUM($C$32:J32)-SUM($C$51:J51),0) -> 0 | ... BW89: =IF(SUM($C$32:BW32)-SUM($C$51:BW51)>0,SUM($C$32:BW32)-SUM($C$51:BW51),0) -> #DIV/0!
A90: =CONCATENATE("Saldos del crédito"," ",A33) -> Saldos del crédito | C90: =IF(SUM(C33:C33)-SUM(C52:C52)>0,SUM(C33:C33)-SUM(C52:C52),0) -> 0 | D90: =IF(SUM($C$33:D33)-SUM($C$52:D52)>0,SUM($C$33:D33)-SUM($C$52:D52),0) -> 0 | E90: =IF(SUM($C$33:E33)-SUM($C$52:E52)>0,SUM($C$33:E33)-SUM($C$52:E52),0) -> 0 | F90: =IF(SUM($C$33:F33)-SUM($C$52:F52)>0,SUM($C$33:F33)-SUM($C$52:F52),0) -> 0 | G90: =IF(SUM($C$33:G33)-SUM($C$52:G52)>0,SUM($C$33:G33)-SUM($C$52:G52),0) -> 0 | H90: =IF(SUM($C$33:H33)-SUM($C$52:H52)>0,SUM($C$33:H33)-SUM($C$52:H52),0) -> 0 | I90: =IF(SUM($C$33:I33)-SUM($C$52:I52)>0,SUM($C$33:I33)-SUM($C$52:I52),0) -> 0 | J90: =IF(SUM($C$33:J33)-SUM($C$52:J52)>0,SUM($C$33:J33)-SUM($C$52:J52),0) -> 0 | K90: =IF(SUM($C$33:K33)-SUM($C$52:K52)>0,SUM($C$33:K33)-SUM($C$52:K52),0) -> 0 | ... BW90: =IF(SUM($C$33:BW33)-SUM($C$52:BW52)>0,SUM($C$33:BW33)-SUM($C$52:BW52),0) -> #DIV/0!
A91: =CONCATENATE("Saldos del crédito"," ",A34) -> Saldos del crédito | C91: =IF(SUM($C$34:C34)-SUM($C$53:C53)>0,SUM($C$34:C34)-SUM($C$53:C53),0) -> 0 | D91: =IF(SUM($C$34:D34)-SUM($C$53:D53)>0,SUM($C$34:D34)-SUM($C$53:D53),0) -> 0 | E91: =IF(SUM($C$34:E34)-SUM($C$53:E53)>0,SUM($C$34:E34)-SUM($C$53:E53),0) -> 0 | F91: =IF(SUM($C$34:F34)-SUM($C$53:F53)>0,SUM($C$34:F34)-SUM($C$53:F53),0) -> 0 | G91: =IF(SUM($C$34:G34)-SUM($C$53:G53)>0,SUM($C$34:G34)-SUM($C$53:G53),0) -> 0 | H91: =IF(SUM($C$34:H34)-SUM($C$53:H53)>0,SUM($C$34:H34)-SUM($C$53:H53),0) -> 0 | I91: =IF(SUM($C$34:I34)-SUM($C$53:I53)>0,SUM($C$34:I34)-SUM($C$53:I53),0) -> 0 | J91: =IF(SUM($C$34:J34)-SUM($C$53:J53)>0,SUM($C$34:J34)-SUM($C$53:J53),0) -> 0 | ... BW91: =IF(SUM($C$34:BW34)-SUM($C$53:BW53)>0,SUM($C$34:BW34)-SUM($C$53:BW53),0) -> #DIV/0!
A92: =CONCATENATE("Saldos del crédito"," ",A35) -> Saldos del crédito | C92: =IF(SUM($C$35:C35)-SUM($C$54:C54)>0,SUM($C$35:C35)-SUM($C$54:C54),0) -> 0 | D92: =IF(SUM($C$35:D35)-SUM($C$54:D54)>0,SUM($C$35:D35)-SUM($C$54:D54),0) -> 0 | E92: =IF(SUM($C$35:E35)-SUM($C$54:E54)>0,SUM($C$35:E35)-SUM($C$54:E54),0) -> 0 | F92: =IF(SUM($C$35:F35)-SUM($C$54:F54)>0,SUM($C$35:F35)-SUM($C$54:F54),0) -> 0 | G92: =IF(SUM($C$35:G35)-SUM($C$54:G54)>0,SUM($C$35:G35)-SUM($C$54:G54),0) -> 0 | H92: =IF(SUM($C$35:H35)-SUM($C$54:H54)>0,SUM($C$35:H35)-SUM($C$54:H54),0) -> 0 | I92: =IF(SUM($C$35:I35)-SUM($C$54:I54)>0,SUM($C$35:I35)-SUM($C$54:I54),0) -> 0 | J92: =IF(SUM($C$35:J35)-SUM($C$54:J54)>0,SUM($C$35:J35)-SUM($C$54:J54),0) -> 0 | ... BW92: =IF(SUM($C$35:BW35)-SUM($C$54:BW54)>0,SUM($C$35:BW35)-SUM($C$54:BW54),0) -> #DIV/0!
A93: =CONCATENATE("Saldos del crédito"," ",A36) -> Saldos del crédito | C93: =IF(SUM($C$36:C36)-SUM($C$55:C55)>0,SUM($C$36:C36)-SUM($C$55:C55),0) -> 0 | D93: =IF(SUM($C$36:D36)-SUM($C$55:D55)>0,SUM($C$36:D36)-SUM($C$55:D55),0) -> 0 | E93: =IF(SUM($C$36:E36)-SUM($C$55:E55)>0,SUM($C$36:E36)-SUM($C$55:E55),0) -> 0 | F93: =IF(SUM($C$36:F36)-SUM($C$55:F55)>0,SUM($C$36:F36)-SUM($C$55:F55),0) -> 0 | G93: =IF(SUM($C$36:G36)-SUM($C$55:G55)>0,SUM($C$36:G36)-SUM($C$55:G55),0) -> 0 | H93: =IF(SUM($C$36:H36)-SUM($C$55:H55)>0,SUM($C$36:H36)-SUM($C$55:H55),0) -> 0 | I93: =IF(SUM($C$36:I36)-SUM($C$55:I55)>0,SUM($C$36:I36)-SUM($C$55:I55),0) -> 0 | J93: =IF(SUM($C$36:J36)-SUM($C$55:J55)>0,SUM($C$36:J36)-SUM($C$55:J55),0) -> 0 | ... BW93: =IF(SUM($C$36:BW36)-SUM($C$55:BW55)>0,SUM($C$36:BW36)-SUM($C$55:BW55),0) -> #DIV/0!
A94: =CONCATENATE("Saldos del crédito"," ",A37) -> Saldos del crédito | C94: =IF(SUM($C$37:C37)-SUM($C$56:C56)>0,SUM($C$37:C37)-SUM($C$56:C56),0) -> 0 | D94: =IF(SUM($C$37:D37)-SUM($C$56:D56)>0,SUM($C$37:D37)-SUM($C$56:D56),0) -> 0 | E94: =IF(SUM($C$37:E37)-SUM($C$56:E56)>0,SUM($C$37:E37)-SUM($C$56:E56),0) -> 0 | F94: =IF(SUM($C$37:F37)-SUM($C$56:F56)>0,SUM($C$37:F37)-SUM($C$56:F56),0) -> 0 | G94: =IF(SUM($C$37:G37)-SUM($C$56:G56)>0,SUM($C$37:G37)-SUM($C$56:G56),0) -> 0 | H94: =IF(SUM($C$37:H37)-SUM($C$56:H56)>0,SUM($C$37:H37)-SUM($C$56:H56),0) -> 0 | I94: =IF(SUM($C$37:I37)-SUM($C$56:I56)>0,SUM($C$37:I37)-SUM($C$56:I56),0) -> 0 | J94: =IF(SUM($C$37:J37)-SUM($C$56:J56)>0,SUM($C$37:J37)-SUM($C$56:J56),0) -> 0 | ... BW94: =IF(SUM($C$37:BW37)-SUM($C$56:BW56)>0,SUM($C$37:BW37)-SUM($C$56:BW56),0) -> #DIV/0!
A95: =CONCATENATE("Saldos del crédito"," ",A38) -> Saldos del crédito | C95: =IF(SUM($C$38:C38)-SUM($C$57:C57)>0,SUM($C$38:C38)-SUM($C$57:C57),0) -> 0 | D95: =IF(SUM($C$38:D38)-SUM($C$57:D57)>0,SUM($C$38:D38)-SUM($C$57:D57),0) -> 0 | E95: =IF(SUM($C$38:E38)-SUM($C$57:E57)>0,SUM($C$38:E38)-SUM($C$57:E57),0) -> 0 | F95: =IF(SUM($C$38:F38)-SUM($C$57:F57)>0,SUM($C$38:F38)-SUM($C$57:F57),0) -> 0 | G95: =IF(SUM($C$38:G38)-SUM($C$57:G57)>0,SUM($C$38:G38)-SUM($C$57:G57),0) -> 0 | H95: =IF(SUM($C$38:H38)-SUM($C$57:H57)>0,SUM($C$38:H38)-SUM($C$57:H57),0) -> 0 | I95: =IF(SUM($C$38:I38)-SUM($C$57:I57)>0,SUM($C$38:I38)-SUM($C$57:I57),0) -> 0 | J95: =IF(SUM($C$38:J38)-SUM($C$57:J57)>0,SUM($C$38:J38)-SUM($C$57:J57),0) -> 0 | ... BW95: =IF(SUM($C$38:BW38)-SUM($C$57:BW57)>0,SUM($C$38:BW38)-SUM($C$57:BW57),0) -> #DIV/0!
A96: =CONCATENATE("Saldos del crédito"," ",A39) -> Saldos del crédito | C96: =IF(SUM($C$39:C39)-SUM($C$58:C58)>0,SUM($C$39:C39)-SUM($C$58:C58),0) -> 0 | D96: =IF(SUM($C$39:D39)-SUM($C$58:D58)>0,SUM($C$39:D39)-SUM($C$58:D58),0) -> 0 | E96: =IF(SUM($C$39:E39)-SUM($C$58:E58)>0,SUM($C$39:E39)-SUM($C$58:E58),0) -> 0 | F96: =IF(SUM($C$39:F39)-SUM($C$58:F58)>0,SUM($C$39:F39)-SUM($C$58:F58),0) -> 0 | G96: =IF(SUM($C$39:G39)-SUM($C$58:G58)>0,SUM($C$39:G39)-SUM($C$58:G58),0) -> 0 | H96: =IF(SUM($C$39:H39)-SUM($C$58:H58)>0,SUM($C$39:H39)-SUM($C$58:H58),0) -> 0 | I96: =IF(SUM($C$39:I39)-SUM($C$58:I58)>0,SUM($C$39:I39)-SUM($C$58:I58),0) -> 0 | J96: =IF(SUM($C$39:J39)-SUM($C$58:J58)>0,SUM($C$39:J39)-SUM($C$58:J58),0) -> 0 | ... BW96: =IF(SUM($C$39:BW39)-SUM($C$58:BW58)>0,SUM($C$39:BW39)-SUM($C$58:BW58),0) -> #DIV/0!
A97: =CONCATENATE("Saldos del crédito"," ",A40) -> Saldos del crédito | C97: =IF(SUM($C$40:C40)-SUM($C$59:C59)>0,SUM($C$40:C40)-SUM($C$59:C59),0) -> 0 | D97: =IF(SUM($C$40:D40)-SUM($C$59:D59)>0,SUM($C$40:D40)-SUM($C$59:D59),0) -> 0 | E97: =IF(SUM($C$40:E40)-SUM($C$59:E59)>0,SUM($C$40:E40)-SUM($C$59:E59),0) -> 0 | F97: =IF(SUM($C$40:F40)-SUM($C$59:F59)>0,SUM($C$40:F40)-SUM($C$59:F59),0) -> 0 | G97: =IF(SUM($C$40:G40)-SUM($C$59:G59)>0,SUM($C$40:G40)-SUM($C$59:G59),0) -> 0 | H97: =IF(SUM($C$40:H40)-SUM($C$59:H59)>0,SUM($C$40:H40)-SUM($C$59:H59),0) -> 0 | I97: =IF(SUM($C$40:I40)-SUM($C$59:I59)>0,SUM($C$40:I40)-SUM($C$59:I59),0) -> 0 | J97: =IF(SUM($C$40:J40)-SUM($C$59:J59)>0,SUM($C$40:J40)-SUM($C$59:J59),0) -> 0 | ... BW97: =IF(SUM($C$40:BW40)-SUM($C$59:BW59)>0,SUM($C$40:BW40)-SUM($C$59:BW59),0) -> #DIV/0!
A98: =CONCATENATE("Saldos del crédito"," ",A41) -> Saldos del crédito | C98: =IF(SUM($C$41:C41)-SUM($C$60:C60)>0,SUM($C$41:C41)-SUM($C$60:C60),0) -> 0 | D98: =IF(SUM($C$41:D41)-SUM($C$60:D60)>0,SUM($C$41:D41)-SUM($C$60:D60),0) -> 0 | E98: =IF(SUM($C$41:E41)-SUM($C$60:E60)>0,SUM($C$41:E41)-SUM($C$60:E60),0) -> 0 | F98: =IF(SUM($C$41:F41)-SUM($C$60:F60)>0,SUM($C$41:F41)-SUM($C$60:F60),0) -> 0 | G98: =IF(SUM($C$41:G41)-SUM($C$60:G60)>0,SUM($C$41:G41)-SUM($C$60:G60),0) -> 0 | H98: =IF(SUM($C$41:H41)-SUM($C$60:H60)>0,SUM($C$41:H41)-SUM($C$60:H60),0) -> 0 | I98: =IF(SUM($C$41:I41)-SUM($C$60:I60)>0,SUM($C$41:I41)-SUM($C$60:I60),0) -> 0 | J98: =IF(SUM($C$41:J41)-SUM($C$60:J60)>0,SUM($C$41:J41)-SUM($C$60:J60),0) -> 0 | ... BW98: =IF(SUM($C$41:BW41)-SUM($C$60:BW60)>0,SUM($C$41:BW41)-SUM($C$60:BW60),0) -> #DIV/0!
A99: =CONCATENATE("Saldos del crédito"," ",A42) -> Saldos del crédito | C99: =IF(SUM($C$42:C42)-SUM($C$61:C61)>0,SUM($C$42:C42)-SUM($C$61:C61),0) -> 0 | D99: =IF(SUM($C$42:D42)-SUM($C$61:D61)>0,SUM($C$42:D42)-SUM($C$61:D61),0) -> 0 | E99: =IF(SUM($C$42:E42)-SUM($C$61:E61)>0,SUM($C$42:E42)-SUM($C$61:E61),0) -> 0 | F99: =IF(SUM($C$42:F42)-SUM($C$61:F61)>0,SUM($C$42:F42)-SUM($C$61:F61),0) -> 0 | G99: =IF(SUM($C$42:G42)-SUM($C$61:G61)>0,SUM($C$42:G42)-SUM($C$61:G61),0) -> 0 | H99: =IF(SUM($C$42:H42)-SUM($C$61:H61)>0,SUM($C$42:H42)-SUM($C$61:H61),0) -> 0 | I99: =IF(SUM($C$42:I42)-SUM($C$61:I61)>0,SUM($C$42:I42)-SUM($C$61:I61),0) -> 0 | J99: =IF(SUM($C$42:J42)-SUM($C$61:J61)>0,SUM($C$42:J42)-SUM($C$61:J61),0) -> 0 | ... BW99: =IF(SUM($C$42:BW42)-SUM($C$61:BW61)>0,SUM($C$42:BW42)-SUM($C$61:BW61),0) -> #DIV/0!
A100: =CONCATENATE("Saldos del crédito"," ",A43) -> Saldos del crédito | C100: =IF(SUM($C$43:C43)-SUM($C$62:C62)>0,SUM($C$43:C43)-SUM($C$62:C62),0) -> 0 | D100: =IF(SUM($C$43:D43)-SUM($C$62:D62)>0,SUM($C$43:D43)-SUM($C$62:D62),0) -> 0 | E100: =IF(SUM($C$43:E43)-SUM($C$62:E62)>0,SUM($C$43:E43)-SUM($C$62:E62),0) -> 0 | F100: =IF(SUM($C$43:F43)-SUM($C$62:F62)>0,SUM($C$43:F43)-SUM($C$62:F62),0) -> 0 | G100: =IF(SUM($C$43:G43)-SUM($C$62:G62)>0,SUM($C$43:G43)-SUM($C$62:G62),0) -> 0 | H100: =IF(SUM($C$43:H43)-SUM($C$62:H62)>0,SUM($C$43:H43)-SUM($C$62:H62),0) -> 0 | I100: =IF(SUM($C$43:I43)-SUM($C$62:I62)>0,SUM($C$43:I43)-SUM($C$62:I62),0) -> 0 | J100: =IF(SUM($C$43:J43)-SUM($C$62:J62)>0,SUM($C$43:J43)-SUM($C$62:J62),0) -> 0 | ... BW100: =IF(SUM($C$43:BW43)-SUM($C$62:BW62)>0,SUM($C$43:BW43)-SUM($C$62:BW62),0) -> #DIV/0!
A101: =CONCATENATE("Saldos del crédito"," ",A44) -> Saldos del crédito | C101: =IF(SUM($C$44:C44)-SUM($C$63:C63)>0,SUM($C$44:C44)-SUM($C$63:C63),0) -> 0 | D101: =IF(SUM($C$44:D44)-SUM($C$63:D63)>0,SUM($C$44:D44)-SUM($C$63:D63),0) -> 0 | E101: =IF(SUM($C$44:E44)-SUM($C$63:E63)>0,SUM($C$44:E44)-SUM($C$63:E63),0) -> 0 | F101: =IF(SUM($C$44:F44)-SUM($C$63:F63)>0,SUM($C$44:F44)-SUM($C$63:F63),0) -> 0 | G101: =IF(SUM($C$44:G44)-SUM($C$63:G63)>0,SUM($C$44:G44)-SUM($C$63:G63),0) -> 0 | H101: =IF(SUM($C$44:H44)-SUM($C$63:H63)>0,SUM($C$44:H44)-SUM($C$63:H63),0) -> 0 | I101: =IF(SUM($C$44:I44)-SUM($C$63:I63)>0,SUM($C$44:I44)-SUM($C$63:I63),0) -> 0 | J101: =IF(SUM($C$44:J44)-SUM($C$63:J63)>0,SUM($C$44:J44)-SUM($C$63:J63),0) -> 0 | ... BW101: =IF(SUM($C$44:BW44)-SUM($C$63:BW63)>0,SUM($C$44:BW44)-SUM($C$63:BW63),0) -> #DIV/0!
A102: =CONCATENATE("Saldos del crédito"," ",A45) -> Saldos del crédito | C102: =IF(SUM($C$45:C45)-SUM($C$64:C64)>0,SUM($C$45:C45)-SUM($C$64:C64),0) -> 0 | D102: =IF(SUM($C$45:D45)-SUM($C$64:D64)>0,SUM($C$45:D45)-SUM($C$64:D64),0) -> 0 | E102: =IF(SUM($C$45:E45)-SUM($C$64:E64)>0,SUM($C$45:E45)-SUM($C$64:E64),0) -> 0 | F102: =IF(SUM($C$45:F45)-SUM($C$64:F64)>0,SUM($C$45:F45)-SUM($C$64:F64),0) -> 0 | G102: =IF(SUM($C$45:G45)-SUM($C$64:G64)>0,SUM($C$45:G45)-SUM($C$64:G64),0) -> 0 | H102: =IF(SUM($C$45:H45)-SUM($C$64:H64)>0,SUM($C$45:H45)-SUM($C$64:H64),0) -> 0 | I102: =IF(SUM($C$45:I45)-SUM($C$64:I64)>0,SUM($C$45:I45)-SUM($C$64:I64),0) -> 0 | J102: =IF(SUM($C$45:J45)-SUM($C$64:J64)>0,SUM($C$45:J45)-SUM($C$64:J64),0) -> 0 | ... BW102: =IF(SUM($C$45:BW45)-SUM($C$64:BW64)>0,SUM($C$45:BW45)-SUM($C$64:BW64),0) -> #DIV/0!
A103: =CONCATENATE("Saldos del crédito"," ",A46) -> Saldos del crédito | C103: =IF(SUM($C$46:C46)-SUM($C$65:C65)>0,SUM($C$46:C46)-SUM($C$65:C65),0) -> 0 | D103: =IF(SUM($C$46:D46)-SUM($C$65:D65)>0,SUM($C$46:D46)-SUM($C$65:D65),0) -> 0 | E103: =IF(SUM($C$46:E46)-SUM($C$65:E65)>0,SUM($C$46:E46)-SUM($C$65:E65),0) -> 0 | F103: =IF(SUM($C$46:F46)-SUM($C$65:F65)>0,SUM($C$46:F46)-SUM($C$65:F65),0) -> 0 | G103: =IF(SUM($C$46:G46)-SUM($C$65:G65)>0,SUM($C$46:G46)-SUM($C$65:G65),0) -> 0 | H103: =IF(SUM($C$46:H46)-SUM($C$65:H65)>0,SUM($C$46:H46)-SUM($C$65:H65),0) -> 0 | I103: =IF(SUM($C$46:I46)-SUM($C$65:I65)>0,SUM($C$46:I46)-SUM($C$65:I65),0) -> 0 | J103: =IF(SUM($C$46:J46)-SUM($C$65:J65)>0,SUM($C$46:J46)-SUM($C$65:J65),0) -> 0 | ... BW103: =IF(SUM($C$46:BW46)-SUM($C$65:BW65)>0,SUM($C$46:BW46)-SUM($C$65:BW65),0) -> #DIV/0!
A104: TOTAL SALDOS DE LA DEUDA | C104: =SUM(C89:C103) -> 0 | D104: =SUM(D89:D103) -> 0 | E104: =SUM(E89:E103) -> 0 | F104: =SUM(F89:F103) -> 0 | G104: =SUM(G89:G103) -> 0 | H104: =SUM(H89:H103) -> 0 | I104: =SUM(I89:I103) -> 0 | J104: =SUM(J89:J103) -> 0 | ... BW104: =SUM(BW89:BW103) -> #DIV/0!
A107: Plantilla Realizada por María Teresa Macías Joven
A108: Universidad de La Sabana
A109: Versión 2021
A110: ®Todos los derechos reservados
A111: Si desea utilizar esta plantilla por fuera del programa Expo-Empresarial, clase de proyecto empresarial de la Universidad de La Sabana, asegúrese de poseer los derechos de uso por parte de la autora de la plantilla, con una autorización clara, expresa y por escrito.

Sheet PRESUPUESTO
D1: =CONCATENATE(INICIO!$B$10," ",INICIO!$B$11) -> TIZA S.A.S
D5: ESTADOS FINANCIEROS BÁSICOS
A7: ESTADO DE RESULTADOS | D7: =Año1 -> 2027 | P7: =Año2 -> 2028 | AB7: =Año3 -> 2029 | AN7: =Año4 -> 2030 | AZ7: =Año5 -> 2031
C8: Mes 0 | D8: Mes 1 | E8: Mes 2 | F8: Mes 3 | G8: Mes 4 | H8: Mes 5 | I8: Mes 6 | J8: Mes 7 | K8: Mes 8 | L8: Mes 9 | M8: Mes 10 | N8: Mes 11 | O8: Mes 12 | P8: Mes 13 | Q8: Mes 14 | R8: Mes 15 | S8: Mes 16 | T8: Mes 17 | U8: Mes 18 | V8: Mes 19 | W8: Mes 20 | X8: Mes 21 | Y8: Mes 22 | Z8: Mes 23 | AA8: Mes 24 | AB8: Mes 25 | AC8: Mes 26 | AD8: Mes 27 | AE8: Mes 28 | AF8: Mes 29 | AG8: Mes 30 | AH8: Mes 31 | AI8: Mes 32 | AJ8: Mes 33 | AK8: Mes 34 | AL8: Mes 35 | AM8: Mes 36 | AN8: Mes 37 | AO8: Mes 38 | AP8: Mes 39 | AQ8: Mes 40 | AR8: Mes 41 | AS8: Mes 42 | AT8: Mes 43 | AU8: Mes 44 | AV8: Mes 45 | AW8: Mes 46 | AX8: Mes 47 | AY8: Mes 48 | AZ8: Mes 49 | BA8: Mes 50 | BB8: Mes 51 | BC8: Mes 52 | BD8: Mes 53 | BE8: Mes 54 | BF8: Mes 55 | BG8: Mes 56 | BH8: Mes 57 | BI8: Mes 58 | BJ8: Mes 59 | BK8: Mes 60
A9: Ventas | D9: =INGRESOS!B30 -> 400000 | E9: =INGRESOS!C30 -> 600000 | F9: =INGRESOS!D30 -> 880000 | G9: =INGRESOS!E30 -> 1200000 | H9: =INGRESOS!F30 -> 1520000 | I9: =INGRESOS!G30 -> 1800000 | J9: =INGRESOS!H30 -> 2200000 | K9: =INGRESOS!I30 -> 2600000 | ... BK9: =INGRESOS!BI30 -> 0
A10: Costo de Ventas | D10: =COSTOS!B65 -> 5612170.3 | E10: =COSTOS!C65 -> 5615490.3 | F10: =COSTOS!D65 -> 5620138.3 | G10: =COSTOS!E65 -> 5625450.3 | H10: =COSTOS!F65 -> 5630762.3 | I10: =COSTOS!G65 -> 5635410.3 | J10: =COSTOS!H65 -> 5745800.3 | K10: =COSTOS!I65 -> 5752440.3 | ... BK10: =COSTOS!BI65 -> 0
A11: UTILIDAD BRUTA | C11: =C9-C10 -> 0 | D11: =D9-D10 -> -5212170.3 | E11: =E9-E10 -> -5015490.3 | F11: =F9-F10 -> -4740138.3 | G11: =G9-G10 -> -4425450.3 | H11: =H9-H10 -> -4110762.3 | I11: =I9-I10 -> -3835410.3 | J11: =J9-J10 -> -3545800.3 | ... BK11: =BK9-BK10 -> 0
A12: Gastos de Administración y Ventas | D12: =GASTOS!B77 -> 317000 | E12: =GASTOS!C77 -> 317000 | F12: =GASTOS!D77 -> 317000 | G12: =GASTOS!E77 -> 317000 | H12: =GASTOS!F77 -> 317000 | I12: =GASTOS!G77 -> 317000 | J12: =GASTOS!H77 -> 317000 | K12: =GASTOS!I77 -> 317000 | ... BK12: =GASTOS!BI77 -> 0
A13: Gastos Pre-Operativos | C13: =INICIO!B65 -> 2382000 | O13: =INICIO!C65 -> 0 | AA13: =INICIO!D65 -> 0 | AM13: =INICIO!E65 -> 0 | AY13: =INICIO!F65 -> 0 | BK13: =INICIO!G65 -> 0
A14: Depreciaciones | D14: =INVERSIONES!C67 -> 0 | E14: =INVERSIONES!D67 -> 0 | F14: =INVERSIONES!E67 -> 0 | G14: =INVERSIONES!F67 -> 0 | H14: =INVERSIONES!G67 -> 0 | I14: =INVERSIONES!H67 -> 0 | J14: =INVERSIONES!I67 -> 0 | K14: =INVERSIONES!J67 -> 0 | ... BK14: =INVERSIONES!BJ67 -> 0
A15: UTILIDAD OPERATIVA | C15: =C11-C12-C13-C14 -> -2382000 | D15: =D11-D12-D13-D14 -> -5529170.3 | E15: =E11-E12-E13-E14 -> -5332490.3 | F15: =F11-F12-F13-F14 -> -5057138.3 | G15: =G11-G12-G13-G14 -> -4742450.3 | H15: =H11-H12-H13-H14 -> -4427762.3 | I15: =I11-I12-I13-I14 -> -4152410.3 | J15: =J11-J12-J13-J14 -> -3862800.3 | ... BK15: =BK11-BK12-BK13-BK14 -> 0
A16: Gastos Financieros | C16: =FINANCIACIÓN!C85 -> 0 | D16: =FINANCIACIÓN!D85 -> 0 | E16: =FINANCIACIÓN!E85 -> 0 | F16: =FINANCIACIÓN!F85 -> 0 | G16: =FINANCIACIÓN!G85 -> 0 | H16: =FINANCIACIÓN!H85 -> 0 | I16: =FINANCIACIÓN!I85 -> 0 | J16: =FINANCIACIÓN!J85 -> 0 | ... BK16: =FINANCIACIÓN!BK85 -> 0
A17: UTILIDAD ANTES DE IMPUESTOS | C17: =C15-C16 -> -2382000 | D17: =D15-D16 -> -5529170.3 | E17: =E15-E16 -> -5332490.3 | F17: =F15-F16 -> -5057138.3 | G17: =G15-G16 -> -4742450.3 | H17: =H15-H16 -> -4427762.3 | I17: =I15-I16 -> -4152410.3 | J17: =J15-J16 -> -3862800.3 | ... BK17: =BK15-BK16 -> 0
A18: Impuestos | D18: =IF(D17>0,D17*INICIO!$B$34,0) -> 0 | E18: =IF(E17>0,E17*INICIO!$B$34,0) -> 0 | F18: =IF(F17>0,F17*INICIO!$B$34,0) -> 0 | G18: =IF(G17>0,G17*INICIO!$B$34,0) -> 0 | H18: =IF(H17>0,H17*INICIO!$B$34,0) -> 0 | I18: =IF(I17>0,I17*INICIO!$B$34,0) -> 0 | J18: =IF(J17>0,J17*INICIO!$B$34,0) -> 0 | K18: =IF(K17>0,K17*INICIO!$B$34,0) -> 0 | ... O18: =IF(O17>0,O17*INICIO!$B$34,0) -> 0 | P18: =IF(P17>0,P17*INICIO!$C$34,0) -> 0 | Q18: =IF(Q17>0,Q17*INICIO!$C$34,0) -> 0 | R18: =IF(R17>0,R17*INICIO!$C$34,0) -> 0 | S18: =IF(S17>0,S17*INICIO!$C$34,0) -> 0 | T18: =IF(T17>0,T17*INICIO!$C$34,0) -> 0 | U18: =IF(U17>0,U17*INICIO!$C$34,0) -> 0 | V18: =IF(V17>0,V17*INICIO!$C$34,0) -> 0 | W18: =IF(W17>0,W17*INICIO!$C$34,0) -> 0 | ... AA18: =IF(AA17>0,AA17*INICIO!$C$34,0) -> 0 | AB18: =IF(AB17>0,AB17*INICIO!$D$34,0) -> 0 | AC18: =IF(AC17>0,AC17*INICIO!$D$34,0) -> 0 | AD18: =IF(AD17>0,AD17*INICIO!$D$34,0) -> 0 | AE18: =IF(AE17>0,AE17*INICIO!$D$34,0) -> 0 | AF18: =IF(AF17>0,AF17*INICIO!$D$34,0) -> 0 | AG18: =IF(AG17>0,AG17*INICIO!$D$34,0) -> 0 | AH18: =IF(AH17>0,AH17*INICIO!$D$34,0) -> 0 | AI18: =IF(AI17>0,AI17*INICIO!$D$34,0) -> 620951.57 | ... AM18: =IF(AM17>0,AM17*INICIO!$D$34,0) -> 4059211.6 | AN18: =IF(AN17>0,AN17*INICIO!$E$34,0) -> 482355.77 | AO18: =IF(AO17>0,AO17*INICIO!$E$34,0) -> 1445068.6 | AP18: =IF(AP17>0,AP17*INICIO!$E$34,0) -> 2407781.4 | AQ18: =IF(AQ17>0,AQ17*INICIO!$E$34,0) -> 3508024.6 | AR18: =IF(AR17>0,AR17*INICIO!$E$34,0) -> 4608267.8 | AS18: =IF(AS17>0,AS17*INICIO!$E$34,0) -> 5708511 | AT18: =IF(AT17>0,AT17*INICIO!$E$34,0) -> 6808754.2 | AU18: =IF(AU17>0,AU17*INICIO!$E$34,0) -> 7908997.4 | ... AY18: =IF(AY17>0,AY17*INICIO!$E$34,0) -> 12860092 | AZ18: =IF(AZ17>0,AZ17*INICIO!$F$34,0) -> 14076356 | BA18: =IF(BA17>0,BA17*INICIO!$F$34,0) -> 0 | BB18: =IF(BB17>0,BB17*INICIO!$F$34,0) -> 0 | BC18: =IF(BC17>0,BC17*INICIO!$F$34,0) -> 0 | BD18: =IF(BD17>0,BD17*INICIO!$F$34,0) -> 0 | BE18: =IF(BE17>0,BE17*INICIO!$F$34,0) -> 0 | BF18: =IF(BF17>0,BF17*INICIO!$F$34,0) -> 0 | BG18: =IF(BG17>0,BG17*INICIO!$F$34,0) -> 0 | ... BK18: =IF(BK17>0,BK17*INICIO!$F$34,0) -> 0
A19: UTILIDAD NETA | C19: =C17-C18 -> -2382000 | D19: =D17-D18 -> -5529170.3 | E19: =E17-E18 -> -5332490.3 | F19: =F17-F18 -> -5057138.3 | G19: =G17-G18 -> -4742450.3 | H19: =H17-H18 -> -4427762.3 | I19: =I17-I18 -> -4152410.3 | J19: =J17-J18 -> -3862800.3 | ... BK19: =BK17-BK18 -> 0
A21: CAPITAL DE TRABAJO | D21: =Año1 -> 2027 | P21: =Año2 -> 2028 | AB21: =Año3 -> 2029 | AN21: =Año4 -> 2030 | AZ21: =Año5 -> 2031
C22: Mes 0 | D22: Mes 1 | E22: Mes 2 | F22: Mes 3 | G22: Mes 4 | H22: Mes 5 | I22: Mes 6 | J22: Mes 7 | K22: Mes 8 | L22: Mes 9 | M22: Mes 10 | N22: Mes 11 | O22: Mes 12 | P22: Mes 13 | Q22: Mes 14 | R22: Mes 15 | S22: Mes 16 | T22: Mes 17 | U22: Mes 18 | V22: Mes 19 | W22: Mes 20 | X22: Mes 21 | Y22: Mes 22 | Z22: Mes 23 | AA22: Mes 24 | AB22: Mes 25 | AC22: Mes 26 | AD22: Mes 27 | AE22: Mes 28 | AF22: Mes 29 | AG22: Mes 30 | AH22: Mes 31 | AI22: Mes 32 | AJ22: Mes 33 | AK22: Mes 34 | AL22: Mes 35 | AM22: Mes 36 | AN22: Mes 37 | AO22: Mes 38 | AP22: Mes 39 | AQ22: Mes 40 | AR22: Mes 41 | AS22: Mes 42 | AT22: Mes 43 | AU22: Mes 44 | AV22: Mes 45 | AW22: Mes 46 | AX22: Mes 47 | AY22: Mes 48 | AZ22: Mes 49 | BA22: Mes 50 | BB22: Mes 51 | BC22: Mes 52 | BD22: Mes 53 | BE22: Mes 54 | BF22: Mes 55 | BG22: Mes 56 | BH22: Mes 57 | BI22: Mes 58 | BJ22: Mes 59 | BK22: Mes 60
A23: Cuenta por Cobrar | D23: =(D9/30)*INGRESOS!B11 -> 0 | E23: =(E9/30)*INGRESOS!C11 -> 0 | F23: =(F9/30)*INGRESOS!D11 -> 0 | G23: =(G9/30)*INGRESOS!E11 -> 0 | H23: =(H9/30)*INGRESOS!F11 -> 0 | I23: =(I9/30)*INGRESOS!G11 -> 0 | J23: =(J9/30)*INGRESOS!H11 -> 0 | K23: =(K9/30)*INGRESOS!I11 -> 0 | ... BK23: =(BK9/30)*INGRESOS!BI11 -> 0
A24: Inventario | D24: =(D10/30)*COSTOS!B63 -> 0 | E24: =(E10/30)*COSTOS!C63 -> 0 | F24: =(F10/30)*COSTOS!D63 -> 0 | G24: =(G10/30)*COSTOS!E63 -> 0 | H24: =(H10/30)*COSTOS!F63 -> 0 | I24: =(I10/30)*COSTOS!G63 -> 0 | J24: =(J10/30)*COSTOS!H63 -> 0 | K24: =(K10/30)*COSTOS!I63 -> 0 | ... BK24: =(BK10/30)*COSTOS!BI63 -> 0
A25: Proveedores | D25: =((D10+D24-C24)/30)*COSTOS!B62 -> 0 | E25: =((E10+E24-D24)/30)*COSTOS!C62 -> 0 | F25: =((F10+F24-E24)/30)*COSTOS!D62 -> 0 | G25: =((G10+G24-F24)/30)*COSTOS!E62 -> 0 | H25: =((H10+H24-G24)/30)*COSTOS!F62 -> 0 | I25: =((I10+I24-H24)/30)*COSTOS!G62 -> 0 | J25: =((J10+J24-I24)/30)*COSTOS!H62 -> 0 | K25: =((K10+K24-J24)/30)*COSTOS!I62 -> 0 | ... BK25: =((BK10+BK24-BJ24)/30)*COSTOS!BI62 -> 0
A26: Cuenta por Pagar Impuestos | D26: =SUM($C$18:D18) -> 0 | E26: =SUM($C$18:E18) -> 0 | F26: =SUM($C$18:F18) -> 0 | G26: =SUM($C$18:G18) -> 0 | H26: =SUM($C$18:H18) -> 0 | I26: =SUM($C$18:I18) -> 0 | J26: =SUM($C$18:J18) -> 0 | K26: =SUM($C$18:K18) -> 0 | ... O26: =SUM($C$18:O18) -> 0 | P26: =SUM($P$18:P18) -> 0 | Q26: =SUM($P$18:Q18) -> 0 | R26: =SUM($P$18:R18) -> 0 | S26: =SUM($P$18:S18) -> 0 | T26: =SUM($P$18:T18) -> 0 | U26: =SUM($P$18:U18) -> 0 | V26: =SUM($P$18:V18) -> 0 | W26: =SUM($P$18:W18) -> 0 | ... AA26: =SUM($P$18:AA18) -> 0 | AB26: =SUM($AB$18:AB18) -> 0 | AC26: =SUM($AB$18:AC18) -> 0 | AD26: =SUM($AB$18:AD18) -> 0 | AE26: =SUM($AB$18:AE18) -> 0 | AF26: =SUM($AB$18:AF18) -> 0 | AG26: =SUM($AB$18:AG18) -> 0 | AH26: =SUM($AB$18:AH18) -> 0 | AI26: =SUM($AB$18:AI18) -> 620951.57 | ... AM26: =SUM($AB$18:AM18) -> 11494112 | AN26: =SUM($AN$18:AN18) -> 482355.77 | AO26: =SUM($AN$18:AO18) -> 1927424.3 | AP26: =SUM($AN$18:AP18) -> 4335205.7 | AQ26: =SUM($AN$18:AQ18) -> 7843230.3 | AR26: =SUM($AN$18:AR18) -> 12451498 | AS26: =SUM($AN$18:AS18) -> 18160009 | AT26: =SUM($AN$18:AT18) -> 24968763 | AU26: =SUM($AN$18:AU18) -> 32877761 | ... AY26: =SUM($AN$18:AY18) -> 76478895 | AZ26: =SUM($AZ$18:AZ18) -> 14076356 | BA26: =SUM($AZ$18:BA18) -> 14076356 | BB26: =SUM($AZ$18:BB18) -> 14076356 | BC26: =SUM($AZ$18:BC18) -> 14076356 | BD26: =SUM($AZ$18:BD18) -> 14076356 | BE26: =SUM($AZ$18:BE18) -> 14076356 | BF26: =SUM($AZ$18:BF18) -> 14076356 | BG26: =SUM($AZ$18:BG18) -> 14076356 | ... BK26: =SUM($AZ$18:BK18) -> 14076356
A27: Cuenta por Pagar Prestaciones | D27: =GASTOS!B87 -> 586250 | E27: =GASTOS!C87 -> 1172500 | F27: =GASTOS!D87 -> 1758750 | G27: =GASTOS!E87 -> 2345000 | H27: =GASTOS!F87 -> 2931250 | I27: =GASTOS!G87 -> 3517500 | J27: =GASTOS!H87 -> 2353750 | K27: =GASTOS!I87 -> 2940000 | ... BK27: =GASTOS!BI87 -> 2230416.7
A28: Cuenta por Pagar Dividendos | D28: =IF(SUM($C$19:C19)>0,SUM($C$19:C19)*(1-FINANCIACIÓN!C28),0) -> 0 | E28: =IF(SUM($C$19:D19)>0,SUM($C$19:D19)*(1-FINANCIACIÓN!D28),0) -> 0 | F28: =IF(SUM($C$19:E19)>0,SUM($C$19:E19)*(1-FINANCIACIÓN!E28),0) -> 0 | G28: =IF(SUM($C$19:F19)>0,SUM($C$19:F19)*(1-FINANCIACIÓN!F28),0) -> 0 | H28: =IF(SUM($C$19:G19)>0,SUM($C$19:G19)*(1-FINANCIACIÓN!G28),0) -> 0 | I28: =IF(SUM($C$19:H19)>0,SUM($C$19:H19)*(1-FINANCIACIÓN!H28),0) -> 0 | J28: =IF(SUM($C$19:I19)>0,SUM($C$19:I19)*(1-FINANCIACIÓN!I28),0) -> 0 | K28: =IF(SUM($C$19:J19)>0,SUM($C$19:J19)*(1-FINANCIACIÓN!J28),0) -> 0 | ... P28: =IF(SUM($C$19:O19)>0,SUM($C$19:O19)*(1-FINANCIACIÓN!O28),0) -> 0 | Q28: =IF(SUM($P$19:P19)>0,SUM($P$19:P19)*(1-FINANCIACIÓN!P28),0) -> 0 | R28: =IF(SUM($P$19:Q19)>0,SUM($P$19:Q19)*(1-FINANCIACIÓN!Q28),0) -> 0 | S28: =IF(SUM($P$19:R19)>0,SUM($P$19:R19)*(1-FINANCIACIÓN!R28),0) -> 0 | T28: =IF(SUM($P$19:S19)>0,SUM($P$19:S19)*(1-FINANCIACIÓN!S28),0) -> 0 | U28: =IF(SUM($P$19:T19)>0,SUM($P$19:T19)*(1-FINANCIACIÓN!T28),0) -> 0 | V28: =IF(SUM($P$19:U19)>0,SUM($P$19:U19)*(1-FINANCIACIÓN!U28),0) -> 0 | W28: =IF(SUM($P$19:V19)>0,SUM($P$19:V19)*(1-FINANCIACIÓN!V28),0) -> 0 | X28: =IF(SUM($P$19:W19)>0,SUM($P$19:W19)*(1-FINANCIACIÓN!W28),0) -> 0 | ... AB28: =IF(SUM($P$19:AA19)>0,SUM($P$19:AA19)*(1-FINANCIACIÓN!AA28),0) -> 0 | AC28: =IF(SUM($AB$19:AB19)>0,SUM($AB$19:AB19)*(1-FINANCIACIÓN!AB28),0) -> 0 | AD28: =IF(SUM($AB$19:AC19)>0,SUM($AB$19:AC19)*(1-FINANCIACIÓN!AC28),0) -> 0 | AE28: =IF(SUM($AB$19:AD19)>0,SUM($AB$19:AD19)*(1-FINANCIACIÓN!AD28),0) -> 0 | AF28: =IF(SUM($AB$19:AE19)>0,SUM($AB$19:AE19)*(1-FINANCIACIÓN!AE28),0) -> 0 | AG28: =IF(SUM($AB$19:AF19)>0,SUM($AB$19:AF19)*(1-FINANCIACIÓN!AF28),0) -> 0 | AH28: =IF(SUM($AB$19:AG19)>0,SUM($AB$19:AG19)*(1-FINANCIACIÓN!AG28),0) -> 0 | AI28: =IF(SUM($AB$19:AH19)>0,SUM($AB$19:AH19)*(1-FINANCIACIÓN!AH28),0) -> 0 | AJ28: =IF(SUM($AB$19:AI19)>0,SUM($AB$19:AI19)*(1-FINANCIACIÓN!AI28),0) -> 0 | ... AN28: =IF(SUM($AB$19:AM19)>0,SUM($AB$19:AM19)*(1-FINANCIACIÓN!AM28),0) -> 0 | AO28: =IF(SUM($AN$19:AN19)>0,SUM($AN$19:AN19)*(1-FINANCIACIÓN!AN28),0) -> #REF! | AP28: =IF(SUM($AN$19:AO19)>0,SUM($AN$19:AO19)*(1-FINANCIACIÓN!AO28),0) -> #REF! | AQ28: =IF(SUM($AN$19:AP19)>0,SUM($AN$19:AP19)*(1-FINANCIACIÓN!AP28),0) -> #REF! | AR28: =IF(SUM($AN$19:AQ19)>0,SUM($AN$19:AQ19)*(1-FINANCIACIÓN!AQ28),0) -> #REF! | AS28: =IF(SUM($AN$19:AR19)>0,SUM($AN$19:AR19)*(1-FINANCIACIÓN!AR28),0) -> #REF! | AT28: =IF(SUM($AN$19:AS19)>0,SUM($AN$19:AS19)*(1-FINANCIACIÓN!AS28),0) -> #REF! | AU28: =IF(SUM($AN$19:AT19)>0,SUM($AN$19:AT19)*(1-FINANCIACIÓN!AT28),0) -> #REF! | AV28: =IF(SUM($AN$19:AU19)>0,SUM($AN$19:AU19)*(1-FINANCIACIÓN!AU28),0) -> #REF! | ... AZ28: =IF(SUM($AN$19:AY19)>0,SUM($AN$19:AY19)*(1-FINANCIACIÓN!AY28),0) -> #REF! | BA28: =IF(SUM($AZ$19:AZ19)>0,SUM($AZ$19:AZ19)*(1-FINANCIACIÓN!AZ28),0) -> #REF! | BB28: =IF(SUM($AZ$19:BA19)>0,SUM($AZ$19:BA19)*(1-FINANCIACIÓN!BA28),0) -> #REF! | BC28: =IF(SUM($AZ$19:BB19)>0,SUM($AZ$19:BB19)*(1-FINANCIACIÓN!BB28),0) -> #REF! | BD28: =IF(SUM($AZ$19:BC19)>0,SUM($AZ$19:BC19)*(1-FINANCIACIÓN!BC28),0) -> #REF! | BE28: =IF(SUM($AZ$19:BD19)>0,SUM($AZ$19:BD19)*(1-FINANCIACIÓN!BD28),0) -> #REF! | BF28: =IF(SUM($AZ$19:BE19)>0,SUM($AZ$19:BE19)*(1-FINANCIACIÓN!BE28),0) -> #REF! | BG28: =IF(SUM($AZ$19:BF19)>0,SUM($AZ$19:BF19)*(1-FINANCIACIÓN!BF28),0) -> #REF! | BH28: =IF(SUM($AZ$19:BG19)>0,SUM($AZ$19:BG19)*(1-FINANCIACIÓN!BG28),0) -> #REF! | ... BK28: =IF(SUM($AZ$19:BJ19)>0,SUM($AZ$19:BJ19)*(1-FINANCIACIÓN!BJ28),0) -> #REF!
A29: Total Cuentas por Pagar (otros) | D29: =SUM(D26:D28) -> 586250 | E29: =SUM(E26:E28) -> 1172500 | F29: =SUM(F26:F28) -> 1758750 | G29: =SUM(G26:G28) -> 2345000 | H29: =SUM(H26:H28) -> 2931250 | I29: =SUM(I26:I28) -> 3517500 | J29: =SUM(J26:J28) -> 2353750 | K29: =SUM(K26:K28) -> 2940000 | ... BK29: =SUM(BK26:BK28) -> #REF!
A31: PRESUPUESTO DE TESORERÍA | D31: =Año1 -> 2027 | P31: =Año2 -> 2028 | AB31: =Año3 -> 2029 | AN31: =Año4 -> 2030 | AZ31: =Año5 -> 2031
C32: Mes 0 | D32: Mes 1 | E32: Mes 2 | F32: Mes 3 | G32: Mes 4 | H32: Mes 5 | I32: Mes 6 | J32: Mes 7 | K32: Mes 8 | L32: Mes 9 | M32: Mes 10 | N32: Mes 11 | O32: Mes 12 | P32: Mes 13 | Q32: Mes 14 | R32: Mes 15 | S32: Mes 16 | T32: Mes 17 | U32: Mes 18 | V32: Mes 19 | W32: Mes 20 | X32: Mes 21 | Y32: Mes 22 | Z32: Mes 23 | AA32: Mes 24 | AB32: Mes 25 | AC32: Mes 26 | AD32: Mes 27 | AE32: Mes 28 | AF32: Mes 29 | AG32: Mes 30 | AH32: Mes 31 | AI32: Mes 32 | AJ32: Mes 33 | AK32: Mes 34 | AL32: Mes 35 | AM32: Mes 36 | AN32: Mes 37 | AO32: Mes 38 | AP32: Mes 39 | AQ32: Mes 40 | AR32: Mes 41 | AS32: Mes 42 | AT32: Mes 43 | AU32: Mes 44 | AV32: Mes 45 | AW32: Mes 46 | AX32: Mes 47 | AY32: Mes 48 | AZ32: Mes 49 | BA32: Mes 50 | BB32: Mes 51 | BC32: Mes 52 | BD32: Mes 53 | BE32: Mes 54 | BF32: Mes 55 | BG32: Mes 56 | BH32: Mes 57 | BI32: Mes 58 | BJ32: Mes 59 | BK32: Mes 60
A33: Ingresos por Actividades de la Operación | C33: =C9-(C23) -> 0 | D33: =D9-(D23-C23) -> 400000 | E33: =E9-(E23-D23) -> 600000 | F33: =F9-(F23-E23) -> 880000 | G33: =G9-(G23-F23) -> 1200000 | H33: =H9-(H23-G23) -> 1520000 | I33: =I9-(I23-H23) -> 1800000 | J33: =J9-(J23-I23) -> 2200000 | K33: =K9-(K23-J23) -> 2600000 | ... BK33: =BK9-(BK23-BJ23) -> 0
A34: Egresos de efectivo por Compras | C34: =(C10+C24-B24)-(C25-B25) -> 0 | D34: =(D10+D24-C24)-(D25-C25) -> 5612170.3 | E34: =(E10+E24-D24)-(E25-D25) -> 5615490.3 | F34: =(F10+F24-E24)-(F25-E25) -> 5620138.3 | G34: =(G10+G24-F24)-(G25-F25) -> 5625450.3 | H34: =(H10+H24-G24)-(H25-G25) -> 5630762.3 | I34: =(I10+I24-H24)-(I25-H25) -> 5635410.3 | J34: =(J10+J24-I24)-(J25-I25) -> 5745800.3 | ... BK34: =(BK10+BK24-BJ24)-(BK25-BJ25) -> 0
A35: Egresos de efectivo por Gastos | C35: =(C12+C18+C13)-(C29-B29) -> 2382000 | D35: =(D12+D18+D13)-(D29-C29) -> -269250 | E35: =(E12+E18+E13)-(E29-D29) -> -269250 | F35: =(F12+F18+F13)-(F29-E29) -> -269250 | G35: =(G12+G18+G13)-(G29-F29) -> -269250 | H35: =(H12+H18+H13)-(H29-G29) -> -269250 | I35: =(I12+I18+I13)-(I29-H29) -> -269250 | J35: =(J12+J18+J13)-(J29-I29) -> 1480750 | ... BK35: =(BK12+BK18+BK13)-(BK29-BJ29) -> #REF!
A36: Saldo Operativo | C36: =C33-SUM(C34:C35) -> -2382000 | D36: =D33-SUM(D34:D35) -> -4942920.3 | E36: =E33-SUM(E34:E35) -> -4746240.3 | F36: =F33-SUM(F34:F35) -> -4470888.3 | G36: =G33-SUM(G34:G35) -> -4156200.3 | H36: =H33-SUM(H34:H35) -> -3841512.3 | I36: =I33-SUM(I34:I35) -> -3566160.3 | J36: =J33-SUM(J34:J35) -> -5026550.3 | ... BK36: =BK33-SUM(BK34:BK35) -> #REF!
A38: Ingresos por Actividades de Inversión
A39: Venta de Propiedad, Planta y Equipo
A40: Venta de Inversiones
A41: Egresos por Actividades de Inversión
A42: Compra de Propiedad, Planta y Equipo | C42: =INVERSIONES!C36 -> 0 | D42: =INVERSIONES!D36 -> 0 | E42: =INVERSIONES!E36 -> 0 | F42: =INVERSIONES!F36 -> 0 | G42: =INVERSIONES!G36 -> 0 | H42: =INVERSIONES!H36 -> 0 | I42: =INVERSIONES!I36 -> 0 | J42: =INVERSIONES!J36 -> 0 | ... BK42: =INVERSIONES!BK36 -> 0
A43: Compra de Inversiones
A44: Saldo de Inversiones | C44: =SUM(C39:C40)-SUM(C42:C43) -> 0 | D44: =SUM(D39:D40)-SUM(D42:D43) -> 0 | E44: =SUM(E39:E40)-SUM(E42:E43) -> 0 | F44: =SUM(F39:F40)-SUM(F42:F43) -> 0 | G44: =SUM(G39:G40)-SUM(G42:G43) -> 0 | H44: =SUM(H39:H40)-SUM(H42:H43) -> 0 | I44: =SUM(I39:I40)-SUM(I42:I43) -> 0 | J44: =SUM(J39:J40)-SUM(J42:J43) -> 0 | ... BK44: =SUM(BK39:BK40)-SUM(BK42:BK43) -> 0
A46: Ingresos por Actividades de Financiación
